Workbook

Sheet README
B2: Atelier Verde SAS — fictional dataset for a 13-week cash forecast
B3: Best Case Study Competition 2026 · Case 4: Financial Navigator by A352 · Data as at Friday 9 October 2026, 18:00
B4: ⚠ FICTIONAL DATA | C4: Every company, person, customer, supplier, bank, amount and date in this workbook is invented and simulated for the case study. Any resemblance to real entities is coincidental. Names of real public bodies or tax schemes (URSSAF, DGFiP, Chorus Pro, LCR, CA3) are used only to make the French payment calendar realistic.
B6: 1. Company overview
B7: Legal form & location | C7: SAS (simplified joint-stock company), workshop and offices in Villeurbanne, Lyon metropolitan area, France. Founded 2014 by two cabinet-makers; family-owned.
B8: What it does | C8: Designs and manufactures eco-designed furniture for workplaces and hotels: solid-oak and FSC birch-plywood desks, meeting tables, storage, acoustic felt panels and booths, and hotel-room furniture. Everything is made to order in its own workshop (CNC machining, sanding, water-based finishing, assembly).
B9: People | C9: 38 full-time employees: 26 in production, 4 in design/engineering, 3 in installation logistics, 5 in sales and admin. Finance team of two: a CFO (part-time, shared with a sister company) and an accountant.
B10: Size (fictional) | C10: Revenue ≈ €6.7M ex VAT forecast for 2026 (growth ≈ 8%). EBITDA ≈ €0.53M (≈ 8%), net profit ≈ €0.19M (≈ 2.8%). Profitable every year, but thin margins and lumpy cash flows. See 'PnL_Monthly'.
B11: How it makes money | C11: Make-to-order: a customer orders, Atelier Verde buys materials about 4 weeks ahead, produces, delivers and invoices on delivery. Customers then pay 30–60 days after the invoice — often later. So the company pays for timber and wages ~2–3 months before it gets paid. Growth makes this gap bigger.
B12: Customer segments (share of 2026 revenue) | C12: • Office fit-out contractors ≈ 45% — design-and-build firms refurbishing offices; 45–60 day terms; usually pay 10–25 days late (they wait for their own client to pay). • Furniture distributors ≈ 24% — reliable; one pays by LCR (automatic bill of exchange) exactly on the due date. • Public sector ≈ 10% — a university (legal limit 30 days) and a public hospital (legal limit 50 days); invoices go through the Chorus Pro portal; in practice the university pays ~10 days late and the hospital ~20 days late. • Hospitality projects ≈ 10% — hotel groups refurbishing whole hotels; few but very large invoices billed by milestone: 30% at order, 40% on delivery, 30% after installation. • Export distributor (Belgium) ≈ 7% — intra-EU sale, no French VAT. • Direct corporate client ≈ 4%.
B13: Suppliers & costs | C13: Materials ≈ 44% of revenue. Biggest single supplier: Holzwerk Bayern GmbH (Germany, timber & plywood, 30-day terms, intra-EU so no VAT is paid). Others: steel frames, acoustic felt, hardware, finishes, transport. Staff costs ≈ €2.4M per year (≈ 36%). Rent for the workshop, energy, an equipment lease and a bank loan for a CNC machine.
B14: Seasonality | C14: Peak September–November (companies spend year-end budgets on office refits). Slump in August (workshop closed two weeks). Christmas closure 24 Dec – 3 Jan. December payroll includes a 13th-month bonus.
B15: Cash calendar (who gets paid when) | C15: Salaries: last business day of the month · Social charges and income tax withheld: 15th of the following month · VAT (monthly CA3 return): ~24th of the following month · Corporate tax instalments: 15 Mar/Jun/Sep/Dec · Rent and insurance: quarterly in advance · Loan: 5th · Equipment lease: 10th · Supplier payment run: every Thursday, on or just before each due date.
B16: Banking | C16: Two accounts (main account via EBICS, card account via PSD2) — the kind of multibank set-up Financial Navigator connects to. Overdraft facility €150k on the main account. CFO's minimum cash buffer: €100k (≈ two weeks of payroll and charges).
B18: 2. The situation on 9 October 2026
B19: Cash | C19: €381,241 across both accounts. Open customer invoices: €1.41M incl. VAT, of which €167k overdue (DSO ≈ 67 days).
B20: Profit looks fine | C20: Q4 2026 is forecast at ≈ €182k net profit (strong October–November deliveries).
B21: …but cash is under pressure | C21: • Lumen Hospitality Group owes €230,400 (Hôtel Lumen Annecy delivery milestone), due 13 Nov 2026; a further €172,800 installation invoice will be issued 30 Oct, due 29 Dec. • A €155,000 Holzwerk Bayern bill (winter timber pre-order + materials for the new Azur Cannes & Antibes hotel project) is due 20 Nov and will be paid on Thu 19 Nov. • December carries the 13th-month bonus (€72k), a corporate tax instalment and property tax. • A planned €34,560 deposit on a new edge-banding machine is due 25 Nov (can be deferred). • Nova Interiors is paying slower and slower (≈ 22 days late in 2025 → ≈ 34 days late in Q3 2026). • Two invoices are disputed (transport damage claim; a hospital invoice rejected for a missing PO number).
B22: Why the CFO wants a tool | C22: From the end of June 2025 cash stayed below the €100k buffer for five weeks, and in the week of 28 July 2025 it slipped into the overdraft (−€38.2k) without anyone seeing it coming: a dividend, payroll, VAT and timber bills went out while summer receipts slowed. The current forecast is a spreadsheet rebuilt by hand once a month.
B24: 3. Sheets in this workbook
B25: Assumptions | C25: Assumption register: every parameter used by the forecast, with source, owner, date and confidence. Blue cells are inputs you can change.
B26: Data_Dictionary | C26: Meaning of every column.
B27: Bank_Accounts | C27: Balances at 9 Oct 2026 — the forecast's starting point.
B28: Bank_Weekly | C28: Weekly opening/closing balances, Apr 2025 – 9 Oct 2026 (80 weeks). Used to back-test the forecast.
B29: Bank_Transactions | C29: Every bank movement, Apr 2025 – 9 Oct 2026 (bank feed).
B30: Customers | C30: Customer master data, plus calculated payment behaviour (average days late, open balance).
B31: AR_Invoices | C31: All customer invoices since Jan 2025: paid ones with payment date and days late; open ones with days overdue.
B32: Order_Book | C32: Invoices planned during the 13 forecast weeks (confirmed orders, project milestones, and pipeline at 80% probability).
B33: Suppliers / AP_Bills | C33: Supplier master and supplier bills since Jan 2025 (paid and open with scheduled payment date).
B34: Committed_Purchases | C34: Purchase orders already placed whose bills will be paid within the forecast window — incl. the €155k Holzwerk bill.
B35: Scheduled_Payments | C35: Payroll, social charges, VAT, taxes, rent, loan, lease, energy, card spending and planned capex in the window.
B36: VAT_Returns | C36: Monthly VAT returns (output VAT − deductible VAT = net payable).
... B43: ▶ Data_Sources | C43: What each data attribute is based on: French regulation, Banque de France statistics, or a stated assumption.
B45: 4. Conventions
B46: Colours | C46: Blue text = input/assumption you can edit · Black = data or formula · Green = formula linking to another sheet · Yellow fill = key assumption.
B47: Units | C47: Euros. 'incl_vat' = amount actually paid/received in cash (VAT included); 'ex_vat' = amount in the P&L.
B48: Weeks | C48: Monday–Sunday. Forecast week 1 = Mon 12 Oct 2026; week 13 ends Sun 10 Jan 2027.
B49: Generated with | C49: Python (pandas, numpy, openpyxl) simulation with a fixed random seed, by Claude (Anthropic) at the participant's request. Payment delays are drawn from per-customer distributions, so history behaves like a real company's: noisy, seasonal, with occasional long delays.

Sheet Forecast_13W
A1: Atelier Verde SAS — 13-week cash forecast (as at Fri 9 Oct 2026)
A2: Fictional data. Cash basis, amounts incl. VAT. Expected values (pipeline orders × probability). Edit blue cells in 'Assumptions' (e.g. S01 Lumen delay) and everything below recalculates.
A4: Week | C4: 1 | D4: 2 | E4: 3 | F4: 4 | G4: 5 | H4: 6 | I4: 7 | J4: 8 | K4: 9 | L4: 10 | M4: 11 | N4: 12 | O4: 13 | P4: 13-week total
A5: Week starting (Monday) | C5: =Assumptions!$C$2+7*(C$4-1) -> 46307 | D5: =Assumptions!$C$2+7*(D$4-1) -> 46314 | E5: =Assumptions!$C$2+7*(E$4-1) -> 46321 | F5: =Assumptions!$C$2+7*(F$4-1) -> 46328 | G5: =Assumptions!$C$2+7*(G$4-1) -> 46335 | H5: =Assumptions!$C$2+7*(H$4-1) -> 46342 | I5: =Assumptions!$C$2+7*(I$4-1) -> 46349 | J5: =Assumptions!$C$2+7*(J$4-1) -> 46356 | ... O5: =Assumptions!$C$2+7*(O$4-1) -> 46391
A6: Week ending (Sunday) | C6: =C5+6 -> 46313 | D6: =D5+6 -> 46320 | E6: =E5+6 -> 46327 | F6: =F5+6 -> 46334 | G6: =G5+6 -> 46341 | H6: =H5+6 -> 46348 | I6: =I5+6 -> 46355 | J6: =J5+6 -> 46362 | ... O6: =O5+6 -> 46397
A8: BASE CASE — customers pay with their usual delays
A9: Opening balance | B9: W1 = Assumptions A03 | C9: =Assumptions!$C$4 -> 381240.65 | D9: =C36 -> 282840.5 | E9: =D36 -> 449176.92 | F9: =E36 -> 100857 | G9: =F36 -> 170790.53 | H9: =G36 -> 253974.51 | I9: =H36 -> 118636.62 | J9: =I36 -> 343376.38 | K9: =J36 -> 164325.06 | ... O9: =N36 -> 219892.39
A10: Receipts
A11: Office fit-out contractor | B11: SUMIFS on Forecast_Lines | C11: =SUMIFS(Forecast_Lines!$J$4:$J$377,Forecast_Lines!$D$4:$D$377,"Receipt",Forecast_Lines!$E$4:$E$377,"Customer – Office fit-out contractor",Forecast_Lines!$U$4:$U$377,"Yes",Forecast_Lines!$O$4:$O$377,C$4) -> 11748 | D11: =SUMIFS(Forecast_Lines!$J$4:$J$377,Forecast_Lines!$D$4:$D$377,"Receipt",Forecast_Lines!$E$4:$E$377,"Customer – Office fit-out contractor",Forecast_Lines!$U$4:$U$377,"Yes",Forecast_Lines!$O$4:$O$377,D$4) -> 105012 | E11: =SUMIFS(Forecast_Lines!$J$4:$J$377,Forecast_Lines!$D$4:$D$377,"Receipt",Forecast_Lines!$E$4:$E$377,"Customer – Office fit-out contractor",Forecast_Lines!$U$4:$U$377,"Yes",Forecast_Lines!$O$4:$O$377,E$4) -> 28500 | F11: =SUMIFS(Forecast_Lines!$J$4:$J$377,Forecast_Lines!$D$4:$D$377,"Receipt",Forecast_Lines!$E$4:$E$377,"Customer – Office fit-out contractor",Forecast_Lines!$U$4:$U$377,"Yes",Forecast_Lines!$O$4:$O$377,F$4) -> 70368 | G11: =SUMIFS(Forecast_Lines!$J$4:$J$377,Forecast_Lines!$D$4:$D$377,"Receipt",Forecast_Lines!$E$4:$E$377,"Customer – Office fit-out contractor",Forecast_Lines!$U$4:$U$377,"Yes",Forecast_Lines!$O$4:$O$377,G$4) -> 43836 | H11: =SUMIFS(Forecast_Lines!$J$4:$J$377,Forecast_Lines!$D$4:$D$377,"Receipt",Forecast_Lines!$E$4:$E$377,"Customer – Office fit-out contractor",Forecast_Lines!$U$4:$U$377,"Yes",Forecast_Lines!$O$4:$O$377,H$4) -> 73788 | I11: =SUMIFS(Forecast_Lines!$J$4:$J$377,Forecast_Lines!$D$4:$D$377,"Receipt",Forecast_Lines!$E$4:$E$377,"Customer – Office fit-out contractor",Forecast_Lines!$U$4:$U$377,"Yes",Forecast_Lines!$O$4:$O$377,I$4) -> 77616 | J11: =SUMIFS(Forecast_Lines!$J$4:$J$377,Forecast_Lines!$D$4:$D$377,"Receipt",Forecast_Lines!$E$4:$E$377,"Customer – Office fit-out contractor",Forecast_Lines!$U$4:$U$377,"Yes",Forecast_Lines!$O$4:$O$377,J$4) -> 34728 | ... O11: =SUMIFS(Forecast_Lines!$J$4:$J$377,Forecast_Lines!$D$4:$D$377,"Receipt",Forecast_Lines!$E$4:$E$377,"Customer – Office fit-out contractor",Forecast_Lines!$U$4:$U$377,"Yes",Forecast_Lines!$O$4:$O$377,O$4) -> 82622.4 | P11: =SUM(C11:O11) -> 879614.4
A12: Furniture distributor | B12: SUMIFS on Forecast_Lines | C12: =SUMIFS(Forecast_Lines!$J$4:$J$377,Forecast_Lines!$D$4:$D$377,"Receipt",Forecast_Lines!$E$4:$E$377,"Customer – Furniture distributor",Forecast_Lines!$U$4:$U$377,"Yes",Forecast_Lines!$O$4:$O$377,C$4) -> 7836 | D12: =SUMIFS(Forecast_Lines!$J$4:$J$377,Forecast_Lines!$D$4:$D$377,"Receipt",Forecast_Lines!$E$4:$E$377,"Customer – Furniture distributor",Forecast_Lines!$U$4:$U$377,"Yes",Forecast_Lines!$O$4:$O$377,D$4) -> 49944 | E12: =SUMIFS(Forecast_Lines!$J$4:$J$377,Forecast_Lines!$D$4:$D$377,"Receipt",Forecast_Lines!$E$4:$E$377,"Customer – Furniture distributor",Forecast_Lines!$U$4:$U$377,"Yes",Forecast_Lines!$O$4:$O$377,E$4) -> 36456 | F12: =SUMIFS(Forecast_Lines!$J$4:$J$377,Forecast_Lines!$D$4:$D$377,"Receipt",Forecast_Lines!$E$4:$E$377,"Customer – Furniture distributor",Forecast_Lines!$U$4:$U$377,"Yes",Forecast_Lines!$O$4:$O$377,F$4) -> 47616 | G12: =SUMIFS(Forecast_Lines!$J$4:$J$377,Forecast_Lines!$D$4:$D$377,"Receipt",Forecast_Lines!$E$4:$E$377,"Customer – Furniture distributor",Forecast_Lines!$U$4:$U$377,"Yes",Forecast_Lines!$O$4:$O$377,G$4) -> 47196 | H12: =SUMIFS(Forecast_Lines!$J$4:$J$377,Forecast_Lines!$D$4:$D$377,"Receipt",Forecast_Lines!$E$4:$E$377,"Customer – Furniture distributor",Forecast_Lines!$U$4:$U$377,"Yes",Forecast_Lines!$O$4:$O$377,H$4) -> 23904 | I12: =SUMIFS(Forecast_Lines!$J$4:$J$377,Forecast_Lines!$D$4:$D$377,"Receipt",Forecast_Lines!$E$4:$E$377,"Customer – Furniture distributor",Forecast_Lines!$U$4:$U$377,"Yes",Forecast_Lines!$O$4:$O$377,I$4) -> 27588 | J12: =SUMIFS(Forecast_Lines!$J$4:$J$377,Forecast_Lines!$D$4:$D$377,"Receipt",Forecast_Lines!$E$4:$E$377,"Customer – Furniture distributor",Forecast_Lines!$U$4:$U$377,"Yes",Forecast_Lines!$O$4:$O$377,J$4) -> 42696 | ... O12: =SUMIFS(Forecast_Lines!$J$4:$J$377,Forecast_Lines!$D$4:$D$377,"Receipt",Forecast_Lines!$E$4:$E$377,"Customer – Furniture distributor",Forecast_Lines!$U$4:$U$377,"Yes",Forecast_Lines!$O$4:$O$377,O$4) -> 36216 | P12: =SUM(C12:O12) -> 508128
A13: Public sector | B13: SUMIFS on Forecast_Lines | C13: =SUMIFS(Forecast_Lines!$J$4:$J$377,Forecast_Lines!$D$4:$D$377,"Receipt",Forecast_Lines!$E$4:$E$377,"Customer – Public sector",Forecast_Lines!$U$4:$U$377,"Yes",Forecast_Lines!$O$4:$O$377,C$4) -> 0 | D13: =SUMIFS(Forecast_Lines!$J$4:$J$377,Forecast_Lines!$D$4:$D$377,"Receipt",Forecast_Lines!$E$4:$E$377,"Customer – Public sector",Forecast_Lines!$U$4:$U$377,"Yes",Forecast_Lines!$O$4:$O$377,D$4) -> 0 | E13: =SUMIFS(Forecast_Lines!$J$4:$J$377,Forecast_Lines!$D$4:$D$377,"Receipt",Forecast_Lines!$E$4:$E$377,"Customer – Public sector",Forecast_Lines!$U$4:$U$377,"Yes",Forecast_Lines!$O$4:$O$377,E$4) -> 14520 | F13: =SUMIFS(Forecast_Lines!$J$4:$J$377,Forecast_Lines!$D$4:$D$377,"Receipt",Forecast_Lines!$E$4:$E$377,"Customer – Public sector",Forecast_Lines!$U$4:$U$377,"Yes",Forecast_Lines!$O$4:$O$377,F$4) -> 29448 | G13: =SUMIFS(Forecast_Lines!$J$4:$J$377,Forecast_Lines!$D$4:$D$377,"Receipt",Forecast_Lines!$E$4:$E$377,"Customer – Public sector",Forecast_Lines!$U$4:$U$377,"Yes",Forecast_Lines!$O$4:$O$377,G$4) -> 0 | H13: =SUMIFS(Forecast_Lines!$J$4:$J$377,Forecast_Lines!$D$4:$D$377,"Receipt",Forecast_Lines!$E$4:$E$377,"Customer – Public sector",Forecast_Lines!$U$4:$U$377,"Yes",Forecast_Lines!$O$4:$O$377,H$4) -> 37440 | I13: =SUMIFS(Forecast_Lines!$J$4:$J$377,Forecast_Lines!$D$4:$D$377,"Receipt",Forecast_Lines!$E$4:$E$377,"Customer – Public sector",Forecast_Lines!$U$4:$U$377,"Yes",Forecast_Lines!$O$4:$O$377,I$4) -> 0 | J13: =SUMIFS(Forecast_Lines!$J$4:$J$377,Forecast_Lines!$D$4:$D$377,"Receipt",Forecast_Lines!$E$4:$E$377,"Customer – Public sector",Forecast_Lines!$U$4:$U$377,"Yes",Forecast_Lines!$O$4:$O$377,J$4) -> 8436 | ... O13: =SUMIFS(Forecast_Lines!$J$4:$J$377,Forecast_Lines!$D$4:$D$377,"Receipt",Forecast_Lines!$E$4:$E$377,"Customer – Public sector",Forecast_Lines!$U$4:$U$377,"Yes",Forecast_Lines!$O$4:$O$377,O$4) -> 17472 | P13: =SUM(C13:O13) -> 131364
A14: Public sector (hospital) | B14: SUMIFS on Forecast_Lines | C14: =SUMIFS(Forecast_Lines!$J$4:$J$377,Forecast_Lines!$D$4:$D$377,"Receipt",Forecast_Lines!$E$4:$E$377,"Customer – Public sector (hospital)",Forecast_Lines!$U$4:$U$377,"Yes",Forecast_Lines!$O$4:$O$377,C$4) -> 0 | D14: =SUMIFS(Forecast_Lines!$J$4:$J$377,Forecast_Lines!$D$4:$D$377,"Receipt",Forecast_Lines!$E$4:$E$377,"Customer – Public sector (hospital)",Forecast_Lines!$U$4:$U$377,"Yes",Forecast_Lines!$O$4:$O$377,D$4) -> 0 | E14: =SUMIFS(Forecast_Lines!$J$4:$J$377,Forecast_Lines!$D$4:$D$377,"Receipt",Forecast_Lines!$E$4:$E$377,"Customer – Public sector (hospital)",Forecast_Lines!$U$4:$U$377,"Yes",Forecast_Lines!$O$4:$O$377,E$4) -> 0 | F14: =SUMIFS(Forecast_Lines!$J$4:$J$377,Forecast_Lines!$D$4:$D$377,"Receipt",Forecast_Lines!$E$4:$E$377,"Customer – Public sector (hospital)",Forecast_Lines!$U$4:$U$377,"Yes",Forecast_Lines!$O$4:$O$377,F$4) -> 0 | G14: =SUMIFS(Forecast_Lines!$J$4:$J$377,Forecast_Lines!$D$4:$D$377,"Receipt",Forecast_Lines!$E$4:$E$377,"Customer – Public sector (hospital)",Forecast_Lines!$U$4:$U$377,"Yes",Forecast_Lines!$O$4:$O$377,G$4) -> 0 | H14: =SUMIFS(Forecast_Lines!$J$4:$J$377,Forecast_Lines!$D$4:$D$377,"Receipt",Forecast_Lines!$E$4:$E$377,"Customer – Public sector (hospital)",Forecast_Lines!$U$4:$U$377,"Yes",Forecast_Lines!$O$4:$O$377,H$4) -> 0 | I14: =SUMIFS(Forecast_Lines!$J$4:$J$377,Forecast_Lines!$D$4:$D$377,"Receipt",Forecast_Lines!$E$4:$E$377,"Customer – Public sector (hospital)",Forecast_Lines!$U$4:$U$377,"Yes",Forecast_Lines!$O$4:$O$377,I$4) -> 35172 | J14: =SUMIFS(Forecast_Lines!$J$4:$J$377,Forecast_Lines!$D$4:$D$377,"Receipt",Forecast_Lines!$E$4:$E$377,"Customer – Public sector (hospital)",Forecast_Lines!$U$4:$U$377,"Yes",Forecast_Lines!$O$4:$O$377,J$4) -> 0 | ... O14: =SUMIFS(Forecast_Lines!$J$4:$J$377,Forecast_Lines!$D$4:$D$377,"Receipt",Forecast_Lines!$E$4:$E$377,"Customer – Public sector (hospital)",Forecast_Lines!$U$4:$U$377,"Yes",Forecast_Lines!$O$4:$O$377,O$4) -> 31236 | P14: =SUM(C14:O14) -> 71880
A15: Hospitality (projects) | B15: SUMIFS on Forecast_Lines | C15: =SUMIFS(Forecast_Lines!$J$4:$J$377,Forecast_Lines!$D$4:$D$377,"Receipt",Forecast_Lines!$E$4:$E$377,"Customer – Hospitality (projects)",Forecast_Lines!$U$4:$U$377,"Yes",Forecast_Lines!$O$4:$O$377,C$4) -> 0 | D15: =SUMIFS(Forecast_Lines!$J$4:$J$377,Forecast_Lines!$D$4:$D$377,"Receipt",Forecast_Lines!$E$4:$E$377,"Customer – Hospitality (projects)",Forecast_Lines!$U$4:$U$377,"Yes",Forecast_Lines!$O$4:$O$377,D$4) -> 0 | E15: =SUMIFS(Forecast_Lines!$J$4:$J$377,Forecast_Lines!$D$4:$D$377,"Receipt",Forecast_Lines!$E$4:$E$377,"Customer – Hospitality (projects)",Forecast_Lines!$U$4:$U$377,"Yes",Forecast_Lines!$O$4:$O$377,E$4) -> 0 | F15: =SUMIFS(Forecast_Lines!$J$4:$J$377,Forecast_Lines!$D$4:$D$377,"Receipt",Forecast_Lines!$E$4:$E$377,"Customer – Hospitality (projects)",Forecast_Lines!$U$4:$U$377,"Yes",Forecast_Lines!$O$4:$O$377,F$4) -> 0 | G15: =SUMIFS(Forecast_Lines!$J$4:$J$377,Forecast_Lines!$D$4:$D$377,"Receipt",Forecast_Lines!$E$4:$E$377,"Customer – Hospitality (projects)",Forecast_Lines!$U$4:$U$377,"Yes",Forecast_Lines!$O$4:$O$377,G$4) -> 0 | H15: =SUMIFS(Forecast_Lines!$J$4:$J$377,Forecast_Lines!$D$4:$D$377,"Receipt",Forecast_Lines!$E$4:$E$377,"Customer – Hospitality (projects)",Forecast_Lines!$U$4:$U$377,"Yes",Forecast_Lines!$O$4:$O$377,H$4) -> 0 | I15: =SUMIFS(Forecast_Lines!$J$4:$J$377,Forecast_Lines!$D$4:$D$377,"Receipt",Forecast_Lines!$E$4:$E$377,"Customer – Hospitality (projects)",Forecast_Lines!$U$4:$U$377,"Yes",Forecast_Lines!$O$4:$O$377,I$4) -> 230400 | J15: =SUMIFS(Forecast_Lines!$J$4:$J$377,Forecast_Lines!$D$4:$D$377,"Receipt",Forecast_Lines!$E$4:$E$377,"Customer – Hospitality (projects)",Forecast_Lines!$U$4:$U$377,"Yes",Forecast_Lines!$O$4:$O$377,J$4) -> 0 | ... O15: =SUMIFS(Forecast_Lines!$J$4:$J$377,Forecast_Lines!$D$4:$D$377,"Receipt",Forecast_Lines!$E$4:$E$377,"Customer – Hospitality (projects)",Forecast_Lines!$U$4:$U$377,"Yes",Forecast_Lines!$O$4:$O$377,O$4) -> 0 | P15: =SUM(C15:O15) -> 360000
A16: Export distributor | B16: SUMIFS on Forecast_Lines | C16: =SUMIFS(Forecast_Lines!$J$4:$J$377,Forecast_Lines!$D$4:$D$377,"Receipt",Forecast_Lines!$E$4:$E$377,"Customer – Export distributor",Forecast_Lines!$U$4:$U$377,"Yes",Forecast_Lines!$O$4:$O$377,C$4) -> 21030 | D16: =SUMIFS(Forecast_Lines!$J$4:$J$377,Forecast_Lines!$D$4:$D$377,"Receipt",Forecast_Lines!$E$4:$E$377,"Customer – Export distributor",Forecast_Lines!$U$4:$U$377,"Yes",Forecast_Lines!$O$4:$O$377,D$4) -> 0 | E16: =SUMIFS(Forecast_Lines!$J$4:$J$377,Forecast_Lines!$D$4:$D$377,"Receipt",Forecast_Lines!$E$4:$E$377,"Customer – Export distributor",Forecast_Lines!$U$4:$U$377,"Yes",Forecast_Lines!$O$4:$O$377,E$4) -> 0 | F16: =SUMIFS(Forecast_Lines!$J$4:$J$377,Forecast_Lines!$D$4:$D$377,"Receipt",Forecast_Lines!$E$4:$E$377,"Customer – Export distributor",Forecast_Lines!$U$4:$U$377,"Yes",Forecast_Lines!$O$4:$O$377,F$4) -> 0 | G16: =SUMIFS(Forecast_Lines!$J$4:$J$377,Forecast_Lines!$D$4:$D$377,"Receipt",Forecast_Lines!$E$4:$E$377,"Customer – Export distributor",Forecast_Lines!$U$4:$U$377,"Yes",Forecast_Lines!$O$4:$O$377,G$4) -> 13160 | H16: =SUMIFS(Forecast_Lines!$J$4:$J$377,Forecast_Lines!$D$4:$D$377,"Receipt",Forecast_Lines!$E$4:$E$377,"Customer – Export distributor",Forecast_Lines!$U$4:$U$377,"Yes",Forecast_Lines!$O$4:$O$377,H$4) -> 13020 | I16: =SUMIFS(Forecast_Lines!$J$4:$J$377,Forecast_Lines!$D$4:$D$377,"Receipt",Forecast_Lines!$E$4:$E$377,"Customer – Export distributor",Forecast_Lines!$U$4:$U$377,"Yes",Forecast_Lines!$O$4:$O$377,I$4) -> 6820 | J16: =SUMIFS(Forecast_Lines!$J$4:$J$377,Forecast_Lines!$D$4:$D$377,"Receipt",Forecast_Lines!$E$4:$E$377,"Customer – Export distributor",Forecast_Lines!$U$4:$U$377,"Yes",Forecast_Lines!$O$4:$O$377,J$4) -> 10970 | ... O16: =SUMIFS(Forecast_Lines!$J$4:$J$377,Forecast_Lines!$D$4:$D$377,"Receipt",Forecast_Lines!$E$4:$E$377,"Customer – Export distributor",Forecast_Lines!$U$4:$U$377,"Yes",Forecast_Lines!$O$4:$O$377,O$4) -> 15980 | P16: =SUM(C16:O16) -> 126860
A17: Direct corporate client | B17: SUMIFS on Forecast_Lines | C17: =SUMIFS(Forecast_Lines!$J$4:$J$377,Forecast_Lines!$D$4:$D$377,"Receipt",Forecast_Lines!$E$4:$E$377,"Customer – Direct corporate client",Forecast_Lines!$U$4:$U$377,"Yes",Forecast_Lines!$O$4:$O$377,C$4) -> 2808 | D17: =SUMIFS(Forecast_Lines!$J$4:$J$377,Forecast_Lines!$D$4:$D$377,"Receipt",Forecast_Lines!$E$4:$E$377,"Customer – Direct corporate client",Forecast_Lines!$U$4:$U$377,"Yes",Forecast_Lines!$O$4:$O$377,D$4) -> 22092 | E17: =SUMIFS(Forecast_Lines!$J$4:$J$377,Forecast_Lines!$D$4:$D$377,"Receipt",Forecast_Lines!$E$4:$E$377,"Customer – Direct corporate client",Forecast_Lines!$U$4:$U$377,"Yes",Forecast_Lines!$O$4:$O$377,E$4) -> 11508 | F17: =SUMIFS(Forecast_Lines!$J$4:$J$377,Forecast_Lines!$D$4:$D$377,"Receipt",Forecast_Lines!$E$4:$E$377,"Customer – Direct corporate client",Forecast_Lines!$U$4:$U$377,"Yes",Forecast_Lines!$O$4:$O$377,F$4) -> 0 | G17: =SUMIFS(Forecast_Lines!$J$4:$J$377,Forecast_Lines!$D$4:$D$377,"Receipt",Forecast_Lines!$E$4:$E$377,"Customer – Direct corporate client",Forecast_Lines!$U$4:$U$377,"Yes",Forecast_Lines!$O$4:$O$377,G$4) -> 8004 | H17: =SUMIFS(Forecast_Lines!$J$4:$J$377,Forecast_Lines!$D$4:$D$377,"Receipt",Forecast_Lines!$E$4:$E$377,"Customer – Direct corporate client",Forecast_Lines!$U$4:$U$377,"Yes",Forecast_Lines!$O$4:$O$377,H$4) -> 7680 | I17: =SUMIFS(Forecast_Lines!$J$4:$J$377,Forecast_Lines!$D$4:$D$377,"Receipt",Forecast_Lines!$E$4:$E$377,"Customer – Direct corporate client",Forecast_Lines!$U$4:$U$377,"Yes",Forecast_Lines!$O$4:$O$377,I$4) -> 13416 | J17: =SUMIFS(Forecast_Lines!$J$4:$J$377,Forecast_Lines!$D$4:$D$377,"Receipt",Forecast_Lines!$E$4:$E$377,"Customer – Direct corporate client",Forecast_Lines!$U$4:$U$377,"Yes",Forecast_Lines!$O$4:$O$377,J$4) -> 3804 | ... O17: =SUMIFS(Forecast_Lines!$J$4:$J$377,Forecast_Lines!$D$4:$D$377,"Receipt",Forecast_Lines!$E$4:$E$377,"Customer – Direct corporate client",Forecast_Lines!$U$4:$U$377,"Yes",Forecast_Lines!$O$4:$O$377,O$4) -> 3753.6 | P17: =SUM(C17:O17) -> 108885.6
A18: Total receipts | C18: =SUM(C11:C17) -> 43422 | D18: =SUM(D11:D17) -> 177048 | E18: =SUM(E11:E17) -> 90984 | F18: =SUM(F11:F17) -> 147432 | G18: =SUM(G11:G17) -> 112196 | H18: =SUM(H11:H17) -> 155832 | I18: =SUM(I11:I17) -> 391012 | J18: =SUM(J11:J17) -> 100634 | ... O18: =SUM(O11:O17) -> 187280 | P18: =SUM(C18:O18) -> 2186732
A19: Payments
A20: Supplier payment | B20: SUMIFS on Forecast_Lines | C20: =SUMIFS(Forecast_Lines!$J$4:$J$377,Forecast_Lines!$D$4:$D$377,"Payment",Forecast_Lines!$E$4:$E$377,"Supplier payment",Forecast_Lines!$O$4:$O$377,C$4) -> -47282.15 | D20: =SUMIFS(Forecast_Lines!$J$4:$J$377,Forecast_Lines!$D$4:$D$377,"Payment",Forecast_Lines!$E$4:$E$377,"Supplier payment",Forecast_Lines!$O$4:$O$377,D$4) -> -6011.58 | E20: =SUMIFS(Forecast_Lines!$J$4:$J$377,Forecast_Lines!$D$4:$D$377,"Payment",Forecast_Lines!$E$4:$E$377,"Supplier payment",Forecast_Lines!$O$4:$O$377,E$4) -> -218823.92 | F20: =SUMIFS(Forecast_Lines!$J$4:$J$377,Forecast_Lines!$D$4:$D$377,"Payment",Forecast_Lines!$E$4:$E$377,"Supplier payment",Forecast_Lines!$O$4:$O$377,F$4) -> -61018.47 | G20: =SUMIFS(Forecast_Lines!$J$4:$J$377,Forecast_Lines!$D$4:$D$377,"Payment",Forecast_Lines!$E$4:$E$377,"Supplier payment",Forecast_Lines!$O$4:$O$377,G$4) -> -6312.02 | H20: =SUMIFS(Forecast_Lines!$J$4:$J$377,Forecast_Lines!$D$4:$D$377,"Payment",Forecast_Lines!$E$4:$E$377,"Supplier payment",Forecast_Lines!$O$4:$O$377,H$4) -> -200469.89 | I20: =SUMIFS(Forecast_Lines!$J$4:$J$377,Forecast_Lines!$D$4:$D$377,"Payment",Forecast_Lines!$E$4:$E$377,"Supplier payment",Forecast_Lines!$O$4:$O$377,I$4) -> -24992.24 | J20: =SUMIFS(Forecast_Lines!$J$4:$J$377,Forecast_Lines!$D$4:$D$377,"Payment",Forecast_Lines!$E$4:$E$377,"Supplier payment",Forecast_Lines!$O$4:$O$377,J$4) -> -166105.32 | ... O20: =SUMIFS(Forecast_Lines!$J$4:$J$377,Forecast_Lines!$D$4:$D$377,"Payment",Forecast_Lines!$E$4:$E$377,"Supplier payment",Forecast_Lines!$O$4:$O$377,O$4) -> -50387.76 | P20: =SUM(C20:O20) -> -1079808
A21: Payroll | B21: SUMIFS on Forecast_Lines | C21: =SUMIFS(Forecast_Lines!$J$4:$J$377,Forecast_Lines!$D$4:$D$377,"Payment",Forecast_Lines!$E$4:$E$377,"Payroll",Forecast_Lines!$O$4:$O$377,C$4) -> 0 | D21: =SUMIFS(Forecast_Lines!$J$4:$J$377,Forecast_Lines!$D$4:$D$377,"Payment",Forecast_Lines!$E$4:$E$377,"Payroll",Forecast_Lines!$O$4:$O$377,D$4) -> 0 | E21: =SUMIFS(Forecast_Lines!$J$4:$J$377,Forecast_Lines!$D$4:$D$377,"Payment",Forecast_Lines!$E$4:$E$377,"Payroll",Forecast_Lines!$O$4:$O$377,E$4) -> -106000 | F21: =SUMIFS(Forecast_Lines!$J$4:$J$377,Forecast_Lines!$D$4:$D$377,"Payment",Forecast_Lines!$E$4:$E$377,"Payroll",Forecast_Lines!$O$4:$O$377,F$4) -> 0 | G21: =SUMIFS(Forecast_Lines!$J$4:$J$377,Forecast_Lines!$D$4:$D$377,"Payment",Forecast_Lines!$E$4:$E$377,"Payroll",Forecast_Lines!$O$4:$O$377,G$4) -> 0 | H21: =SUMIFS(Forecast_Lines!$J$4:$J$377,Forecast_Lines!$D$4:$D$377,"Payment",Forecast_Lines!$E$4:$E$377,"Payroll",Forecast_Lines!$O$4:$O$377,H$4) -> 0 | I21: =SUMIFS(Forecast_Lines!$J$4:$J$377,Forecast_Lines!$D$4:$D$377,"Payment",Forecast_Lines!$E$4:$E$377,"Payroll",Forecast_Lines!$O$4:$O$377,I$4) -> 0 | J21: =SUMIFS(Forecast_Lines!$J$4:$J$377,Forecast_Lines!$D$4:$D$377,"Payment",Forecast_Lines!$E$4:$E$377,"Payroll",Forecast_Lines!$O$4:$O$377,J$4) -> -106000 | ... O21: =SUMIFS(Forecast_Lines!$J$4:$J$377,Forecast_Lines!$D$4:$D$377,"Payment",Forecast_Lines!$E$4:$E$377,"Payroll",Forecast_Lines!$O$4:$O$377,O$4) -> 0 | P21: =SUM(C21:O21) -> -390000
A22: VAT payment | B22: SUMIFS on Forecast_Lines | C22: =SUMIFS(Forecast_Lines!$J$4:$J$377,Forecast_Lines!$D$4:$D$377,"Payment",Forecast_Lines!$E$4:$E$377,"VAT payment",Forecast_Lines!$O$4:$O$377,C$4) -> 0 | D22: =SUMIFS(Forecast_Lines!$J$4:$J$377,Forecast_Lines!$D$4:$D$377,"Payment",Forecast_Lines!$E$4:$E$377,"VAT payment",Forecast_Lines!$O$4:$O$377,D$4) -> 0 | E22: =SUMIFS(Forecast_Lines!$J$4:$J$377,Forecast_Lines!$D$4:$D$377,"Payment",Forecast_Lines!$E$4:$E$377,"VAT payment",Forecast_Lines!$O$4:$O$377,E$4) -> -109780 | F22: =SUMIFS(Forecast_Lines!$J$4:$J$377,Forecast_Lines!$D$4:$D$377,"Payment",Forecast_Lines!$E$4:$E$377,"VAT payment",Forecast_Lines!$O$4:$O$377,F$4) -> 0 | G22: =SUMIFS(Forecast_Lines!$J$4:$J$377,Forecast_Lines!$D$4:$D$377,"Payment",Forecast_Lines!$E$4:$E$377,"VAT payment",Forecast_Lines!$O$4:$O$377,G$4) -> 0 | H22: =SUMIFS(Forecast_Lines!$J$4:$J$377,Forecast_Lines!$D$4:$D$377,"Payment",Forecast_Lines!$E$4:$E$377,"VAT payment",Forecast_Lines!$O$4:$O$377,H$4) -> 0 | I22: =SUMIFS(Forecast_Lines!$J$4:$J$377,Forecast_Lines!$D$4:$D$377,"Payment",Forecast_Lines!$E$4:$E$377,"VAT payment",Forecast_Lines!$O$4:$O$377,I$4) -> -102020 | J22: =SUMIFS(Forecast_Lines!$J$4:$J$377,Forecast_Lines!$D$4:$D$377,"Payment",Forecast_Lines!$E$4:$E$377,"VAT payment",Forecast_Lines!$O$4:$O$377,J$4) -> 0 | ... O22: =SUMIFS(Forecast_Lines!$J$4:$J$377,Forecast_Lines!$D$4:$D$377,"Payment",Forecast_Lines!$E$4:$E$377,"VAT payment",Forecast_Lines!$O$4:$O$377,O$4) -> 0 | P22: =SUM(C22:O22) -> -301220
A23: Social charges & income tax withheld | B23: SUMIFS on Forecast_Lines | C23: =SUMIFS(Forecast_Lines!$J$4:$J$377,Forecast_Lines!$D$4:$D$377,"Payment",Forecast_Lines!$E$4:$E$377,"Social charges & income tax withheld",Forecast_Lines!$O$4:$O$377,C$4) -> -86000 | D23: =SUMIFS(Forecast_Lines!$J$4:$J$377,Forecast_Lines!$D$4:$D$377,"Payment",Forecast_Lines!$E$4:$E$377,"Social charges & income tax withheld",Forecast_Lines!$O$4:$O$377,D$4) -> 0 | E23: =SUMIFS(Forecast_Lines!$J$4:$J$377,Forecast_Lines!$D$4:$D$377,"Payment",Forecast_Lines!$E$4:$E$377,"Social charges & income tax withheld",Forecast_Lines!$O$4:$O$377,E$4) -> 0 | F23: =SUMIFS(Forecast_Lines!$J$4:$J$377,Forecast_Lines!$D$4:$D$377,"Payment",Forecast_Lines!$E$4:$E$377,"Social charges & income tax withheld",Forecast_Lines!$O$4:$O$377,F$4) -> 0 | G23: =SUMIFS(Forecast_Lines!$J$4:$J$377,Forecast_Lines!$D$4:$D$377,"Payment",Forecast_Lines!$E$4:$E$377,"Social charges & income tax withheld",Forecast_Lines!$O$4:$O$377,G$4) -> 0 | H23: =SUMIFS(Forecast_Lines!$J$4:$J$377,Forecast_Lines!$D$4:$D$377,"Payment",Forecast_Lines!$E$4:$E$377,"Social charges & income tax withheld",Forecast_Lines!$O$4:$O$377,H$4) -> -86000 | I23: =SUMIFS(Forecast_Lines!$J$4:$J$377,Forecast_Lines!$D$4:$D$377,"Payment",Forecast_Lines!$E$4:$E$377,"Social charges & income tax withheld",Forecast_Lines!$O$4:$O$377,I$4) -> 0 | J23: =SUMIFS(Forecast_Lines!$J$4:$J$377,Forecast_Lines!$D$4:$D$377,"Payment",Forecast_Lines!$E$4:$E$377,"Social charges & income tax withheld",Forecast_Lines!$O$4:$O$377,J$4) -> 0 | ... O23: =SUMIFS(Forecast_Lines!$J$4:$J$377,Forecast_Lines!$D$4:$D$377,"Payment",Forecast_Lines!$E$4:$E$377,"Social charges & income tax withheld",Forecast_Lines!$O$4:$O$377,O$4) -> 0 | P23: =SUM(C23:O23) -> -258000
A24: Card & sundry spending | B24: SUMIFS on Forecast_Lines | C24: =SUMIFS(Forecast_Lines!$J$4:$J$377,Forecast_Lines!$D$4:$D$377,"Payment",Forecast_Lines!$E$4:$E$377,"Card & sundry spending",Forecast_Lines!$O$4:$O$377,C$4) -> -4700 | D24: =SUMIFS(Forecast_Lines!$J$4:$J$377,Forecast_Lines!$D$4:$D$377,"Payment",Forecast_Lines!$E$4:$E$377,"Card & sundry spending",Forecast_Lines!$O$4:$O$377,D$4) -> -4700 | E24: =SUMIFS(Forecast_Lines!$J$4:$J$377,Forecast_Lines!$D$4:$D$377,"Payment",Forecast_Lines!$E$4:$E$377,"Card & sundry spending",Forecast_Lines!$O$4:$O$377,E$4) -> -4700 | F24: =SUMIFS(Forecast_Lines!$J$4:$J$377,Forecast_Lines!$D$4:$D$377,"Payment",Forecast_Lines!$E$4:$E$377,"Card & sundry spending",Forecast_Lines!$O$4:$O$377,F$4) -> -4700 | G24: =SUMIFS(Forecast_Lines!$J$4:$J$377,Forecast_Lines!$D$4:$D$377,"Payment",Forecast_Lines!$E$4:$E$377,"Card & sundry spending",Forecast_Lines!$O$4:$O$377,G$4) -> -4700 | H24: =SUMIFS(Forecast_Lines!$J$4:$J$377,Forecast_Lines!$D$4:$D$377,"Payment",Forecast_Lines!$E$4:$E$377,"Card & sundry spending",Forecast_Lines!$O$4:$O$377,H$4) -> -4700 | I24: =SUMIFS(Forecast_Lines!$J$4:$J$377,Forecast_Lines!$D$4:$D$377,"Payment",Forecast_Lines!$E$4:$E$377,"Card & sundry spending",Forecast_Lines!$O$4:$O$377,I$4) -> -4700 | J24: =SUMIFS(Forecast_Lines!$J$4:$J$377,Forecast_Lines!$D$4:$D$377,"Payment",Forecast_Lines!$E$4:$E$377,"Card & sundry spending",Forecast_Lines!$O$4:$O$377,J$4) -> -4700 | ... O24: =SUMIFS(Forecast_Lines!$J$4:$J$377,Forecast_Lines!$D$4:$D$377,"Payment",Forecast_Lines!$E$4:$E$377,"Card & sundry spending",Forecast_Lines!$O$4:$O$377,O$4) -> -4700 | P24: =SUM(C24:O24) -> -58200
A25: Energy | B25: SUMIFS on Forecast_Lines | C25: =SUMIFS(Forecast_Lines!$J$4:$J$377,Forecast_Lines!$D$4:$D$377,"Payment",Forecast_Lines!$E$4:$E$377,"Energy",Forecast_Lines!$O$4:$O$377,C$4) -> 0 | D25: =SUMIFS(Forecast_Lines!$J$4:$J$377,Forecast_Lines!$D$4:$D$377,"Payment",Forecast_Lines!$E$4:$E$377,"Energy",Forecast_Lines!$O$4:$O$377,D$4) -> 0 | E25: =SUMIFS(Forecast_Lines!$J$4:$J$377,Forecast_Lines!$D$4:$D$377,"Payment",Forecast_Lines!$E$4:$E$377,"Energy",Forecast_Lines!$O$4:$O$377,E$4) -> 0 | F25: =SUMIFS(Forecast_Lines!$J$4:$J$377,Forecast_Lines!$D$4:$D$377,"Payment",Forecast_Lines!$E$4:$E$377,"Energy",Forecast_Lines!$O$4:$O$377,F$4) -> 0 | G25: =SUMIFS(Forecast_Lines!$J$4:$J$377,Forecast_Lines!$D$4:$D$377,"Payment",Forecast_Lines!$E$4:$E$377,"Energy",Forecast_Lines!$O$4:$O$377,G$4) -> -14160 | H25: =SUMIFS(Forecast_Lines!$J$4:$J$377,Forecast_Lines!$D$4:$D$377,"Payment",Forecast_Lines!$E$4:$E$377,"Energy",Forecast_Lines!$O$4:$O$377,H$4) -> 0 | I25: =SUMIFS(Forecast_Lines!$J$4:$J$377,Forecast_Lines!$D$4:$D$377,"Payment",Forecast_Lines!$E$4:$E$377,"Energy",Forecast_Lines!$O$4:$O$377,I$4) -> 0 | J25: =SUMIFS(Forecast_Lines!$J$4:$J$377,Forecast_Lines!$D$4:$D$377,"Payment",Forecast_Lines!$E$4:$E$377,"Energy",Forecast_Lines!$O$4:$O$377,J$4) -> 0 | ... O25: =SUMIFS(Forecast_Lines!$J$4:$J$377,Forecast_Lines!$D$4:$D$377,"Payment",Forecast_Lines!$E$4:$E$377,"Energy",Forecast_Lines!$O$4:$O$377,O$4) -> -14160 | P25: =SUM(C25:O25) -> -42480
A26: Capex (discretionary) | B26: SUMIFS on Forecast_Lines | C26: =SUMIFS(Forecast_Lines!$J$4:$J$377,Forecast_Lines!$D$4:$D$377,"Payment",Forecast_Lines!$E$4:$E$377,"Capex (discretionary)",Forecast_Lines!$O$4:$O$377,C$4) -> 0 | D26: =SUMIFS(Forecast_Lines!$J$4:$J$377,Forecast_Lines!$D$4:$D$377,"Payment",Forecast_Lines!$E$4:$E$377,"Capex (discretionary)",Forecast_Lines!$O$4:$O$377,D$4) -> 0 | E26: =SUMIFS(Forecast_Lines!$J$4:$J$377,Forecast_Lines!$D$4:$D$377,"Payment",Forecast_Lines!$E$4:$E$377,"Capex (discretionary)",Forecast_Lines!$O$4:$O$377,E$4) -> 0 | F26: =SUMIFS(Forecast_Lines!$J$4:$J$377,Forecast_Lines!$D$4:$D$377,"Payment",Forecast_Lines!$E$4:$E$377,"Capex (discretionary)",Forecast_Lines!$O$4:$O$377,F$4) -> 0 | G26: =SUMIFS(Forecast_Lines!$J$4:$J$377,Forecast_Lines!$D$4:$D$377,"Payment",Forecast_Lines!$E$4:$E$377,"Capex (discretionary)",Forecast_Lines!$O$4:$O$377,G$4) -> 0 | H26: =SUMIFS(Forecast_Lines!$J$4:$J$377,Forecast_Lines!$D$4:$D$377,"Payment",Forecast_Lines!$E$4:$E$377,"Capex (discretionary)",Forecast_Lines!$O$4:$O$377,H$4) -> 0 | I26: =SUMIFS(Forecast_Lines!$J$4:$J$377,Forecast_Lines!$D$4:$D$377,"Payment",Forecast_Lines!$E$4:$E$377,"Capex (discretionary)",Forecast_Lines!$O$4:$O$377,I$4) -> -34560 | J26: =SUMIFS(Forecast_Lines!$J$4:$J$377,Forecast_Lines!$D$4:$D$377,"Payment",Forecast_Lines!$E$4:$E$377,"Capex (discretionary)",Forecast_Lines!$O$4:$O$377,J$4) -> 0 | ... O26: =SUMIFS(Forecast_Lines!$J$4:$J$377,Forecast_Lines!$D$4:$D$377,"Payment",Forecast_Lines!$E$4:$E$377,"Capex (discretionary)",Forecast_Lines!$O$4:$O$377,O$4) -> 0 | P26: =SUM(C26:O26) -> -34560
A27: Bank loan repayment | B27: SUMIFS on Forecast_Lines | C27: =SUMIFS(Forecast_Lines!$J$4:$J$377,Forecast_Lines!$D$4:$D$377,"Payment",Forecast_Lines!$E$4:$E$377,"Bank loan repayment",Forecast_Lines!$O$4:$O$377,C$4) -> 0 | D27: =SUMIFS(Forecast_Lines!$J$4:$J$377,Forecast_Lines!$D$4:$D$377,"Payment",Forecast_Lines!$E$4:$E$377,"Bank loan repayment",Forecast_Lines!$O$4:$O$377,D$4) -> 0 | E27: =SUMIFS(Forecast_Lines!$J$4:$J$377,Forecast_Lines!$D$4:$D$377,"Payment",Forecast_Lines!$E$4:$E$377,"Bank loan repayment",Forecast_Lines!$O$4:$O$377,E$4) -> 0 | F27: =SUMIFS(Forecast_Lines!$J$4:$J$377,Forecast_Lines!$D$4:$D$377,"Payment",Forecast_Lines!$E$4:$E$377,"Bank loan repayment",Forecast_Lines!$O$4:$O$377,F$4) -> -8900 | G27: =SUMIFS(Forecast_Lines!$J$4:$J$377,Forecast_Lines!$D$4:$D$377,"Payment",Forecast_Lines!$E$4:$E$377,"Bank loan repayment",Forecast_Lines!$O$4:$O$377,G$4) -> 0 | H27: =SUMIFS(Forecast_Lines!$J$4:$J$377,Forecast_Lines!$D$4:$D$377,"Payment",Forecast_Lines!$E$4:$E$377,"Bank loan repayment",Forecast_Lines!$O$4:$O$377,H$4) -> 0 | I27: =SUMIFS(Forecast_Lines!$J$4:$J$377,Forecast_Lines!$D$4:$D$377,"Payment",Forecast_Lines!$E$4:$E$377,"Bank loan repayment",Forecast_Lines!$O$4:$O$377,I$4) -> 0 | J27: =SUMIFS(Forecast_Lines!$J$4:$J$377,Forecast_Lines!$D$4:$D$377,"Payment",Forecast_Lines!$E$4:$E$377,"Bank loan repayment",Forecast_Lines!$O$4:$O$377,J$4) -> 0 | ... O27: =SUMIFS(Forecast_Lines!$J$4:$J$377,Forecast_Lines!$D$4:$D$377,"Payment",Forecast_Lines!$E$4:$E$377,"Bank loan repayment",Forecast_Lines!$O$4:$O$377,O$4) -> -8900 | P27: =SUM(C27:O27) -> -26700
A28: Corporate income tax instalment | B28: SUMIFS on Forecast_Lines | C28: =SUMIFS(Forecast_Lines!$J$4:$J$377,Forecast_Lines!$D$4:$D$377,"Payment",Forecast_Lines!$E$4:$E$377,"Corporate income tax instalment",Forecast_Lines!$O$4:$O$377,C$4) -> 0 | D28: =SUMIFS(Forecast_Lines!$J$4:$J$377,Forecast_Lines!$D$4:$D$377,"Payment",Forecast_Lines!$E$4:$E$377,"Corporate income tax instalment",Forecast_Lines!$O$4:$O$377,D$4) -> 0 | E28: =SUMIFS(Forecast_Lines!$J$4:$J$377,Forecast_Lines!$D$4:$D$377,"Payment",Forecast_Lines!$E$4:$E$377,"Corporate income tax instalment",Forecast_Lines!$O$4:$O$377,E$4) -> 0 | F28: =SUMIFS(Forecast_Lines!$J$4:$J$377,Forecast_Lines!$D$4:$D$377,"Payment",Forecast_Lines!$E$4:$E$377,"Corporate income tax instalment",Forecast_Lines!$O$4:$O$377,F$4) -> 0 | G28: =SUMIFS(Forecast_Lines!$J$4:$J$377,Forecast_Lines!$D$4:$D$377,"Payment",Forecast_Lines!$E$4:$E$377,"Corporate income tax instalment",Forecast_Lines!$O$4:$O$377,G$4) -> 0 | H28: =SUMIFS(Forecast_Lines!$J$4:$J$377,Forecast_Lines!$D$4:$D$377,"Payment",Forecast_Lines!$E$4:$E$377,"Corporate income tax instalment",Forecast_Lines!$O$4:$O$377,H$4) -> 0 | I28: =SUMIFS(Forecast_Lines!$J$4:$J$377,Forecast_Lines!$D$4:$D$377,"Payment",Forecast_Lines!$E$4:$E$377,"Corporate income tax instalment",Forecast_Lines!$O$4:$O$377,I$4) -> 0 | J28: =SUMIFS(Forecast_Lines!$J$4:$J$377,Forecast_Lines!$D$4:$D$377,"Payment",Forecast_Lines!$E$4:$E$377,"Corporate income tax instalment",Forecast_Lines!$O$4:$O$377,J$4) -> 0 | ... O28: =SUMIFS(Forecast_Lines!$J$4:$J$377,Forecast_Lines!$D$4:$D$377,"Payment",Forecast_Lines!$E$4:$E$377,"Corporate income tax instalment",Forecast_Lines!$O$4:$O$377,O$4) -> 0 | P28: =SUM(C28:O28) -> -24500
A29: Rent | B29: SUMIFS on Forecast_Lines | C29: =SUMIFS(Forecast_Lines!$J$4:$J$377,Forecast_Lines!$D$4:$D$377,"Payment",Forecast_Lines!$E$4:$E$377,"Rent",Forecast_Lines!$O$4:$O$377,C$4) -> 0 | D29: =SUMIFS(Forecast_Lines!$J$4:$J$377,Forecast_Lines!$D$4:$D$377,"Payment",Forecast_Lines!$E$4:$E$377,"Rent",Forecast_Lines!$O$4:$O$377,D$4) -> 0 | E29: =SUMIFS(Forecast_Lines!$J$4:$J$377,Forecast_Lines!$D$4:$D$377,"Payment",Forecast_Lines!$E$4:$E$377,"Rent",Forecast_Lines!$O$4:$O$377,E$4) -> 0 | F29: =SUMIFS(Forecast_Lines!$J$4:$J$377,Forecast_Lines!$D$4:$D$377,"Payment",Forecast_Lines!$E$4:$E$377,"Rent",Forecast_Lines!$O$4:$O$377,F$4) -> 0 | G29: =SUMIFS(Forecast_Lines!$J$4:$J$377,Forecast_Lines!$D$4:$D$377,"Payment",Forecast_Lines!$E$4:$E$377,"Rent",Forecast_Lines!$O$4:$O$377,G$4) -> 0 | H29: =SUMIFS(Forecast_Lines!$J$4:$J$377,Forecast_Lines!$D$4:$D$377,"Payment",Forecast_Lines!$E$4:$E$377,"Rent",Forecast_Lines!$O$4:$O$377,H$4) -> 0 | I29: =SUMIFS(Forecast_Lines!$J$4:$J$377,Forecast_Lines!$D$4:$D$377,"Payment",Forecast_Lines!$E$4:$E$377,"Rent",Forecast_Lines!$O$4:$O$377,I$4) -> 0 | J29: =SUMIFS(Forecast_Lines!$J$4:$J$377,Forecast_Lines!$D$4:$D$377,"Payment",Forecast_Lines!$E$4:$E$377,"Rent",Forecast_Lines!$O$4:$O$377,J$4) -> 0 | ... O29: =SUMIFS(Forecast_Lines!$J$4:$J$377,Forecast_Lines!$D$4:$D$377,"Payment",Forecast_Lines!$E$4:$E$377,"Rent",Forecast_Lines!$O$4:$O$377,O$4) -> -23400 | P29: =SUM(C29:O29) -> -23400
A30: Equipment lease | B30: SUMIFS on Forecast_Lines | C30: =SUMIFS(Forecast_Lines!$J$4:$J$377,Forecast_Lines!$D$4:$D$377,"Payment",Forecast_Lines!$E$4:$E$377,"Equipment lease",Forecast_Lines!$O$4:$O$377,C$4) -> -3840 | D30: =SUMIFS(Forecast_Lines!$J$4:$J$377,Forecast_Lines!$D$4:$D$377,"Payment",Forecast_Lines!$E$4:$E$377,"Equipment lease",Forecast_Lines!$O$4:$O$377,D$4) -> 0 | E30: =SUMIFS(Forecast_Lines!$J$4:$J$377,Forecast_Lines!$D$4:$D$377,"Payment",Forecast_Lines!$E$4:$E$377,"Equipment lease",Forecast_Lines!$O$4:$O$377,E$4) -> 0 | F30: =SUMIFS(Forecast_Lines!$J$4:$J$377,Forecast_Lines!$D$4:$D$377,"Payment",Forecast_Lines!$E$4:$E$377,"Equipment lease",Forecast_Lines!$O$4:$O$377,F$4) -> 0 | G30: =SUMIFS(Forecast_Lines!$J$4:$J$377,Forecast_Lines!$D$4:$D$377,"Payment",Forecast_Lines!$E$4:$E$377,"Equipment lease",Forecast_Lines!$O$4:$O$377,G$4) -> -3840 | H30: =SUMIFS(Forecast_Lines!$J$4:$J$377,Forecast_Lines!$D$4:$D$377,"Payment",Forecast_Lines!$E$4:$E$377,"Equipment lease",Forecast_Lines!$O$4:$O$377,H$4) -> 0 | I30: =SUMIFS(Forecast_Lines!$J$4:$J$377,Forecast_Lines!$D$4:$D$377,"Payment",Forecast_Lines!$E$4:$E$377,"Equipment lease",Forecast_Lines!$O$4:$O$377,I$4) -> 0 | J30: =SUMIFS(Forecast_Lines!$J$4:$J$377,Forecast_Lines!$D$4:$D$377,"Payment",Forecast_Lines!$E$4:$E$377,"Equipment lease",Forecast_Lines!$O$4:$O$377,J$4) -> 0 | ... O30: =SUMIFS(Forecast_Lines!$J$4:$J$377,Forecast_Lines!$D$4:$D$377,"Payment",Forecast_Lines!$E$4:$E$377,"Equipment lease",Forecast_Lines!$O$4:$O$377,O$4) -> 0 | P30: =SUM(C30:O30) -> -11520
A31: IT, telecom & software | B31: SUMIFS on Forecast_Lines | C31: =SUMIFS(Forecast_Lines!$J$4:$J$377,Forecast_Lines!$D$4:$D$377,"Payment",Forecast_Lines!$E$4:$E$377,"IT, telecom & software",Forecast_Lines!$O$4:$O$377,C$4) -> 0 | D31: =SUMIFS(Forecast_Lines!$J$4:$J$377,Forecast_Lines!$D$4:$D$377,"Payment",Forecast_Lines!$E$4:$E$377,"IT, telecom & software",Forecast_Lines!$O$4:$O$377,D$4) -> 0 | E31: =SUMIFS(Forecast_Lines!$J$4:$J$377,Forecast_Lines!$D$4:$D$377,"Payment",Forecast_Lines!$E$4:$E$377,"IT, telecom & software",Forecast_Lines!$O$4:$O$377,E$4) -> 0 | F31: =SUMIFS(Forecast_Lines!$J$4:$J$377,Forecast_Lines!$D$4:$D$377,"Payment",Forecast_Lines!$E$4:$E$377,"IT, telecom & software",Forecast_Lines!$O$4:$O$377,F$4) -> -2880 | G31: =SUMIFS(Forecast_Lines!$J$4:$J$377,Forecast_Lines!$D$4:$D$377,"Payment",Forecast_Lines!$E$4:$E$377,"IT, telecom & software",Forecast_Lines!$O$4:$O$377,G$4) -> 0 | H31: =SUMIFS(Forecast_Lines!$J$4:$J$377,Forecast_Lines!$D$4:$D$377,"Payment",Forecast_Lines!$E$4:$E$377,"IT, telecom & software",Forecast_Lines!$O$4:$O$377,H$4) -> 0 | I31: =SUMIFS(Forecast_Lines!$J$4:$J$377,Forecast_Lines!$D$4:$D$377,"Payment",Forecast_Lines!$E$4:$E$377,"IT, telecom & software",Forecast_Lines!$O$4:$O$377,I$4) -> 0 | J31: =SUMIFS(Forecast_Lines!$J$4:$J$377,Forecast_Lines!$D$4:$D$377,"Payment",Forecast_Lines!$E$4:$E$377,"IT, telecom & software",Forecast_Lines!$O$4:$O$377,J$4) -> -2880 | ... O31: =SUMIFS(Forecast_Lines!$J$4:$J$377,Forecast_Lines!$D$4:$D$377,"Payment",Forecast_Lines!$E$4:$E$377,"IT, telecom & software",Forecast_Lines!$O$4:$O$377,O$4) -> -2880 | P31: =SUM(C31:O31) -> -8640
A32: Insurance | B32: SUMIFS on Forecast_Lines | C32: =SUMIFS(Forecast_Lines!$J$4:$J$377,Forecast_Lines!$D$4:$D$377,"Payment",Forecast_Lines!$E$4:$E$377,"Insurance",Forecast_Lines!$O$4:$O$377,C$4) -> 0 | D32: =SUMIFS(Forecast_Lines!$J$4:$J$377,Forecast_Lines!$D$4:$D$377,"Payment",Forecast_Lines!$E$4:$E$377,"Insurance",Forecast_Lines!$O$4:$O$377,D$4) -> 0 | E32: =SUMIFS(Forecast_Lines!$J$4:$J$377,Forecast_Lines!$D$4:$D$377,"Payment",Forecast_Lines!$E$4:$E$377,"Insurance",Forecast_Lines!$O$4:$O$377,E$4) -> 0 | F32: =SUMIFS(Forecast_Lines!$J$4:$J$377,Forecast_Lines!$D$4:$D$377,"Payment",Forecast_Lines!$E$4:$E$377,"Insurance",Forecast_Lines!$O$4:$O$377,F$4) -> 0 | G32: =SUMIFS(Forecast_Lines!$J$4:$J$377,Forecast_Lines!$D$4:$D$377,"Payment",Forecast_Lines!$E$4:$E$377,"Insurance",Forecast_Lines!$O$4:$O$377,G$4) -> 0 | H32: =SUMIFS(Forecast_Lines!$J$4:$J$377,Forecast_Lines!$D$4:$D$377,"Payment",Forecast_Lines!$E$4:$E$377,"Insurance",Forecast_Lines!$O$4:$O$377,H$4) -> 0 | I32: =SUMIFS(Forecast_Lines!$J$4:$J$377,Forecast_Lines!$D$4:$D$377,"Payment",Forecast_Lines!$E$4:$E$377,"Insurance",Forecast_Lines!$O$4:$O$377,I$4) -> 0 | J32: =SUMIFS(Forecast_Lines!$J$4:$J$377,Forecast_Lines!$D$4:$D$377,"Payment",Forecast_Lines!$E$4:$E$377,"Insurance",Forecast_Lines!$O$4:$O$377,J$4) -> 0 | ... O32: =SUMIFS(Forecast_Lines!$J$4:$J$377,Forecast_Lines!$D$4:$D$377,"Payment",Forecast_Lines!$E$4:$E$377,"Insurance",Forecast_Lines!$O$4:$O$377,O$4) -> -7800 | P32: =SUM(C32:O32) -> -7800
A33: Business property tax | B33: SUMIFS on Forecast_Lines | C33: =SUMIFS(Forecast_Lines!$J$4:$J$377,Forecast_Lines!$D$4:$D$377,"Payment",Forecast_Lines!$E$4:$E$377,"Business property tax",Forecast_Lines!$O$4:$O$377,C$4) -> 0 | D33: =SUMIFS(Forecast_Lines!$J$4:$J$377,Forecast_Lines!$D$4:$D$377,"Payment",Forecast_Lines!$E$4:$E$377,"Business property tax",Forecast_Lines!$O$4:$O$377,D$4) -> 0 | E33: =SUMIFS(Forecast_Lines!$J$4:$J$377,Forecast_Lines!$D$4:$D$377,"Payment",Forecast_Lines!$E$4:$E$377,"Business property tax",Forecast_Lines!$O$4:$O$377,E$4) -> 0 | F33: =SUMIFS(Forecast_Lines!$J$4:$J$377,Forecast_Lines!$D$4:$D$377,"Payment",Forecast_Lines!$E$4:$E$377,"Business property tax",Forecast_Lines!$O$4:$O$377,F$4) -> 0 | G33: =SUMIFS(Forecast_Lines!$J$4:$J$377,Forecast_Lines!$D$4:$D$377,"Payment",Forecast_Lines!$E$4:$E$377,"Business property tax",Forecast_Lines!$O$4:$O$377,G$4) -> 0 | H33: =SUMIFS(Forecast_Lines!$J$4:$J$377,Forecast_Lines!$D$4:$D$377,"Payment",Forecast_Lines!$E$4:$E$377,"Business property tax",Forecast_Lines!$O$4:$O$377,H$4) -> 0 | I33: =SUMIFS(Forecast_Lines!$J$4:$J$377,Forecast_Lines!$D$4:$D$377,"Payment",Forecast_Lines!$E$4:$E$377,"Business property tax",Forecast_Lines!$O$4:$O$377,I$4) -> 0 | J33: =SUMIFS(Forecast_Lines!$J$4:$J$377,Forecast_Lines!$D$4:$D$377,"Payment",Forecast_Lines!$E$4:$E$377,"Business property tax",Forecast_Lines!$O$4:$O$377,J$4) -> 0 | ... O33: =SUMIFS(Forecast_Lines!$J$4:$J$377,Forecast_Lines!$D$4:$D$377,"Payment",Forecast_Lines!$E$4:$E$377,"Business property tax",Forecast_Lines!$O$4:$O$377,O$4) -> 0 | P33: =SUM(C33:O33) -> -6200
A34: Total payments | C34: =SUM(C20:C33) -> -141822.15 | D34: =SUM(D20:D33) -> -10711.58 | E34: =SUM(E20:E33) -> -439303.92 | F34: =SUM(F20:F33) -> -77498.47 | G34: =SUM(G20:G33) -> -29012.02 | H34: =SUM(H20:H33) -> -291169.89 | I34: =SUM(I20:I33) -> -166272.24 | J34: =SUM(J20:J33) -> -279685.32 | ... O34: =SUM(O20:O33) -> -112227.76 | P34: =SUM(C34:O34) -> -2273028
A35: Net cash flow | C35: =C18+C34 -> -98400.15 | D35: =D18+D34 -> 166336.42 | E35: =E18+E34 -> -348319.92 | F35: =F18+F34 -> 69933.53 | G35: =G18+G34 -> 83183.98 | H35: =H18+H34 -> -135337.89 | I35: =I18+I34 -> 224739.76 | J35: =J18+J34 -> -179051.32 | ... O35: =O18+O34 -> 75052.24 | P35: =SUM(C35:O35) -> -86296.02
A36: CLOSING BALANCE — base | B36: opening + receipts + payments | C36: =C9+C35 -> 282840.5 | D36: =D9+D35 -> 449176.92 | E36: =E9+E35 -> 100857 | F36: =F9+F35 -> 170790.53 | G36: =G9+G35 -> 253974.51 | H36: =H9+H35 -> 118636.62 | I36: =I9+I35 -> 343376.38 | J36: =J9+J35 -> 164325.06 | ... O36: =O9+O35 -> 294944.63
A37: Minimum cash buffer | B37: Assumptions A04 | C37: =Assumptions!$C$5 -> 100000 | D37: =Assumptions!$C$5 -> 100000 | E37: =Assumptions!$C$5 -> 100000 | F37: =Assumptions!$C$5 -> 100000 | G37: =Assumptions!$C$5 -> 100000 | H37: =Assumptions!$C$5 -> 100000 | I37: =Assumptions!$C$5 -> 100000 | J37: =Assumptions!$C$5 -> 100000 | ... O37: =Assumptions!$C$5 -> 100000
A38: Headroom above buffer — base | C38: =C36-C37 -> 182840.5 | D38: =D36-D37 -> 349176.92 | E38: =E36-E37 -> 857 | F38: =F36-F37 -> 70790.53 | G38: =G36-G37 -> 153974.51 | H38: =H36-H37 -> 18636.62 | I38: =I36-I37 -> 243376.38 | J38: =J36-J37 -> 64325.06 | ... O38: =O36-O37 -> 194944.63
A39: Flag — base | C39: =IF(C36<-Assumptions!$C$6,"BEYOND OVERDRAFT",IF(C36<0,"OVERDRAFT",IF(C36<C37,"BELOW BUFFER","ok"))) -> ok | D39: =IF(D36<-Assumptions!$C$6,"BEYOND OVERDRAFT",IF(D36<0,"OVERDRAFT",IF(D36<D37,"BELOW BUFFER","ok"))) -> ok | E39: =IF(E36<-Assumptions!$C$6,"BEYOND OVERDRAFT",IF(E36<0,"OVERDRAFT",IF(E36<E37,"BELOW BUFFER","ok"))) -> ok | F39: =IF(F36<-Assumptions!$C$6,"BEYOND OVERDRAFT",IF(F36<0,"OVERDRAFT",IF(F36<F37,"BELOW BUFFER","ok"))) -> ok | G39: =IF(G36<-Assumptions!$C$6,"BEYOND OVERDRAFT",IF(G36<0,"OVERDRAFT",IF(G36<G37,"BELOW BUFFER","ok"))) -> ok | H39: =IF(H36<-Assumptions!$C$6,"BEYOND OVERDRAFT",IF(H36<0,"OVERDRAFT",IF(H36<H37,"BELOW BUFFER","ok"))) -> ok | I39: =IF(I36<-Assumptions!$C$6,"BEYOND OVERDRAFT",IF(I36<0,"OVERDRAFT",IF(I36<I37,"BELOW BUFFER","ok"))) -> ok | J39: =IF(J36<-Assumptions!$C$6,"BEYOND OVERDRAFT",IF(J36<0,"OVERDRAFT",IF(J36<J37,"BELOW BUFFER","ok"))) -> ok | ... O39: =IF(O36<-Assumptions!$C$6,"BEYOND OVERDRAFT",IF(O36<0,"OVERDRAFT",IF(O36<O37,"BELOW BUFFER","ok"))) -> ok
A41: SCENARIO S1 — Lumen Hospitality pays 45 days later than usual (Assumptions S01)
A42: Opening balance | C42: =Assumptions!$C$4 -> 381240.65 | D42: =C45 -> 282840.5 | E42: =D45 -> 449176.92 | F42: =E45 -> 100857 | G42: =F45 -> 170790.53 | H42: =G45 -> 253974.51 | I42: =H45 -> 118636.62 | J42: =I45 -> 112976.38 | K42: =J45 -> -66074.94 | ... O42: =N45 -> -10507.61
A43: Total receipts | B43: SUMIFS on Q | C43: =SUMIFS(Forecast_Lines!$J$4:$J$377,Forecast_Lines!$D$4:$D$377,"Receipt",Forecast_Lines!$U$4:$U$377,"Yes",Forecast_Lines!$Q$4:$Q$377,C$4) -> 43422 | D43: =SUMIFS(Forecast_Lines!$J$4:$J$377,Forecast_Lines!$D$4:$D$377,"Receipt",Forecast_Lines!$U$4:$U$377,"Yes",Forecast_Lines!$Q$4:$Q$377,D$4) -> 177048 | E43: =SUMIFS(Forecast_Lines!$J$4:$J$377,Forecast_Lines!$D$4:$D$377,"Receipt",Forecast_Lines!$U$4:$U$377,"Yes",Forecast_Lines!$Q$4:$Q$377,E$4) -> 90984 | F43: =SUMIFS(Forecast_Lines!$J$4:$J$377,Forecast_Lines!$D$4:$D$377,"Receipt",Forecast_Lines!$U$4:$U$377,"Yes",Forecast_Lines!$Q$4:$Q$377,F$4) -> 147432 | G43: =SUMIFS(Forecast_Lines!$J$4:$J$377,Forecast_Lines!$D$4:$D$377,"Receipt",Forecast_Lines!$U$4:$U$377,"Yes",Forecast_Lines!$Q$4:$Q$377,G$4) -> 112196 | H43: =SUMIFS(Forecast_Lines!$J$4:$J$377,Forecast_Lines!$D$4:$D$377,"Receipt",Forecast_Lines!$U$4:$U$377,"Yes",Forecast_Lines!$Q$4:$Q$377,H$4) -> 155832 | I43: =SUMIFS(Forecast_Lines!$J$4:$J$377,Forecast_Lines!$D$4:$D$377,"Receipt",Forecast_Lines!$U$4:$U$377,"Yes",Forecast_Lines!$Q$4:$Q$377,I$4) -> 160612 | J43: =SUMIFS(Forecast_Lines!$J$4:$J$377,Forecast_Lines!$D$4:$D$377,"Receipt",Forecast_Lines!$U$4:$U$377,"Yes",Forecast_Lines!$Q$4:$Q$377,J$4) -> 100634 | ... O43: =SUMIFS(Forecast_Lines!$J$4:$J$377,Forecast_Lines!$D$4:$D$377,"Receipt",Forecast_Lines!$U$4:$U$377,"Yes",Forecast_Lines!$Q$4:$Q$377,O$4) -> 187280 | P43: =SUM(C43:O43) -> 1956332
A44: Total payments | B44: same as base | C44: =SUMIFS(Forecast_Lines!$J$4:$J$377,Forecast_Lines!$D$4:$D$377,"Payment",Forecast_Lines!$Q$4:$Q$377,C$4) -> -141822.15 | D44: =SUMIFS(Forecast_Lines!$J$4:$J$377,Forecast_Lines!$D$4:$D$377,"Payment",Forecast_Lines!$Q$4:$Q$377,D$4) -> -10711.58 | E44: =SUMIFS(Forecast_Lines!$J$4:$J$377,Forecast_Lines!$D$4:$D$377,"Payment",Forecast_Lines!$Q$4:$Q$377,E$4) -> -439303.92 | F44: =SUMIFS(Forecast_Lines!$J$4:$J$377,Forecast_Lines!$D$4:$D$377,"Payment",Forecast_Lines!$Q$4:$Q$377,F$4) -> -77498.47 | G44: =SUMIFS(Forecast_Lines!$J$4:$J$377,Forecast_Lines!$D$4:$D$377,"Payment",Forecast_Lines!$Q$4:$Q$377,G$4) -> -29012.02 | H44: =SUMIFS(Forecast_Lines!$J$4:$J$377,Forecast_Lines!$D$4:$D$377,"Payment",Forecast_Lines!$Q$4:$Q$377,H$4) -> -291169.89 | I44: =SUMIFS(Forecast_Lines!$J$4:$J$377,Forecast_Lines!$D$4:$D$377,"Payment",Forecast_Lines!$Q$4:$Q$377,I$4) -> -166272.24 | J44: =SUMIFS(Forecast_Lines!$J$4:$J$377,Forecast_Lines!$D$4:$D$377,"Payment",Forecast_Lines!$Q$4:$Q$377,J$4) -> -279685.32 | ... O44: =SUMIFS(Forecast_Lines!$J$4:$J$377,Forecast_Lines!$D$4:$D$377,"Payment",Forecast_Lines!$Q$4:$Q$377,O$4) -> -112227.76 | P44: =SUM(C44:O44) -> -2273028
A45: CLOSING BALANCE — S1 | C45: =C42+C43+C44 -> 282840.5 | D45: =D42+D43+D44 -> 449176.92 | E45: =E42+E43+E44 -> 100857 | F45: =F42+F43+F44 -> 170790.53 | G45: =G42+G43+G44 -> 253974.51 | H45: =H42+H43+H44 -> 118636.62 | I45: =I42+I43+I44 -> 112976.38 | J45: =J42+J43+J44 -> -66074.94 | ... O45: =O42+O43+O44 -> 64544.63
A46: Difference vs base | C46: =C45-C36 -> 0 | D46: =D45-D36 -> 0 | E46: =E45-E36 -> 0 | F46: =F45-F36 -> 0 | G46: =G45-G36 -> 0 | H46: =H45-H36 -> 0 | I46: =I45-I36 -> -230400 | J46: =J45-J36 -> -230400 | ... O46: =O45-O36 -> -230400
A47: Flag — S1 | C47: =IF(C45<-Assumptions!$C$6,"BEYOND OVERDRAFT",IF(C45<0,"OVERDRAFT",IF(C45<Assumptions!$C$5,"BELOW BUFFER","ok"))) -> ok | D47: =IF(D45<-Assumptions!$C$6,"BEYOND OVERDRAFT",IF(D45<0,"OVERDRAFT",IF(D45<Assumptions!$C$5,"BELOW BUFFER","ok"))) -> ok | E47: =IF(E45<-Assumptions!$C$6,"BEYOND OVERDRAFT",IF(E45<0,"OVERDRAFT",IF(E45<Assumptions!$C$5,"BELOW BUFFER","ok"))) -> ok | F47: =IF(F45<-Assumptions!$C$6,"BEYOND OVERDRAFT",IF(F45<0,"OVERDRAFT",IF(F45<Assumptions!$C$5,"BELOW BUFFER","ok"))) -> ok | G47: =IF(G45<-Assumptions!$C$6,"BEYOND OVERDRAFT",IF(G45<0,"OVERDRAFT",IF(G45<Assumptions!$C$5,"BELOW BUFFER","ok"))) -> ok | H47: =IF(H45<-Assumptions!$C$6,"BEYOND OVERDRAFT",IF(H45<0,"OVERDRAFT",IF(H45<Assumptions!$C$5,"BELOW BUFFER","ok"))) -> ok | I47: =IF(I45<-Assumptions!$C$6,"BEYOND OVERDRAFT",IF(I45<0,"OVERDRAFT",IF(I45<Assumptions!$C$5,"BELOW BUFFER","ok"))) -> ok | J47: =IF(J45<-Assumptions!$C$6,"BEYOND OVERDRAFT",IF(J45<0,"OVERDRAFT",IF(J45<Assumptions!$C$5,"BELOW BUFFER","ok"))) -> OVERDRAFT | ... O47: =IF(O45<-Assumptions!$C$6,"BEYOND OVERDRAFT",IF(O45<0,"OVERDRAFT",IF(O45<Assumptions!$C$5,"BELOW BUFFER","ok"))) -> BELOW BUFFER
A48: Below buffer? (1 = yes) — S1 | B48: helper for first-breach week | C48: =IF(C45<Assumptions!$C$5,1,0) -> 0 | D48: =IF(D45<Assumptions!$C$5,1,0) -> 0 | E48: =IF(E45<Assumptions!$C$5,1,0) -> 0 | F48: =IF(F45<Assumptions!$C$5,1,0) -> 0 | G48: =IF(G45<Assumptions!$C$5,1,0) -> 0 | H48: =IF(H45<Assumptions!$C$5,1,0) -> 0 | I48: =IF(I45<Assumptions!$C$5,1,0) -> 0 | J48: =IF(J45<Assumptions!$C$5,1,0) -> 1 | ... O48: =IF(O45<Assumptions!$C$5,1,0) -> 1
A50: SCENARIO S2 — S1 + office fit-out contractors pay 15 days slower (Assumptions S02)
A51: Opening balance | C51: =Assumptions!$C$4 -> 381240.65 | D51: =C54 -> 271092.5 | E51: =D54 -> 332416.92 | F51: =E54 -> -32655 | G51: =F54 -> 33558.53 | H51: =G54 -> 139770.51 | I51: =H54 -> 1012.62 | J51: =I54 -> -38427.62 | K51: =J54 -> -200126.94 | ... O51: =N54 -> -197767.61
A52: Total receipts | B52: SUMIFS on S | C52: =SUMIFS(Forecast_Lines!$J$4:$J$377,Forecast_Lines!$D$4:$D$377,"Receipt",Forecast_Lines!$U$4:$U$377,"Yes",Forecast_Lines!$S$4:$S$377,C$4) -> 31674 | D52: =SUMIFS(Forecast_Lines!$J$4:$J$377,Forecast_Lines!$D$4:$D$377,"Receipt",Forecast_Lines!$U$4:$U$377,"Yes",Forecast_Lines!$S$4:$S$377,D$4) -> 72036 | E52: =SUMIFS(Forecast_Lines!$J$4:$J$377,Forecast_Lines!$D$4:$D$377,"Receipt",Forecast_Lines!$U$4:$U$377,"Yes",Forecast_Lines!$S$4:$S$377,E$4) -> 74232 | F52: =SUMIFS(Forecast_Lines!$J$4:$J$377,Forecast_Lines!$D$4:$D$377,"Receipt",Forecast_Lines!$U$4:$U$377,"Yes",Forecast_Lines!$S$4:$S$377,F$4) -> 143712 | G52: =SUMIFS(Forecast_Lines!$J$4:$J$377,Forecast_Lines!$D$4:$D$377,"Receipt",Forecast_Lines!$U$4:$U$377,"Yes",Forecast_Lines!$S$4:$S$377,G$4) -> 135224 | H52: =SUMIFS(Forecast_Lines!$J$4:$J$377,Forecast_Lines!$D$4:$D$377,"Receipt",Forecast_Lines!$U$4:$U$377,"Yes",Forecast_Lines!$S$4:$S$377,H$4) -> 152412 | I52: =SUMIFS(Forecast_Lines!$J$4:$J$377,Forecast_Lines!$D$4:$D$377,"Receipt",Forecast_Lines!$U$4:$U$377,"Yes",Forecast_Lines!$S$4:$S$377,I$4) -> 126832 | J52: =SUMIFS(Forecast_Lines!$J$4:$J$377,Forecast_Lines!$D$4:$D$377,"Receipt",Forecast_Lines!$U$4:$U$377,"Yes",Forecast_Lines!$S$4:$S$377,J$4) -> 117986 | ... O52: =SUMIFS(Forecast_Lines!$J$4:$J$377,Forecast_Lines!$D$4:$D$377,"Receipt",Forecast_Lines!$U$4:$U$377,"Yes",Forecast_Lines!$S$4:$S$377,O$4) -> 195917.6 | P52: =SUM(C52:O52) -> 1777709.6
A53: Total payments | B53: same as base | C53: =SUMIFS(Forecast_Lines!$J$4:$J$377,Forecast_Lines!$D$4:$D$377,"Payment",Forecast_Lines!$S$4:$S$377,C$4) -> -141822.15 | D53: =SUMIFS(Forecast_Lines!$J$4:$J$377,Forecast_Lines!$D$4:$D$377,"Payment",Forecast_Lines!$S$4:$S$377,D$4) -> -10711.58 | E53: =SUMIFS(Forecast_Lines!$J$4:$J$377,Forecast_Lines!$D$4:$D$377,"Payment",Forecast_Lines!$S$4:$S$377,E$4) -> -439303.92 | F53: =SUMIFS(Forecast_Lines!$J$4:$J$377,Forecast_Lines!$D$4:$D$377,"Payment",Forecast_Lines!$S$4:$S$377,F$4) -> -77498.47 | G53: =SUMIFS(Forecast_Lines!$J$4:$J$377,Forecast_Lines!$D$4:$D$377,"Payment",Forecast_Lines!$S$4:$S$377,G$4) -> -29012.02 | H53: =SUMIFS(Forecast_Lines!$J$4:$J$377,Forecast_Lines!$D$4:$D$377,"Payment",Forecast_Lines!$S$4:$S$377,H$4) -> -291169.89 | I53: =SUMIFS(Forecast_Lines!$J$4:$J$377,Forecast_Lines!$D$4:$D$377,"Payment",Forecast_Lines!$S$4:$S$377,I$4) -> -166272.24 | J53: =SUMIFS(Forecast_Lines!$J$4:$J$377,Forecast_Lines!$D$4:$D$377,"Payment",Forecast_Lines!$S$4:$S$377,J$4) -> -279685.32 | ... O53: =SUMIFS(Forecast_Lines!$J$4:$J$377,Forecast_Lines!$D$4:$D$377,"Payment",Forecast_Lines!$S$4:$S$377,O$4) -> -112227.76 | P53: =SUM(C53:O53) -> -2273028
A54: CLOSING BALANCE — S2 | C54: =C51+C52+C53 -> 271092.5 | D54: =D51+D52+D53 -> 332416.92 | E54: =E51+E52+E53 -> -32655 | F54: =F51+F52+F53 -> 33558.53 | G54: =G51+G52+G53 -> 139770.51 | H54: =H51+H52+H53 -> 1012.62 | I54: =I51+I52+I53 -> -38427.62 | J54: =J51+J52+J53 -> -200126.94 | ... O54: =O51+O52+O53 -> -114077.77
A55: Difference vs base | C55: =C54-C36 -> -11748 | D55: =D54-D36 -> -116760 | E55: =E54-E36 -> -133512 | F55: =F54-F36 -> -137232 | G55: =G54-G36 -> -114204 | H55: =H54-H36 -> -117624 | I55: =I54-I36 -> -381804 | J55: =J54-J36 -> -364452 | ... O55: =O54-O36 -> -409022.4
A56: Flag — S2 | C56: =IF(C54<-Assumptions!$C$6,"BEYOND OVERDRAFT",IF(C54<0,"OVERDRAFT",IF(C54<Assumptions!$C$5,"BELOW BUFFER","ok"))) -> ok | D56: =IF(D54<-Assumptions!$C$6,"BEYOND OVERDRAFT",IF(D54<0,"OVERDRAFT",IF(D54<Assumptions!$C$5,"BELOW BUFFER","ok"))) -> ok | E56: =IF(E54<-Assumptions!$C$6,"BEYOND OVERDRAFT",IF(E54<0,"OVERDRAFT",IF(E54<Assumptions!$C$5,"BELOW BUFFER","ok"))) -> OVERDRAFT | F56: =IF(F54<-Assumptions!$C$6,"BEYOND OVERDRAFT",IF(F54<0,"OVERDRAFT",IF(F54<Assumptions!$C$5,"BELOW BUFFER","ok"))) -> BELOW BUFFER | G56: =IF(G54<-Assumptions!$C$6,"BEYOND OVERDRAFT",IF(G54<0,"OVERDRAFT",IF(G54<Assumptions!$C$5,"BELOW BUFFER","ok"))) -> ok | H56: =IF(H54<-Assumptions!$C$6,"BEYOND OVERDRAFT",IF(H54<0,"OVERDRAFT",IF(H54<Assumptions!$C$5,"BELOW BUFFER","ok"))) -> BELOW BUFFER | I56: =IF(I54<-Assumptions!$C$6,"BEYOND OVERDRAFT",IF(I54<0,"OVERDRAFT",IF(I54<Assumptions!$C$5,"BELOW BUFFER","ok"))) -> OVERDRAFT | J56: =IF(J54<-Assumptions!$C$6,"BEYOND OVERDRAFT",IF(J54<0,"OVERDRAFT",IF(J54<Assumptions!$C$5,"BELOW BUFFER","ok"))) -> BEYOND OVERDRAFT | ... O56: =IF(O54<-Assumptions!$C$6,"BEYOND OVERDRAFT",IF(O54<0,"OVERDRAFT",IF(O54<Assumptions!$C$5,"BELOW BUFFER","ok"))) -> OVERDRAFT
A57: Below buffer? (1 = yes) — S2 | B57: helper for first-breach week | C57: =IF(C54<Assumptions!$C$5,1,0) -> 0 | D57: =IF(D54<Assumptions!$C$5,1,0) -> 0 | E57: =IF(E54<Assumptions!$C$5,1,0) -> 1 | F57: =IF(F54<Assumptions!$C$5,1,0) -> 1 | G57: =IF(G54<Assumptions!$C$5,1,0) -> 0 | H57: =IF(H54<Assumptions!$C$5,1,0) -> 1 | I57: =IF(I54<Assumptions!$C$5,1,0) -> 1 | J57: =IF(J54<Assumptions!$C$5,1,0) -> 1 | ... O57: =IF(O54<Assumptions!$C$5,1,0) -> 1
A59: UNCERTAINTY — Monte Carlo, 4,000 simulations (values from the forecast run of 9 Oct 2026)
A60: Re-sampled: each customer's past delays, pipeline orders (80%), card spending ±15%, VAT estimates ±10%.
A61: Base closing — P10 (pessimistic) | B61: simulation output | C61: 312708 | D61: 421505 | E61: 78240 | F61: 131307 | G61: 249962 | H61: 100091 | I61: 303365 | J61: 169674 | K61: 216208 | L61: 247233 | M61: 243925 | N61: 92665 | O61: 180265
A62: Base closing — P50 (median) | B62: simulation output | C62: 341561 | D62: 459515 | E62: 125905 | F62: 182531 | G62: 299356 | H62: 152279 | I62: 353322 | J62: 218283 | K62: 263638 | L62: 313727 | M62: 315864 | N62: 214148 | O62: 319452
A63: Base closing — P90 (optimistic) | B63: simulation output | C63: 378223 | D63: 505876 | E63: 171788 | F63: 228454 | G63: 352090 | H63: 204503 | I63: 398801 | J63: 262272 | K63: 313696 | L63: 437705 | M63: 440364 | N63: 291621 | O63: 488236
A64: Base — probability of being below the buffer | B64: share of simulations | C64: 0 | D64: 0 | E64: 0.254 | F64: 0.015 | G64: 0 | H64: 0.099 | I64: 0 | J64: 0.001 | K64: 0 | L64: 0 | M64: 0 | N64: 0.122 | O64: 0.006
A65: S1 closing — P10 (pessimistic) | B65: simulation output | C65: 312708 | D65: 421505 | E65: 78240 | F65: 131307 | G65: 249962 | H65: 100091 | I65: 72965 | J65: -60726 | K65: -14192 | L65: 16833 | M65: 13525 | N65: -137735 | O65: -9022
A66: S1 closing — P50 (median) | B66: simulation output | C66: 341561 | D66: 459515 | E66: 125905 | F66: 182531 | G66: 299356 | H66: 152279 | I66: 122922 | J66: -12117 | K66: 33238 | L66: 83327 | M66: 85464 | N66: -16252 | O66: 206929
A67: S1 closing — P90 (optimistic) | B67: simulation output | C67: 378223 | D67: 505876 | E67: 171788 | F67: 228454 | G67: 352090 | H67: 204503 | I67: 168401 | J67: 31872 | K67: 83296 | L67: 207305 | M67: 209964 | N67: 61221 | O67: 346611
A68: S1 — probability of being below the buffer | B68: share of simulations | C68: 0 | D68: 0 | E68: 0.254 | F68: 0.015 | G68: 0 | H68: 0.099 | I68: 0.272 | J68: 0.998 | K68: 0.96 | L68: 0.578 | M68: 0.566 | N68: 0.98 | O68: 0.279
A70: CFO ACTION PACKAGES applied to S1 (values from the forecast run — see CFO_Actions)
A71: S1 + A1–A4 (no-regret package) | C71: 282840 | D71: 454997 | E71: 106677 | F71: 214735 | G71: 313879 | H71: 284145 | I71: 340956 | J71: 144649 | K71: 216101 | L71: 162864 | M71: 179246 | N71: 99664 | O71: 216777
A72: S1 + A1–A4 + A6 (invoice financing) | C72: 282840 | D72: 454997 | E72: 106677 | F72: 399055 | G72: 498199 | H72: 468465 | I72: 525276 | J72: 328969 | K72: 400421 | L72: 347184 | M72: 363566 | N72: 283984 | O72: 401097
A74: PROFIT ≠ CASH — Q4 2026
A75: Net profit Q4 2026 (accrual, P&L) | C75: =PnL_Monthly!O26 -> 182320.5
A76: Cash change over 13 weeks — base | C76: =O36-C9 -> -86296.02
A77: Cash change over 13 weeks — S1 | C77: =O45-Assumptions!$C$4 -> -316696.02
A78: Lowest weekly balance — base | C78: =MIN(C36:O36) -> 100857
A79: Lowest weekly balance — S1 | C79: =MIN(C45:O45) -> -66074.94
A80: Lowest weekly balance — S2 | C80: =MIN(C54:O54) -> -200126.94
A81: First week below buffer — S1 | C81: =IFERROR(MATCH(1,C48:O48,0),"none") -> 8
A82: Lowest balance vs overdraft limit — S2 | C82: =MIN(C54:O54)+Assumptions!$C$6 -> -50126.94
A83: Why they differ: Q4 profit counts sales when invoiced; cash waits 45–110 days for customers to pay, while timber, wages, VAT and taxes are paid on fixed dates.

Sheet Warning
B2: ⚠ Cash shortfall warning — raised Fri 9 Oct 2026
B3: Generated from the forecast run (template text filled with forecast numbers; every number links to Forecast_13W / Forecast_Lines). Advisory only — the CFO decides.
B5: Headline | C5: If Lumen Hospitality pays its €230,400 delivery invoice 45 days later than usual, cash falls below the €100k buffer in week 8 (week of 30 Nov 2026) and reaches −€66,075 — €166,075 short of the buffer and inside the overdraft.
B6: Lead time | C6: 7 weeks before the breach — enough time to act without emergency borrowing.
B7: Main cause | C7: Timing, not profitability: (1) the €230,400 Lumen receipt (invoice INV-2026-1149) moves from week 7 to after week 13; (2) it coincides with the €155,000 Holzwerk Bayern timber pre-order paid on 19 Nov (week 6); (3) week 8 itself is heavy: Holzwerk Bayern GmbH €122,068, Employees (38 FTE) €106,000, Aciers Rhône-Métal €38,640.
B8: Profit vs cash | C8: Q4 2026 still shows a net profit of ≈ €182k in the P&L: the sales are real and invoiced, but the cash has not arrived yet.
B9: How sure are we? | C9: In the base case the lowest point is €100,857 in week 3 — just above the buffer, with a 25% chance of dipping below it that week (41% chance of at least one week below the buffer in 13 weeks). If the Lumen delay happens, a breach is near-certain (100% of simulations). If contractors also slow down (S2), the overdraft is used in 100% of simulations and the balance reaches about −€200,127, beyond the €150k facility — so S2 cannot be solved by the overdraft alone.
B10: Watch-list | C10: Nova Interiors is paying slower (≈ 22 days late in 2025 → ≈ 34 days in Q3 2026). Two invoices are disputed (€32k) and excluded from expected receipts until resolved.
B11: What to do | C11: See CFO_Actions. The no-regret package A1–A4 keeps S1 at ≈ €100k (the buffer); adding A6 (finance the Lumen invoice) restores headroom. Nothing is executed without the CFO's decision.
B12: Assumptions behind this | C12: Assumptions A01–A12 and scenario S01 (45 days) — change them in 'Assumptions' to test other delays; Forecast_13W updates automatically.
B14: Live checks (formulas)
B15: First week below buffer (S1) | C15: =Forecast_13W!C81 -> 8
B16: Lowest balance (S1) | C16: =MIN(Forecast_13W!C45:O45) -> -66074.94
B17: Lowest balance (base) | C17: =MIN(Forecast_13W!C36:O36) -> 100857
B18: Lumen delay assumed (days) | C18: =Assumptions!$C$14 -> 45

Sheet CFO_Actions
A1: Options for the CFO to evaluate under scenario S1 — the tool proposes, the CFO decides. Nothing is sent to a bank, customer or supplier automatically.
A2: S1 lowest balance without action: €-66,075 (week 8). 'Effect on lowest balance' = how much the lowest weekly balance of S1 improves if the action alone is taken.
A4: id | B4: action | C4: what it means | D4: effect on lowest balance (€) | E4: new lowest balance (€) | F4: week of new low | G4: cost / trade-off | H4: confidence | I4: owner | J4: status | K4: CFO decision | L4: decided by | M4: date | N4: CFO comment
A5: A1 | B5: Get the two slowest contractors to pay on time | C5: Reminder 5 days before due date + phone follow-up for Bâtir Bureaux and Nova Interiors (they pay 22–34 days late); goal: half of their invoices due in the window paid on the due date. Late-payment penalties and the €40 fixed fee are in the terms of sale as leverage. | D5: 81840 | E5: 15765 | F5: 8 | G5: Staff time; relationship risk is low (penalties are contractual) | H5: Medium | I5: Accountant + sales director | J5: Proposed – awaiting CFO decision
A6: A2 | B6: Fix the rejected hospital invoice | C6: Re-submit CHU Vallée du Rhône invoice in Chorus Pro with the missing PO number (€16.8k). | D6: 16824 | E6: -49251 | F6: 8 | G6: None | H6: High | I6: Accountant | J6: Proposed – awaiting CFO decision
A7: A3 | B7: Defer the edge-bander deposit | C7: Move the €34.6k machine deposit from 25 Nov to January (delivery slips ~6 weeks). | D7: 34560 | E7: -31515 | F7: 8 | G7: Machine arrives later; possible price revision | H7: High | I7: CEO / CFO | J7: Proposed – awaiting CFO decision
A8: A4 | B8: Split the Holzwerk timber bill | C8: Ask Holzwerk Bayern to accept 50% on 19 Nov and 50% four weeks later. | D8: 55567 | E8: -10508 | F8: 12 | G8: May lose part of the 3% volume discount (≤ €4.7k) | H8: Medium | I8: CFO + purchasing | J8: Proposed – awaiting CFO decision
A9: A5 | B9: Early-payment offer to Lumen | C9: Offer Lumen a 2% discount if the €230k delivery invoice is paid on its usual date, and fix the installation snags fast. | D9: 166932 | E9: 100857 | F9: 3 | G9: ≈ €4.6k discount | H9: Low–Medium | I9: CEO (relationship owner) | J9: Proposed – awaiting CFO decision
A10: A6 | B10: Finance the Lumen invoice | C10: Use invoice financing (factoring) on the €230k Lumen invoice: ~80% advanced in week 4. | D10: 166932 | E10: 100857 | F10: 3 | G10: ≈ €3–4k fees + interest; customer may be notified | H10: High (if bank agrees) | I10: CFO + bank | J10: Proposed – awaiting CFO decision
A11: A7 | B11: Draw on the €150k overdraft | C11: Covers any balance below zero; does not restore the €100k buffer. | D11: 0 | E11: -66075 | F11: 8 | G11: ≈ 4.6% p.a. on amounts drawn (S2 stress: ≈ €937 for the quarter); signals stress to the bank | H11: High (facility in place) | I11: CFO | J11: Proposed – awaiting CFO decision
A13: Packages
B14: A1–A4 (no-regret: collections, dispute fix, defer capex, split timber bill) | E14: 99664 | F14: 12
B15: A1–A4 + A6 (also finance the Lumen invoice) | E15: 106677 | F15: 3
B16: Stress S2 with A1–A4 + A6 → remaining gap covered by A7 overdraft | E16: -26835
A18: Effects are estimates from the forecast engine (deterministic S1). Actions interact, so package effects are not the sum of single effects. Legend: yellow = CFO input.

Sheet Forecast_Lines
A1: Every cash line behind the 13-week forecast. Expected date (base) = due date + the customer's median days late over the last 12 months (for invoices already overdue: median of the longer past delays). Scenario dates and all week numbers are formulas linked to Assumptions.
A3: line_id | B3: source_sheet | C3: source_id | D3: flow | E3: category | F3: counterparty | G3: customer_id | H3: amount_eur | I3: probability | J3: expected_value_eur | K3: due_date | L3: days_late_now | M3: assumed_days_late | N3: expected_date | O3: week | P3: expected_date_S1 | Q3: week_S1 | R3: expected_date_S2 | S3: week_S2 | T3: status | U3: included_in_base | V3: description
A4: L0335 | B4: Scheduled_Payments | C4: PAY-001 | D4: Payment | E4: Equipment lease | F4: LeasEquip France | H4: -3840 | I4: 1 | J4: =H4*I4 -> -3840 | K4: 46307 | N4: 46307 | O4: =IF(INT((N4-Assumptions!$C$2)/7)+1>Assumptions!$C$3,"after W13",INT((N4-Assumptions!$C$2)/7)+1) -> 1 | P4: =IF(AND(D4="Receipt",G4="C01"),WORKDAY(N4+Assumptions!$C$14-1,1),N4) -> 46307 | Q4: =IF(INT((P4-Assumptions!$C$2)/7)+1>Assumptions!$C$3,"after W13",INT((P4-Assumptions!$C$2)/7)+1) -> 1 | R4: =IF(AND(D4="Receipt",OR(G4="C01",G4="C02",G4="C03",G4="C04",G4="C07")),WORKDAY(N4+IF(G4="C01",Assumptions!$C$14,Assumptions!$C$15)-1,1),N4) -> 46307 | S4: =IF(INT((R4-Assumptions!$C$2)/7)+1>Assumptions!$C$3,"after W13",INT((R4-Assumptions!$C$2)/7)+1) -> 1 | T4: Contractual / statutory | U4: Yes
A5: L0019 | B5: AR_Invoices | C5: INV-2026-1119 | D5: Receipt | E5: Customer – Furniture distributor | F5: Officea Distribution | G5: C05 | H5: 7836 | I5: 1 | J5: =H5*I5 -> 7836 | K5: 46306 | L5: 0 | M5: 0 | N5: 46307 | O5: =IF(INT((N5-Assumptions!$C$2)/7)+1>Assumptions!$C$3,"after W13",INT((N5-Assumptions!$C$2)/7)+1) -> 1 | P5: =IF(AND(D5="Receipt",G5="C01"),WORKDAY(N5+Assumptions!$C$14-1,1),N5) -> 46307 | Q5: =IF(INT((P5-Assumptions!$C$2)/7)+1>Assumptions!$C$3,"after W13",INT((P5-Assumptions!$C$2)/7)+1) -> 1 | R5: =IF(AND(D5="Receipt",OR(G5="C01",G5="C02",G5="C03",G5="C04",G5="C07")),WORKDAY(N5+IF(G5="C01",Assumptions!$C$14,Assumptions!$C$15)-1,1),N5) -> 46307 | S5: =IF(INT((R5-Assumptions!$C$2)/7)+1>Assumptions!$C$3,"after W13",INT((R5-Assumptions!$C$2)/7)+1) -> 1 | T5: Open | U5: Yes | V5: Furniture order
A6: L0040 | B6: AR_Invoices | C6: INV-2026-1142 | D6: Receipt | E6: Customer – Office fit-out contractor | F6: Studio Kaya Design | G6: C07 | H6: 8220 | I6: 1 | J6: =H6*I6 -> 8220 | K6: 46305 | L6: 0 | M6: 3 | N6: 46308 | O6: =IF(INT((N6-Assumptions!$C$2)/7)+1>Assumptions!$C$3,"after W13",INT((N6-Assumptions!$C$2)/7)+1) -> 1 | P6: =IF(AND(D6="Receipt",G6="C01"),WORKDAY(N6+Assumptions!$C$14-1,1),N6) -> 46308 | Q6: =IF(INT((P6-Assumptions!$C$2)/7)+1>Assumptions!$C$3,"after W13",INT((P6-Assumptions!$C$2)/7)+1) -> 1 | R6: =IF(AND(D6="Receipt",OR(G6="C01",G6="C02",G6="C03",G6="C04",G6="C07")),WORKDAY(N6+IF(G6="C01",Assumptions!$C$14,Assumptions!$C$15)-1,1),N6) -> 46323 | S6: =IF(INT((R6-Assumptions!$C$2)/7)+1>Assumptions!$C$3,"after W13",INT((R6-Assumptions!$C$2)/7)+1) -> 3 | T6: Open | U6: Yes | V6: Furniture order
A7: L0336 | B7: Scheduled_Payments | C7: PAY-002 | D7: Payment | E7: Card & sundry spending | F7: Fuel, travel, consumables | H7: -4700 | I7: 1 | J7: =H7*I7 -> -4700 | K7: 46309 | N7: 46309 | O7: =IF(INT((N7-Assumptions!$C$2)/7)+1>Assumptions!$C$3,"after W13",INT((N7-Assumptions!$C$2)/7)+1) -> 1 | P7: =IF(AND(D7="Receipt",G7="C01"),WORKDAY(N7+Assumptions!$C$14-1,1),N7) -> 46309 | Q7: =IF(INT((P7-Assumptions!$C$2)/7)+1>Assumptions!$C$3,"after W13",INT((P7-Assumptions!$C$2)/7)+1) -> 1 | R7: =IF(AND(D7="Receipt",OR(G7="C01",G7="C02",G7="C03",G7="C04",G7="C07")),WORKDAY(N7+IF(G7="C01",Assumptions!$C$14,Assumptions!$C$15)-1,1),N7) -> 46309 | S7: =IF(INT((R7-Assumptions!$C$2)/7)+1>Assumptions!$C$3,"after W13",INT((R7-Assumptions!$C$2)/7)+1) -> 1 | T7: Estimate (run-rate) | U7: Yes | V7: Run-rate estimate (avg of last 26 weeks, rounded)
A8: L0005 | B8: AR_Invoices | C8: INV-2026-1093 | D8: Receipt | E8: Customer – Export distributor | F8: Arkade Interiors SRL | G8: C12 | H8: 10400 | I8: 1 | J8: =H8*I8 -> 10400 | K8: 46301 | L8: 3 | M8: 8 | N8: 46309 | O8: =IF(INT((N8-Assumptions!$C$2)/7)+1>Assumptions!$C$3,"after W13",INT((N8-Assumptions!$C$2)/7)+1) -> 1 | P8: =IF(AND(D8="Receipt",G8="C01"),WORKDAY(N8+Assumptions!$C$14-1,1),N8) -> 46309 | Q8: =IF(INT((P8-Assumptions!$C$2)/7)+1>Assumptions!$C$3,"after W13",INT((P8-Assumptions!$C$2)/7)+1) -> 1 | R8: =IF(AND(D8="Receipt",OR(G8="C01",G8="C02",G8="C03",G8="C04",G8="C07")),WORKDAY(N8+IF(G8="C01",Assumptions!$C$14,Assumptions!$C$15)-1,1),N8) -> 46309 | S8: =IF(INT((R8-Assumptions!$C$2)/7)+1>Assumptions!$C$3,"after W13",INT((R8-Assumptions!$C$2)/7)+1) -> 1 | T8: Open | U8: Yes | V8: Furniture order
A9: L0006 | B9: AR_Invoices | C9: INV-2026-1094 | D9: Receipt | E9: Customer – Export distributor | F9: Arkade Interiors SRL | G9: C12 | H9: 10630 | I9: 1 | J9: =H9*I9 -> 10630 | K9: 46301 | L9: 3 | M9: 8 | N9: 46309 | O9: =IF(INT((N9-Assumptions!$C$2)/7)+1>Assumptions!$C$3,"after W13",INT((N9-Assumptions!$C$2)/7)+1) -> 1 | P9: =IF(AND(D9="Receipt",G9="C01"),WORKDAY(N9+Assumptions!$C$14-1,1),N9) -> 46309 | Q9: =IF(INT((P9-Assumptions!$C$2)/7)+1>Assumptions!$C$3,"after W13",INT((P9-Assumptions!$C$2)/7)+1) -> 1 | R9: =IF(AND(D9="Receipt",OR(G9="C01",G9="C02",G9="C03",G9="C04",G9="C07")),WORKDAY(N9+IF(G9="C01",Assumptions!$C$14,Assumptions!$C$15)-1,1),N9) -> 46309 | S9: =IF(INT((R9-Assumptions!$C$2)/7)+1>Assumptions!$C$3,"after W13",INT((R9-Assumptions!$C$2)/7)+1) -> 1 | T9: Open | U9: Yes | V9: Furniture order
A10: L0042 | B10: AR_Invoices | C10: INV-2026-1144 | D10: Receipt | E10: Customer – Office fit-out contractor | F10: Studio Kaya Design | G10: C07 | H10: 3528 | I10: 1 | J10: =H10*I10 -> 3528 | K10: 46306 | L10: 0 | M10: 3 | N10: 46309 | O10: =IF(INT((N10-Assumptions!$C$2)/7)+1>Assumptions!$C$3,"after W13",INT((N10-Assumptions!$C$2)/7)+1) -> 1 | P10: =IF(AND(D10="Receipt",G10="C01"),WORKDAY(N10+Assumptions!$C$14-1,1),N10) -> 46309 | Q10: =IF(INT((P10-Assumptions!$C$2)/7)+1>Assumptions!$C$3,"after W13",INT((P10-Assumptions!$C$2)/7)+1) -> 1 | R10: =IF(AND(D10="Receipt",OR(G10="C01",G10="C02",G10="C03",G10="C04",G10="C07")),WORKDAY(N10+IF(G10="C01",Assumptions!$C$14,Assumptions!$C$15)-1,1),N10) -> 46324 | S10: =IF(INT((R10-Assumptions!$C$2)/7)+1>Assumptions!$C$3,"after W13",INT((R10-Assumptions!$C$2)/7)+1) -> 3 | T10: Open | U10: Yes | V10: Furniture order
A11: L0303 | B11: AP_Bills | C11: BILL-2026-0218 | D11: Payment | E11: Supplier payment | F11: Aciers Rhône-Métal | H11: -41069.59 | I11: 1 | J11: =H11*I11 -> -41069.59 | K11: 46313 | N11: 46310 | O11: =IF(INT((N11-Assumptions!$C$2)/7)+1>Assumptions!$C$3,"after W13",INT((N11-Assumptions!$C$2)/7)+1) -> 1 | P11: =IF(AND(D11="Receipt",G11="C01"),WORKDAY(N11+Assumptions!$C$14-1,1),N11) -> 46310 | Q11: =IF(INT((P11-Assumptions!$C$2)/7)+1>Assumptions!$C$3,"after W13",INT((P11-Assumptions!$C$2)/7)+1) -> 1 | R11: =IF(AND(D11="Receipt",OR(G11="C01",G11="C02",G11="C03",G11="C04",G11="C07")),WORKDAY(N11+IF(G11="C01",Assumptions!$C$14,Assumptions!$C$15)-1,1),N11) -> 46310 | S11: =IF(INT((R11-Assumptions!$C$2)/7)+1>Assumptions!$C$3,"after W13",INT((R11-Assumptions!$C$2)/7)+1) -> 1 | T11: Open bill | U11: Yes | V11: Steel frames – 1st half
A12: L0305 | B12: AP_Bills | C12: BILL-2026-0223 | D12: Payment | E12: Supplier payment | F12: Quincaillerie Pro Est | H12: -6212.56 | I12: 1 | J12: =H12*I12 -> -6212.56 | K12: 46311 | N12: 46310 | O12: =IF(INT((N12-Assumptions!$C$2)/7)+1>Assumptions!$C$3,"after W13",INT((N12-Assumptions!$C$2)/7)+1) -> 1 | P12: =IF(AND(D12="Receipt",G12="C01"),WORKDAY(N12+Assumptions!$C$14-1,1),N12) -> 46310 | Q12: =IF(INT((P12-Assumptions!$C$2)/7)+1>Assumptions!$C$3,"after W13",INT((P12-Assumptions!$C$2)/7)+1) -> 1 | R12: =IF(AND(D12="Receipt",OR(G12="C01",G12="C02",G12="C03",G12="C04",G12="C07")),WORKDAY(N12+IF(G12="C01",Assumptions!$C$14,Assumptions!$C$15)-1,1),N12) -> 46310 | S12: =IF(INT((R12-Assumptions!$C$2)/7)+1>Assumptions!$C$3,"after W13",INT((R12-Assumptions!$C$2)/7)+1) -> 1 | T12: Open bill | U12: Yes | V12: Hardware & fittings
A13: L0337 | B13: Scheduled_Payments | C13: PAY-003 | D13: Payment | E13: Social charges & income tax withheld | F13: URSSAF / AGIRC-ARRCO / DGFiP (PAS) | H13: -86000 | I13: 1 | J13: =H13*I13 -> -86000 | K13: 46310 | N13: 46310 | O13: =IF(INT((N13-Assumptions!$C$2)/7)+1>Assumptions!$C$3,"after W13",INT((N13-Assumptions!$C$2)/7)+1) -> 1 | P13: =IF(AND(D13="Receipt",G13="C01"),WORKDAY(N13+Assumptions!$C$14-1,1),N13) -> 46310 | Q13: =IF(INT((P13-Assumptions!$C$2)/7)+1>Assumptions!$C$3,"after W13",INT((P13-Assumptions!$C$2)/7)+1) -> 1 | R13: =IF(AND(D13="Receipt",OR(G13="C01",G13="C02",G13="C03",G13="C04",G13="C07")),WORKDAY(N13+IF(G13="C01",Assumptions!$C$14,Assumptions!$C$15)-1,1),N13) -> 46310 | S13: =IF(INT((R13-Assumptions!$C$2)/7)+1>Assumptions!$C$3,"after W13",INT((R13-Assumptions!$C$2)/7)+1) -> 1 | T13: Contractual / statutory | U13: Yes | V13: for previous month's payroll
A14: L0020 | B14: AR_Invoices | C14: INV-2026-1120 | D14: Receipt | E14: Customer – Direct corporate client | F14: Hub & Desk Coworking SAS | G14: C11 | H14: 2808 | I14: 1 | J14: =H14*I14 -> 2808 | K14: 46296 | L14: 8 | M14: 15 | N14: 46311 | O14: =IF(INT((N14-Assumptions!$C$2)/7)+1>Assumptions!$C$3,"after W13",INT((N14-Assumptions!$C$2)/7)+1) -> 1 | P14: =IF(AND(D14="Receipt",G14="C01"),WORKDAY(N14+Assumptions!$C$14-1,1),N14) -> 46311 | Q14: =IF(INT((P14-Assumptions!$C$2)/7)+1>Assumptions!$C$3,"after W13",INT((P14-Assumptions!$C$2)/7)+1) -> 1 | R14: =IF(AND(D14="Receipt",OR(G14="C01",G14="C02",G14="C03",G14="C04",G14="C07")),WORKDAY(N14+IF(G14="C01",Assumptions!$C$14,Assumptions!$C$15)-1,1),N14) -> 46311 | S14: =IF(INT((R14-Assumptions!$C$2)/7)+1>Assumptions!$C$3,"after W13",INT((R14-Assumptions!$C$2)/7)+1) -> 1 | T14: Open | U14: Yes | V14: Furniture order
A15: L0002 | B15: AR_Invoices | C15: INV-2026-1068 | D15: Receipt | E15: Customer – Office fit-out contractor | F15: Bâtir Bureaux SAS | G15: C02 | H15: 14868 | I15: 1 | J15: =H15*I15 -> 14868 | K15: 46283 | L15: 21 | M15: 30 | N15: 46314 | O15: =IF(INT((N15-Assumptions!$C$2)/7)+1>Assumptions!$C$3,"after W13",INT((N15-Assumptions!$C$2)/7)+1) -> 2 | P15: =IF(AND(D15="Receipt",G15="C01"),WORKDAY(N15+Assumptions!$C$14-1,1),N15) -> 46314 | Q15: =IF(INT((P15-Assumptions!$C$2)/7)+1>Assumptions!$C$3,"after W13",INT((P15-Assumptions!$C$2)/7)+1) -> 2 | R15: =IF(AND(D15="Receipt",OR(G15="C01",G15="C02",G15="C03",G15="C04",G15="C07")),WORKDAY(N15+IF(G15="C01",Assumptions!$C$14,Assumptions!$C$15)-1,1),N15) -> 46329 | S15: =IF(INT((R15-Assumptions!$C$2)/7)+1>Assumptions!$C$3,"after W13",INT((R15-Assumptions!$C$2)/7)+1) -> 4 | T15: Open | U15: Yes | V15: Furniture order
A16: L0007 | B16: AR_Invoices | C16: INV-2026-1101 | D16: Receipt | E16: Customer – Office fit-out contractor | F16: Nova Interiors SARL | G16: C04 | H16: 15624 | I16: 1 | J16: =H16*I16 -> 15624 | K16: 46286 | L16: 18 | M16: 28 | N16: 46314 | O16: =IF(INT((N16-Assumptions!$C$2)/7)+1>Assumptions!$C$3,"after W13",INT((N16-Assumptions!$C$2)/7)+1) -> 2 | P16: =IF(AND(D16="Receipt",G16="C01"),WORKDAY(N16+Assumptions!$C$14-1,1),N16) -> 46314 | Q16: =IF(INT((P16-Assumptions!$C$2)/7)+1>Assumptions!$C$3,"after W13",INT((P16-Assumptions!$C$2)/7)+1) -> 2 | R16: =IF(AND(D16="Receipt",OR(G16="C01",G16="C02",G16="C03",G16="C04",G16="C07")),WORKDAY(N16+IF(G16="C01",Assumptions!$C$14,Assumptions!$C$15)-1,1),N16) -> 46329 | S16: =IF(INT((R16-Assumptions!$C$2)/7)+1>Assumptions!$C$3,"after W13",INT((R16-Assumptions!$C$2)/7)+1) -> 4 | T16: Open | U16: Yes | V16: Furniture order
A17: L0010 | B17: AR_Invoices | C17: INV-2026-1105 | D17: Receipt | E17: Customer – Furniture distributor | F17: Mobilier Pro Rhône | G17: C06 | H17: 4656 | I17: 1 | J17: =H17*I17 -> 4656 | K17: 46290 | L17: 14 | M17: 24.5 | N17: 46314 | O17: =IF(INT((N17-Assumptions!$C$2)/7)+1>Assumptions!$C$3,"after W13",INT((N17-Assumptions!$C$2)/7)+1) -> 2 | P17: =IF(AND(D17="Receipt",G17="C01"),WORKDAY(N17+Assumptions!$C$14-1,1),N17) -> 46314 | Q17: =IF(INT((P17-Assumptions!$C$2)/7)+1>Assumptions!$C$3,"after W13",INT((P17-Assumptions!$C$2)/7)+1) -> 2 | R17: =IF(AND(D17="Receipt",OR(G17="C01",G17="C02",G17="C03",G17="C04",G17="C07")),WORKDAY(N17+IF(G17="C01",Assumptions!$C$14,Assumptions!$C$15)-1,1),N17) -> 46314 | S17: =IF(INT((R17-Assumptions!$C$2)/7)+1>Assumptions!$C$3,"after W13",INT((R17-Assumptions!$C$2)/7)+1) -> 2 | T17: Open | U17: Yes | V17: Furniture order
A18: L0027 | B18: AR_Invoices | C18: INV-2026-1127 | D18: Receipt | E18: Customer – Direct corporate client | F18: Hub & Desk Coworking SAS | G18: C11 | H18: 11184 | I18: 1 | J18: =H18*I18 -> 11184 | K18: 46298 | L18: 6 | M18: 15 | N18: 46314 | O18: =IF(INT((N18-Assumptions!$C$2)/7)+1>Assumptions!$C$3,"after W13",INT((N18-Assumptions!$C$2)/7)+1) -> 2 | P18: =IF(AND(D18="Receipt",G18="C01"),WORKDAY(N18+Assumptions!$C$14-1,1),N18) -> 46314 | Q18: =IF(INT((P18-Assumptions!$C$2)/7)+1>Assumptions!$C$3,"after W13",INT((P18-Assumptions!$C$2)/7)+1) -> 2 | R18: =IF(AND(D18="Receipt",OR(G18="C01",G18="C02",G18="C03",G18="C04",G18="C07")),WORKDAY(N18+IF(G18="C01",Assumptions!$C$14,Assumptions!$C$15)-1,1),N18) -> 46314 | S18: =IF(INT((R18-Assumptions!$C$2)/7)+1>Assumptions!$C$3,"after W13",INT((R18-Assumptions!$C$2)/7)+1) -> 2 | T18: Open | U18: Yes | V18: Furniture order
A19: L0030 | B19: AR_Invoices | C19: INV-2026-1130 | D19: Receipt | E19: Customer – Furniture distributor | F19: Officea Distribution | G19: C05 | H19: 13284 | I19: 1 | J19: =H19*I19 -> 13284 | K19: 46314 | L19: 0 | M19: 0 | N19: 46314 | O19: =IF(INT((N19-Assumptions!$C$2)/7)+1>Assumptions!$C$3,"after W13",INT((N19-Assumptions!$C$2)/7)+1) -> 2 | P19: =IF(AND(D19="Receipt",G19="C01"),WORKDAY(N19+Assumptions!$C$14-1,1),N19) -> 46314 | Q19: =IF(INT((P19-Assumptions!$C$2)/7)+1>Assumptions!$C$3,"after W13",INT((P19-Assumptions!$C$2)/7)+1) -> 2 | R19: =IF(AND(D19="Receipt",OR(G19="C01",G19="C02",G19="C03",G19="C04",G19="C07")),WORKDAY(N19+IF(G19="C01",Assumptions!$C$14,Assumptions!$C$15)-1,1),N19) -> 46314 | S19: =IF(INT((R19-Assumptions!$C$2)/7)+1>Assumptions!$C$3,"after W13",INT((R19-Assumptions!$C$2)/7)+1) -> 2 | T19: Open | U19: Yes | V19: Furniture order
A20: L0031 | B20: AR_Invoices | C20: INV-2026-1131 | D20: Receipt | E20: Customer – Furniture distributor | F20: Officea Distribution | G20: C05 | H20: 6672 | I20: 1 | J20: =H20*I20 -> 6672 | K20: 46314 | L20: 0 | M20: 0 | N20: 46314 | O20: =IF(INT((N20-Assumptions!$C$2)/7)+1>Assumptions!$C$3,"after W13",INT((N20-Assumptions!$C$2)/7)+1) -> 2 | P20: =IF(AND(D20="Receipt",G20="C01"),WORKDAY(N20+Assumptions!$C$14-1,1),N20) -> 46314 | Q20: =IF(INT((P20-Assumptions!$C$2)/7)+1>Assumptions!$C$3,"after W13",INT((P20-Assumptions!$C$2)/7)+1) -> 2 | R20: =IF(AND(D20="Receipt",OR(G20="C01",G20="C02",G20="C03",G20="C04",G20="C07")),WORKDAY(N20+IF(G20="C01",Assumptions!$C$14,Assumptions!$C$15)-1,1),N20) -> 46314 | S20: =IF(INT((R20-Assumptions!$C$2)/7)+1>Assumptions!$C$3,"after W13",INT((R20-Assumptions!$C$2)/7)+1) -> 2 | T20: Open | U20: Yes | V20: Furniture order
A21: L0033 | B21: AR_Invoices | C21: INV-2026-1134 | D21: Receipt | E21: Customer – Furniture distributor | F21: Officea Distribution | G21: C05 | H21: 9876 | I21: 1 | J21: =H21*I21 -> 9876 | K21: 46314 | L21: 0 | M21: 0 | N21: 46314 | O21: =IF(INT((N21-Assumptions!$C$2)/7)+1>Assumptions!$C$3,"after W13",INT((N21-Assumptions!$C$2)/7)+1) -> 2 | P21: =IF(AND(D21="Receipt",G21="C01"),WORKDAY(N21+Assumptions!$C$14-1,1),N21) -> 46314 | Q21: =IF(INT((P21-Assumptions!$C$2)/7)+1>Assumptions!$C$3,"after W13",INT((P21-Assumptions!$C$2)/7)+1) -> 2 | R21: =IF(AND(D21="Receipt",OR(G21="C01",G21="C02",G21="C03",G21="C04",G21="C07")),WORKDAY(N21+IF(G21="C01",Assumptions!$C$14,Assumptions!$C$15)-1,1),N21) -> 46314 | S21: =IF(INT((R21-Assumptions!$C$2)/7)+1>Assumptions!$C$3,"after W13",INT((R21-Assumptions!$C$2)/7)+1) -> 2 | T21: Open | U21: Yes | V21: Furniture order
A22: L0036 | B22: AR_Invoices | C22: INV-2026-1137 | D22: Receipt | E22: Customer – Direct corporate client | F22: Hub & Desk Coworking SAS | G22: C11 | H22: 5856 | I22: 1 | J22: =H22*I22 -> 5856 | K22: 46302 | L22: 2 | M22: 12.5 | N22: 46314 | O22: =IF(INT((N22-Assumptions!$C$2)/7)+1>Assumptions!$C$3,"after W13",INT((N22-Assumptions!$C$2)/7)+1) -> 2 | P22: =IF(AND(D22="Receipt",G22="C01"),WORKDAY(N22+Assumptions!$C$14-1,1),N22) -> 46314 | Q22: =IF(INT((P22-Assumptions!$C$2)/7)+1>Assumptions!$C$3,"after W13",INT((P22-Assumptions!$C$2)/7)+1) -> 2 | R22: =IF(AND(D22="Receipt",OR(G22="C01",G22="C02",G22="C03",G22="C04",G22="C07")),WORKDAY(N22+IF(G22="C01",Assumptions!$C$14,Assumptions!$C$15)-1,1),N22) -> 46314 | S22: =IF(INT((R22-Assumptions!$C$2)/7)+1>Assumptions!$C$3,"after W13",INT((R22-Assumptions!$C$2)/7)+1) -> 2 | T22: Open | U22: Yes | V22: Furniture order
A23: L0012 | B23: AR_Invoices | C23: INV-2026-1108 | D23: Receipt | E23: Customer – Office fit-out contractor | F23: Espace & Co Aménagement | G23: C03 | H23: 19920 | I23: 1 | J23: =H23*I23 -> 19920 | K23: 46305 | L23: 0 | M23: 10 | N23: 46315 | O23: =IF(INT((N23-Assumptions!$C$2)/7)+1>Assumptions!$C$3,"after W13",INT((N23-Assumptions!$C$2)/7)+1) -> 2 | P23: =IF(AND(D23="Receipt",G23="C01"),WORKDAY(N23+Assumptions!$C$14-1,1),N23) -> 46315 | Q23: =IF(INT((P23-Assumptions!$C$2)/7)+1>Assumptions!$C$3,"after W13",INT((P23-Assumptions!$C$2)/7)+1) -> 2 | R23: =IF(AND(D23="Receipt",OR(G23="C01",G23="C02",G23="C03",G23="C04",G23="C07")),WORKDAY(N23+IF(G23="C01",Assumptions!$C$14,Assumptions!$C$15)-1,1),N23) -> 46330 | S23: =IF(INT((R23-Assumptions!$C$2)/7)+1>Assumptions!$C$3,"after W13",INT((R23-Assumptions!$C$2)/7)+1) -> 4 | T23: Open | U23: Yes | V23: Furniture order
A24: L0056 | B24: AR_Invoices | C24: INV-2026-1158 | D24: Receipt | E24: Customer – Office fit-out contractor | F24: Studio Kaya Design | G24: C07 | H24: 2616 | I24: 1 | J24: =H24*I24 -> 2616 | K24: 46312 | L24: 0 | M24: 3 | N24: 46315 | O24: =IF(INT((N24-Assumptions!$C$2)/7)+1>Assumptions!$C$3,"after W13",INT((N24-Assumptions!$C$2)/7)+1) -> 2 | P24: =IF(AND(D24="Receipt",G24="C01"),WORKDAY(N24+Assumptions!$C$14-1,1),N24) -> 46315 | Q24: =IF(INT((P24-Assumptions!$C$2)/7)+1>Assumptions!$C$3,"after W13",INT((P24-Assumptions!$C$2)/7)+1) -> 2 | R24: =IF(AND(D24="Receipt",OR(G24="C01",G24="C02",G24="C03",G24="C04",G24="C07")),WORKDAY(N24+IF(G24="C01",Assumptions!$C$14,Assumptions!$C$15)-1,1),N24) -> 46330 | S24: =IF(INT((R24-Assumptions!$C$2)/7)+1>Assumptions!$C$3,"after W13",INT((R24-Assumptions!$C$2)/7)+1) -> 4 | T24: Open | U24: Yes | V24: Furniture order
A25: L0057 | B25: AR_Invoices | C25: INV-2026-1159 | D25: Receipt | E25: Customer – Office fit-out contractor | F25: Studio Kaya Design | G25: C07 | H25: 2748 | I25: 1 | J25: =H25*I25 -> 2748 | K25: 46312 | L25: 0 | M25: 3 | N25: 46315 | O25: =IF(INT((N25-Assumptions!$C$2)/7)+1>Assumptions!$C$3,"after W13",INT((N25-Assumptions!$C$2)/7)+1) -> 2 | P25: =IF(AND(D25="Receipt",G25="C01"),WORKDAY(N25+Assumptions!$C$14-1,1),N25) -> 46315 | Q25: =IF(INT((P25-Assumptions!$C$2)/7)+1>Assumptions!$C$3,"after W13",INT((P25-Assumptions!$C$2)/7)+1) -> 2 | R25: =IF(AND(D25="Receipt",OR(G25="C01",G25="C02",G25="C03",G25="C04",G25="C07")),WORKDAY(N25+IF(G25="C01",Assumptions!$C$14,Assumptions!$C$15)-1,1),N25) -> 46330 | S25: =IF(INT((R25-Assumptions!$C$2)/7)+1>Assumptions!$C$3,"after W13",INT((R25-Assumptions!$C$2)/7)+1) -> 4 | T25: Open | U25: Yes | V25: Furniture order
A26: L0338 | B26: Scheduled_Payments | C26: PAY-004 | D26: Payment | E26: Card & sundry spending | F26: Fuel, travel, consumables | H26: -4700 | I26: 1 | J26: =H26*I26 -> -4700 | K26: 46316 | N26: 46316 | O26: =IF(INT((N26-Assumptions!$C$2)/7)+1>Assumptions!$C$3,"after W13",INT((N26-Assumptions!$C$2)/7)+1) -> 2 | P26: =IF(AND(D26="Receipt",G26="C01"),WORKDAY(N26+Assumptions!$C$14-1,1),N26) -> 46316 | Q26: =IF(INT((P26-Assumptions!$C$2)/7)+1>Assumptions!$C$3,"after W13",INT((P26-Assumptions!$C$2)/7)+1) -> 2 | R26: =IF(AND(D26="Receipt",OR(G26="C01",G26="C02",G26="C03",G26="C04",G26="C07")),WORKDAY(N26+IF(G26="C01",Assumptions!$C$14,Assumptions!$C$15)-1,1),N26) -> 46316 | S26: =IF(INT((R26-Assumptions!$C$2)/7)+1>Assumptions!$C$3,"after W13",INT((R26-Assumptions!$C$2)/7)+1) -> 2 | T26: Estimate (run-rate) | U26: Yes | V26: Run-rate estimate (avg of last 26 weeks, rounded)
A27: L0060 | B27: AR_Invoices | C27: INV-2026-1162 | D27: Receipt | E27: Customer – Office fit-out contractor | F27: Studio Kaya Design | G27: C07 | H27: 2916 | I27: 1 | J27: =H27*I27 -> 2916 | K27: 46313 | L27: 0 | M27: 3 | N27: 46316 | O27: =IF(INT((N27-Assumptions!$C$2)/7)+1>Assumptions!$C$3,"after W13",INT((N27-Assumptions!$C$2)/7)+1) -> 2 | P27: =IF(AND(D27="Receipt",G27="C01"),WORKDAY(N27+Assumptions!$C$14-1,1),N27) -> 46316 | Q27: =IF(INT((P27-Assumptions!$C$2)/7)+1>Assumptions!$C$3,"after W13",INT((P27-Assumptions!$C$2)/7)+1) -> 2 | R27: =IF(AND(D27="Receipt",OR(G27="C01",G27="C02",G27="C03",G27="C04",G27="C07")),WORKDAY(N27+IF(G27="C01",Assumptions!$C$14,Assumptions!$C$15)-1,1),N27) -> 46331 | S27: =IF(INT((R27-Assumptions!$C$2)/7)+1>Assumptions!$C$3,"after W13",INT((R27-Assumptions!$C$2)/7)+1) -> 4 | T27: Open | U27: Yes | V27: Furniture order
A28: L0064 | B28: AR_Invoices | C28: INV-2026-1166 | D28: Receipt | E28: Customer – Office fit-out contractor | F28: Studio Kaya Design | G28: C07 | H28: 7956 | I28: 1 | J28: =H28*I28 -> 7956 | K28: 46313 | L28: 0 | M28: 3 | N28: 46316 | O28: =IF(INT((N28-Assumptions!$C$2)/7)+1>Assumptions!$C$3,"after W13",INT((N28-Assumptions!$C$2)/7)+1) -> 2 | P28: =IF(AND(D28="Receipt",G28="C01"),WORKDAY(N28+Assumptions!$C$14-1,1),N28) -> 46316 | Q28: =IF(INT((P28-Assumptions!$C$2)/7)+1>Assumptions!$C$3,"after W13",INT((P28-Assumptions!$C$2)/7)+1) -> 2 | R28: =IF(AND(D28="Receipt",OR(G28="C01",G28="C02",G28="C03",G28="C04",G28="C07")),WORKDAY(N28+IF(G28="C01",Assumptions!$C$14,Assumptions!$C$15)-1,1),N28) -> 46331 | S28: =IF(INT((R28-Assumptions!$C$2)/7)+1>Assumptions!$C$3,"after W13",INT((R28-Assumptions!$C$2)/7)+1) -> 4 | T28: Open | U28: Yes | V28: Furniture order
A29: L0307 | B29: AP_Bills | C29: BILL-2026-0225 | D29: Payment | E29: Supplier payment | F29: Quincaillerie Pro Est | H29: -6011.58 | I29: 1 | J29: =H29*I29 -> -6011.58 | K29: 46318 | N29: 46317 | O29: =IF(INT((N29-Assumptions!$C$2)/7)+1>Assumptions!$C$3,"after W13",INT((N29-Assumptions!$C$2)/7)+1) -> 2 | P29: =IF(AND(D29="Receipt",G29="C01"),WORKDAY(N29+Assumptions!$C$14-1,1),N29) -> 46317 | Q29: =IF(INT((P29-Assumptions!$C$2)/7)+1>Assumptions!$C$3,"after W13",INT((P29-Assumptions!$C$2)/7)+1) -> 2 | R29: =IF(AND(D29="Receipt",OR(G29="C01",G29="C02",G29="C03",G29="C04",G29="C07")),WORKDAY(N29+IF(G29="C01",Assumptions!$C$14,Assumptions!$C$15)-1,1),N29) -> 46317 | S29: =IF(INT((R29-Assumptions!$C$2)/7)+1>Assumptions!$C$3,"after W13",INT((R29-Assumptions!$C$2)/7)+1) -> 2 | T29: Open bill | U29: Yes | V29: Hardware & fittings
A30: L0001 | B30: AR_Invoices | C30: INV-2026-1066 | D30: Receipt | E30: Customer – Office fit-out contractor | F30: Nova Interiors SARL | G30: C04 | H30: 15432 | I30: 1 | J30: =H30*I30 -> 15432 | K30: 46268 | L30: 36 | M30: 49 | N30: 46317 | O30: =IF(INT((N30-Assumptions!$C$2)/7)+1>Assumptions!$C$3,"after W13",INT((N30-Assumptions!$C$2)/7)+1) -> 2 | P30: =IF(AND(D30="Receipt",G30="C01"),WORKDAY(N30+Assumptions!$C$14-1,1),N30) -> 46317 | Q30: =IF(INT((P30-Assumptions!$C$2)/7)+1>Assumptions!$C$3,"after W13",INT((P30-Assumptions!$C$2)/7)+1) -> 2 | R30: =IF(AND(D30="Receipt",OR(G30="C01",G30="C02",G30="C03",G30="C04",G30="C07")),WORKDAY(N30+IF(G30="C01",Assumptions!$C$14,Assumptions!$C$15)-1,1),N30) -> 46332 | S30: =IF(INT((R30-Assumptions!$C$2)/7)+1>Assumptions!$C$3,"after W13",INT((R30-Assumptions!$C$2)/7)+1) -> 4 | T30: Open – disputed | U30: No – disputed (A12) | V30: Furniture order
A31: L0035 | B31: AR_Invoices | C31: INV-2026-1136 | D31: Receipt | E31: Customer – Furniture distributor | F31: Officea Distribution | G31: C05 | H31: 6756 | I31: 1 | J31: =H31*I31 -> 6756 | K31: 46317 | L31: 0 | M31: 0 | N31: 46317 | O31: =IF(INT((N31-Assumptions!$C$2)/7)+1>Assumptions!$C$3,"after W13",INT((N31-Assumptions!$C$2)/7)+1) -> 2 | P31: =IF(AND(D31="Receipt",G31="C01"),WORKDAY(N31+Assumptions!$C$14-1,1),N31) -> 46317 | Q31: =IF(INT((P31-Assumptions!$C$2)/7)+1>Assumptions!$C$3,"after W13",INT((P31-Assumptions!$C$2)/7)+1) -> 2 | R31: =IF(AND(D31="Receipt",OR(G31="C01",G31="C02",G31="C03",G31="C04",G31="C07")),WORKDAY(N31+IF(G31="C01",Assumptions!$C$14,Assumptions!$C$15)-1,1),N31) -> 46317 | S31: =IF(INT((R31-Assumptions!$C$2)/7)+1>Assumptions!$C$3,"after W13",INT((R31-Assumptions!$C$2)/7)+1) -> 2 | T31: Open | U31: Yes | V31: Furniture order
A32: L0003 | B32: AR_Invoices | C32: INV-2026-1085 | D32: Receipt | E32: Customer – Office fit-out contractor | F32: Bâtir Bureaux SAS | G32: C02 | H32: 15720 | I32: 1 | J32: =H32*I32 -> 15720 | K32: 46294 | L32: 10 | M32: 24 | N32: 46318 | O32: =IF(INT((N32-Assumptions!$C$2)/7)+1>Assumptions!$C$3,"after W13",INT((N32-Assumptions!$C$2)/7)+1) -> 2 | P32: =IF(AND(D32="Receipt",G32="C01"),WORKDAY(N32+Assumptions!$C$14-1,1),N32) -> 46318 | Q32: =IF(INT((P32-Assumptions!$C$2)/7)+1>Assumptions!$C$3,"after W13",INT((P32-Assumptions!$C$2)/7)+1) -> 2 | R32: =IF(AND(D32="Receipt",OR(G32="C01",G32="C02",G32="C03",G32="C04",G32="C07")),WORKDAY(N32+IF(G32="C01",Assumptions!$C$14,Assumptions!$C$15)-1,1),N32) -> 46335 | S32: =IF(INT((R32-Assumptions!$C$2)/7)+1>Assumptions!$C$3,"after W13",INT((R32-Assumptions!$C$2)/7)+1) -> 5 | T32: Open | U32: Yes | V32: Furniture order
A33: L0009 | B33: AR_Invoices | C33: INV-2026-1103 | D33: Receipt | E33: Customer – Office fit-out contractor | F33: Nova Interiors SARL | G33: C04 | H33: 11652 | I33: 1 | J33: =H33*I33 -> 11652 | K33: 46290 | L33: 14 | M33: 28 | N33: 46318 | O33: =IF(INT((N33-Assumptions!$C$2)/7)+1>Assumptions!$C$3,"after W13",INT((N33-Assumptions!$C$2)/7)+1) -> 2 | P33: =IF(AND(D33="Receipt",G33="C01"),WORKDAY(N33+Assumptions!$C$14-1,1),N33) -> 46318 | Q33: =IF(INT((P33-Assumptions!$C$2)/7)+1>Assumptions!$C$3,"after W13",INT((P33-Assumptions!$C$2)/7)+1) -> 2 | R33: =IF(AND(D33="Receipt",OR(G33="C01",G33="C02",G33="C03",G33="C04",G33="C07")),WORKDAY(N33+IF(G33="C01",Assumptions!$C$14,Assumptions!$C$15)-1,1),N33) -> 46335 | S33: =IF(INT((R33-Assumptions!$C$2)/7)+1>Assumptions!$C$3,"after W13",INT((R33-Assumptions!$C$2)/7)+1) -> 5 | T33: Open | U33: Yes | V33: Furniture order
A34: L0014 | B34: AR_Invoices | C34: INV-2026-1111 | D34: Receipt | E34: Customer – Direct corporate client | F34: Hub & Desk Coworking SAS | G34: C11 | H34: 5052 | I34: 1 | J34: =H34*I34 -> 5052 | K34: 46276 | L34: 28 | M34: 42 | N34: 46318 | O34: =IF(INT((N34-Assumptions!$C$2)/7)+1>Assumptions!$C$3,"after W13",INT((N34-Assumptions!$C$2)/7)+1) -> 2 | P34: =IF(AND(D34="Receipt",G34="C01"),WORKDAY(N34+Assumptions!$C$14-1,1),N34) -> 46318 | Q34: =IF(INT((P34-Assumptions!$C$2)/7)+1>Assumptions!$C$3,"after W13",INT((P34-Assumptions!$C$2)/7)+1) -> 2 | R34: =IF(AND(D34="Receipt",OR(G34="C01",G34="C02",G34="C03",G34="C04",G34="C07")),WORKDAY(N34+IF(G34="C01",Assumptions!$C$14,Assumptions!$C$15)-1,1),N34) -> 46318 | S34: =IF(INT((R34-Assumptions!$C$2)/7)+1>Assumptions!$C$3,"after W13",INT((R34-Assumptions!$C$2)/7)+1) -> 2 | T34: Open | U34: Yes | V34: Furniture order
A35: L0015 | B35: AR_Invoices | C35: INV-2026-1113 | D35: Receipt | E35: Customer – Office fit-out contractor | F35: Espace & Co Aménagement | G35: C03 | H35: 10992 | I35: 1 | J35: =H35*I35 -> 10992 | K35: 46308 | L35: 0 | M35: 10 | N35: 46318 | O35: =IF(INT((N35-Assumptions!$C$2)/7)+1>Assumptions!$C$3,"after W13",INT((N35-Assumptions!$C$2)/7)+1) -> 2 | P35: =IF(AND(D35="Receipt",G35="C01"),WORKDAY(N35+Assumptions!$C$14-1,1),N35) -> 46318 | Q35: =IF(INT((P35-Assumptions!$C$2)/7)+1>Assumptions!$C$3,"after W13",INT((P35-Assumptions!$C$2)/7)+1) -> 2 | R35: =IF(AND(D35="Receipt",OR(G35="C01",G35="C02",G35="C03",G35="C04",G35="C07")),WORKDAY(N35+IF(G35="C01",Assumptions!$C$14,Assumptions!$C$15)-1,1),N35) -> 46335 | S35: =IF(INT((R35-Assumptions!$C$2)/7)+1>Assumptions!$C$3,"after W13",INT((R35-Assumptions!$C$2)/7)+1) -> 5 | T35: Open | U35: Yes | V35: Furniture order
A36: L0022 | B36: AR_Invoices | C36: INV-2026-1122 | D36: Receipt | E36: Customer – Furniture distributor | F36: Mobilier Pro Rhône | G36: C06 | H36: 2964 | I36: 1 | J36: =H36*I36 -> 2964 | K36: 46311 | L36: 0 | M36: 7 | N36: 46318 | O36: =IF(INT((N36-Assumptions!$C$2)/7)+1>Assumptions!$C$3,"after W13",INT((N36-Assumptions!$C$2)/7)+1) -> 2 | P36: =IF(AND(D36="Receipt",G36="C01"),WORKDAY(N36+Assumptions!$C$14-1,1),N36) -> 46318 | Q36: =IF(INT((P36-Assumptions!$C$2)/7)+1>Assumptions!$C$3,"after W13",INT((P36-Assumptions!$C$2)/7)+1) -> 2 | R36: =IF(AND(D36="Receipt",OR(G36="C01",G36="C02",G36="C03",G36="C04",G36="C07")),WORKDAY(N36+IF(G36="C01",Assumptions!$C$14,Assumptions!$C$15)-1,1),N36) -> 46318 | S36: =IF(INT((R36-Assumptions!$C$2)/7)+1>Assumptions!$C$3,"after W13",INT((R36-Assumptions!$C$2)/7)+1) -> 2 | T36: Open | U36: Yes | V36: Furniture order
A37: L0023 | B37: AR_Invoices | C37: INV-2026-1123 | D37: Receipt | E37: Customer – Furniture distributor | F37: Mobilier Pro Rhône | G37: C06 | H37: 5736 | I37: 1 | J37: =H37*I37 -> 5736 | K37: 46311 | L37: 0 | M37: 7 | N37: 46318 | O37: =IF(INT((N37-Assumptions!$C$2)/7)+1>Assumptions!$C$3,"after W13",INT((N37-Assumptions!$C$2)/7)+1) -> 2 | P37: =IF(AND(D37="Receipt",G37="C01"),WORKDAY(N37+Assumptions!$C$14-1,1),N37) -> 46318 | Q37: =IF(INT((P37-Assumptions!$C$2)/7)+1>Assumptions!$C$3,"after W13",INT((P37-Assumptions!$C$2)/7)+1) -> 2 | R37: =IF(AND(D37="Receipt",OR(G37="C01",G37="C02",G37="C03",G37="C04",G37="C07")),WORKDAY(N37+IF(G37="C01",Assumptions!$C$14,Assumptions!$C$15)-1,1),N37) -> 46318 | S37: =IF(INT((R37-Assumptions!$C$2)/7)+1>Assumptions!$C$3,"after W13",INT((R37-Assumptions!$C$2)/7)+1) -> 2 | T37: Open | U37: Yes | V37: Furniture order
A38: L0339 | B38: Scheduled_Payments | C38: PAY-005 | D38: Payment | E38: VAT payment | F38: DGFiP | H38: -109780 | I38: 1 | J38: =H38*I38 -> -109780 | K38: 46321 | N38: 46321 | O38: =IF(INT((N38-Assumptions!$C$2)/7)+1>Assumptions!$C$3,"after W13",INT((N38-Assumptions!$C$2)/7)+1) -> 3 | P38: =IF(AND(D38="Receipt",G38="C01"),WORKDAY(N38+Assumptions!$C$14-1,1),N38) -> 46321 | Q38: =IF(INT((P38-Assumptions!$C$2)/7)+1>Assumptions!$C$3,"after W13",INT((P38-Assumptions!$C$2)/7)+1) -> 3 | R38: =IF(AND(D38="Receipt",OR(G38="C01",G38="C02",G38="C03",G38="C04",G38="C07")),WORKDAY(N38+IF(G38="C01",Assumptions!$C$14,Assumptions!$C$15)-1,1),N38) -> 46321 | S38: =IF(INT((R38-Assumptions!$C$2)/7)+1>Assumptions!$C$3,"after W13",INT((R38-Assumptions!$C$2)/7)+1) -> 3 | T38: Known (return prepared) | U38: Yes | V38: VAT for 2026-09
A39: L0004 | B39: AR_Invoices | C39: INV-2026-1087 | D39: Receipt | E39: Customer – Office fit-out contractor | F39: Bâtir Bureaux SAS | G39: C02 | H39: 7836 | I39: 1 | J39: =H39*I39 -> 7836 | K39: 46297 | L39: 7 | M39: 23 | N39: 46321 | O39: =IF(INT((N39-Assumptions!$C$2)/7)+1>Assumptions!$C$3,"after W13",INT((N39-Assumptions!$C$2)/7)+1) -> 3 | P39: =IF(AND(D39="Receipt",G39="C01"),WORKDAY(N39+Assumptions!$C$14-1,1),N39) -> 46321 | Q39: =IF(INT((P39-Assumptions!$C$2)/7)+1>Assumptions!$C$3,"after W13",INT((P39-Assumptions!$C$2)/7)+1) -> 3 | R39: =IF(AND(D39="Receipt",OR(G39="C01",G39="C02",G39="C03",G39="C04",G39="C07")),WORKDAY(N39+IF(G39="C01",Assumptions!$C$14,Assumptions!$C$15)-1,1),N39) -> 46336 | S39: =IF(INT((R39-Assumptions!$C$2)/7)+1>Assumptions!$C$3,"after W13",INT((R39-Assumptions!$C$2)/7)+1) -> 5 | T39: Open | U39: Yes | V39: Furniture order
A40: L0011 | B40: AR_Invoices | C40: INV-2026-1107 | D40: Receipt | E40: Customer – Public sector (hospital) | F40: CHU Vallée du Rhône | G40: C09 | H40: 16824 | I40: 1 | J40: =H40*I40 -> 16824 | K40: 46295 | L40: 9 | M40: 24 | N40: 46321 | O40: =IF(INT((N40-Assumptions!$C$2)/7)+1>Assumptions!$C$3,"after W13",INT((N40-Assumptions!$C$2)/7)+1) -> 3 | P40: =IF(AND(D40="Receipt",G40="C01"),WORKDAY(N40+Assumptions!$C$14-1,1),N40) -> 46321 | Q40: =IF(INT((P40-Assumptions!$C$2)/7)+1>Assumptions!$C$3,"after W13",INT((P40-Assumptions!$C$2)/7)+1) -> 3 | R40: =IF(AND(D40="Receipt",OR(G40="C01",G40="C02",G40="C03",G40="C04",G40="C07")),WORKDAY(N40+IF(G40="C01",Assumptions!$C$14,Assumptions!$C$15)-1,1),N40) -> 46321 | S40: =IF(INT((R40-Assumptions!$C$2)/7)+1>Assumptions!$C$3,"after W13",INT((R40-Assumptions!$C$2)/7)+1) -> 3 | T40: Open – disputed | U40: No – disputed (A12) | V40: Furniture order
A41: L0029 | B41: AR_Invoices | C41: INV-2026-1129 | D41: Receipt | E41: Customer – Furniture distributor | F41: Mobilier Pro Rhône | G41: C06 | H41: 12852 | I41: 1 | J41: =H41*I41 -> 12852 | K41: 46314 | L41: 0 | M41: 7 | N41: 46321 | O41: =IF(INT((N41-Assumptions!$C$2)/7)+1>Assumptions!$C$3,"after W13",INT((N41-Assumptions!$C$2)/7)+1) -> 3 | P41: =IF(AND(D41="Receipt",G41="C01"),WORKDAY(N41+Assumptions!$C$14-1,1),N41) -> 46321 | Q41: =IF(INT((P41-Assumptions!$C$2)/7)+1>Assumptions!$C$3,"after W13",INT((P41-Assumptions!$C$2)/7)+1) -> 3 | R41: =IF(AND(D41="Receipt",OR(G41="C01",G41="C02",G41="C03",G41="C04",G41="C07")),WORKDAY(N41+IF(G41="C01",Assumptions!$C$14,Assumptions!$C$15)-1,1),N41) -> 46321 | S41: =IF(INT((R41-Assumptions!$C$2)/7)+1>Assumptions!$C$3,"after W13",INT((R41-Assumptions!$C$2)/7)+1) -> 3 | T41: Open | U41: Yes | V41: Furniture order
A42: L0059 | B42: AR_Invoices | C42: INV-2026-1161 | D42: Receipt | E42: Customer – Public sector | F42: Université Lyon-Est | G42: C08 | H42: 14520 | I42: 1 | J42: =H42*I42 -> 14520 | K42: 46313 | L42: 0 | M42: 8.5 | N42: 46321 | O42: =IF(INT((N42-Assumptions!$C$2)/7)+1>Assumptions!$C$3,"after W13",INT((N42-Assumptions!$C$2)/7)+1) -> 3 | P42: =IF(AND(D42="Receipt",G42="C01"),WORKDAY(N42+Assumptions!$C$14-1,1),N42) -> 46321 | Q42: =IF(INT((P42-Assumptions!$C$2)/7)+1>Assumptions!$C$3,"after W13",INT((P42-Assumptions!$C$2)/7)+1) -> 3 | R42: =IF(AND(D42="Receipt",OR(G42="C01",G42="C02",G42="C03",G42="C04",G42="C07")),WORKDAY(N42+IF(G42="C01",Assumptions!$C$14,Assumptions!$C$15)-1,1),N42) -> 46321 | S42: =IF(INT((R42-Assumptions!$C$2)/7)+1>Assumptions!$C$3,"after W13",INT((R42-Assumptions!$C$2)/7)+1) -> 3 | T42: Open | U42: Yes | V42: Furniture order
A43: L0008 | B43: AR_Invoices | C43: INV-2026-1102 | D43: Receipt | E43: Customer – Office fit-out contractor | F43: Bâtir Bureaux SAS | G43: C02 | H43: 18648 | I43: 1 | J43: =H43*I43 -> 18648 | K43: 46301 | L43: 3 | M43: 21 | N43: 46322 | O43: =IF(INT((N43-Assumptions!$C$2)/7)+1>Assumptions!$C$3,"after W13",INT((N43-Assumptions!$C$2)/7)+1) -> 3 | P43: =IF(AND(D43="Receipt",G43="C01"),WORKDAY(N43+Assumptions!$C$14-1,1),N43) -> 46322 | Q43: =IF(INT((P43-Assumptions!$C$2)/7)+1>Assumptions!$C$3,"after W13",INT((P43-Assumptions!$C$2)/7)+1) -> 3 | R43: =IF(AND(D43="Receipt",OR(G43="C01",G43="C02",G43="C03",G43="C04",G43="C07")),WORKDAY(N43+IF(G43="C01",Assumptions!$C$14,Assumptions!$C$15)-1,1),N43) -> 46337 | S43: =IF(INT((R43-Assumptions!$C$2)/7)+1>Assumptions!$C$3,"after W13",INT((R43-Assumptions!$C$2)/7)+1) -> 5 | T43: Open | U43: Yes | V43: Furniture order
A44: L0340 | B44: Scheduled_Payments | C44: PAY-006 | D44: Payment | E44: Card & sundry spending | F44: Fuel, travel, consumables | H44: -4700 | I44: 1 | J44: =H44*I44 -> -4700 | K44: 46323 | N44: 46323 | O44: =IF(INT((N44-Assumptions!$C$2)/7)+1>Assumptions!$C$3,"after W13",INT((N44-Assumptions!$C$2)/7)+1) -> 3 | P44: =IF(AND(D44="Receipt",G44="C01"),WORKDAY(N44+Assumptions!$C$14-1,1),N44) -> 46323 | Q44: =IF(INT((P44-Assumptions!$C$2)/7)+1>Assumptions!$C$3,"after W13",INT((P44-Assumptions!$C$2)/7)+1) -> 3 | R44: =IF(AND(D44="Receipt",OR(G44="C01",G44="C02",G44="C03",G44="C04",G44="C07")),WORKDAY(N44+IF(G44="C01",Assumptions!$C$14,Assumptions!$C$15)-1,1),N44) -> 46323 | S44: =IF(INT((R44-Assumptions!$C$2)/7)+1>Assumptions!$C$3,"after W13",INT((R44-Assumptions!$C$2)/7)+1) -> 3 | T44: Estimate (run-rate) | U44: Yes | V44: Run-rate estimate (avg of last 26 weeks, rounded)
A45: L0052 | B45: AR_Invoices | C45: INV-2026-1154 | D45: Receipt | E45: Customer – Direct corporate client | F45: Hub & Desk Coworking SAS | G45: C11 | H45: 11508 | I45: 1 | J45: =H45*I45 -> 11508 | K45: 46311 | L45: 0 | M45: 12 | N45: 46323 | O45: =IF(INT((N45-Assumptions!$C$2)/7)+1>Assumptions!$C$3,"after W13",INT((N45-Assumptions!$C$2)/7)+1) -> 3 | P45: =IF(AND(D45="Receipt",G45="C01"),WORKDAY(N45+Assumptions!$C$14-1,1),N45) -> 46323 | Q45: =IF(INT((P45-Assumptions!$C$2)/7)+1>Assumptions!$C$3,"after W13",INT((P45-Assumptions!$C$2)/7)+1) -> 3 | R45: =IF(AND(D45="Receipt",OR(G45="C01",G45="C02",G45="C03",G45="C04",G45="C07")),WORKDAY(N45+IF(G45="C01",Assumptions!$C$14,Assumptions!$C$15)-1,1),N45) -> 46323 | S45: =IF(INT((R45-Assumptions!$C$2)/7)+1>Assumptions!$C$3,"after W13",INT((R45-Assumptions!$C$2)/7)+1) -> 3 | T45: Open | U45: Yes | V45: Furniture order
A46: L0073 | B46: AR_Invoices | C46: INV-2026-1175 | D46: Receipt | E46: Customer – Office fit-out contractor | F46: Studio Kaya Design | G46: C07 | H46: 2016 | I46: 1 | J46: =H46*I46 -> 2016 | K46: 46320 | L46: 0 | M46: 3 | N46: 46323 | O46: =IF(INT((N46-Assumptions!$C$2)/7)+1>Assumptions!$C$3,"after W13",INT((N46-Assumptions!$C$2)/7)+1) -> 3 | P46: =IF(AND(D46="Receipt",G46="C01"),WORKDAY(N46+Assumptions!$C$14-1,1),N46) -> 46323 | Q46: =IF(INT((P46-Assumptions!$C$2)/7)+1>Assumptions!$C$3,"after W13",INT((P46-Assumptions!$C$2)/7)+1) -> 3 | R46: =IF(AND(D46="Receipt",OR(G46="C01",G46="C02",G46="C03",G46="C04",G46="C07")),WORKDAY(N46+IF(G46="C01",Assumptions!$C$14,Assumptions!$C$15)-1,1),N46) -> 46338 | S46: =IF(INT((R46-Assumptions!$C$2)/7)+1>Assumptions!$C$3,"after W13",INT((R46-Assumptions!$C$2)/7)+1) -> 5 | T46: Open | U46: Yes | V46: Furniture order
A47: L0306 | B47: AP_Bills | C47: BILL-2026-0224 | D47: Payment | E47: Supplier payment | F47: Aciers Rhône-Métal | H47: -42319.76 | I47: 1 | J47: =H47*I47 -> -42319.76 | K47: 46327 | N47: 46324 | O47: =IF(INT((N47-Assumptions!$C$2)/7)+1>Assumptions!$C$3,"after W13",INT((N47-Assumptions!$C$2)/7)+1) -> 3 | P47: =IF(AND(D47="Receipt",G47="C01"),WORKDAY(N47+Assumptions!$C$14-1,1),N47) -> 46324 | Q47: =IF(INT((P47-Assumptions!$C$2)/7)+1>Assumptions!$C$3,"after W13",INT((P47-Assumptions!$C$2)/7)+1) -> 3 | R47: =IF(AND(D47="Receipt",OR(G47="C01",G47="C02",G47="C03",G47="C04",G47="C07")),WORKDAY(N47+IF(G47="C01",Assumptions!$C$14,Assumptions!$C$15)-1,1),N47) -> 46324 | S47: =IF(INT((R47-Assumptions!$C$2)/7)+1>Assumptions!$C$3,"after W13",INT((R47-Assumptions!$C$2)/7)+1) -> 3 | T47: Open bill | U47: Yes | V47: Steel frames – 2nd half
A48: L0308 | B48: AP_Bills | C48: BILL-2026-0226 | D48: Payment | E48: Supplier payment | F48: TransAlp Logistique | H48: -22333.04 | I48: 1 | J48: =H48*I48 -> -22333.04 | K48: 46325 | N48: 46324 | O48: =IF(INT((N48-Assumptions!$C$2)/7)+1>Assumptions!$C$3,"after W13",INT((N48-Assumptions!$C$2)/7)+1) -> 3 | P48: =IF(AND(D48="Receipt",G48="C01"),WORKDAY(N48+Assumptions!$C$14-1,1),N48) -> 46324 | Q48: =IF(INT((P48-Assumptions!$C$2)/7)+1>Assumptions!$C$3,"after W13",INT((P48-Assumptions!$C$2)/7)+1) -> 3 | R48: =IF(AND(D48="Receipt",OR(G48="C01",G48="C02",G48="C03",G48="C04",G48="C07")),WORKDAY(N48+IF(G48="C01",Assumptions!$C$14,Assumptions!$C$15)-1,1),N48) -> 46324 | S48: =IF(INT((R48-Assumptions!$C$2)/7)+1>Assumptions!$C$3,"after W13",INT((R48-Assumptions!$C$2)/7)+1) -> 3 | T48: Open bill | U48: Yes | V48: Transport Sep 2026
A49: L0309 | B49: AP_Bills | C49: BILL-2026-0227 | D49: Payment | E49: Supplier payment | F49: Quincaillerie Pro Est | H49: -6410.15 | I49: 1 | J49: =H49*I49 -> -6410.15 | K49: 46327 | N49: 46324 | O49: =IF(INT((N49-Assumptions!$C$2)/7)+1>Assumptions!$C$3,"after W13",INT((N49-Assumptions!$C$2)/7)+1) -> 3 | P49: =IF(AND(D49="Receipt",G49="C01"),WORKDAY(N49+Assumptions!$C$14-1,1),N49) -> 46324 | Q49: =IF(INT((P49-Assumptions!$C$2)/7)+1>Assumptions!$C$3,"after W13",INT((P49-Assumptions!$C$2)/7)+1) -> 3 | R49: =IF(AND(D49="Receipt",OR(G49="C01",G49="C02",G49="C03",G49="C04",G49="C07")),WORKDAY(N49+IF(G49="C01",Assumptions!$C$14,Assumptions!$C$15)-1,1),N49) -> 46324 | S49: =IF(INT((R49-Assumptions!$C$2)/7)+1>Assumptions!$C$3,"after W13",INT((R49-Assumptions!$C$2)/7)+1) -> 3 | T49: Open bill | U49: Yes | V49: Hardware & fittings
A50: L0311 | B50: AP_Bills | C50: BILL-2026-0229 | D50: Payment | E50: Supplier payment | F50: Holzwerk Bayern GmbH | H50: -147760.97 | I50: 1 | J50: =H50*I50 -> -147760.97 | K50: 46330 | N50: 46324 | O50: =IF(INT((N50-Assumptions!$C$2)/7)+1>Assumptions!$C$3,"after W13",INT((N50-Assumptions!$C$2)/7)+1) -> 3 | P50: =IF(AND(D50="Receipt",G50="C01"),WORKDAY(N50+Assumptions!$C$14-1,1),N50) -> 46324 | Q50: =IF(INT((P50-Assumptions!$C$2)/7)+1>Assumptions!$C$3,"after W13",INT((P50-Assumptions!$C$2)/7)+1) -> 3 | R50: =IF(AND(D50="Receipt",OR(G50="C01",G50="C02",G50="C03",G50="C04",G50="C07")),WORKDAY(N50+IF(G50="C01",Assumptions!$C$14,Assumptions!$C$15)-1,1),N50) -> 46324 | S50: =IF(INT((R50-Assumptions!$C$2)/7)+1>Assumptions!$C$3,"after W13",INT((R50-Assumptions!$C$2)/7)+1) -> 3 | T50: Open bill | U50: Yes | V50: Timber & plywood – Oct 2026 delivery
A51: L0341 | B51: Scheduled_Payments | C51: PAY-007 | D51: Payment | E51: Payroll | F51: Employees (38 FTE) | H51: -106000 | I51: 1 | J51: =H51*I51 -> -106000 | K51: 46325 | N51: 46325 | O51: =IF(INT((N51-Assumptions!$C$2)/7)+1>Assumptions!$C$3,"after W13",INT((N51-Assumptions!$C$2)/7)+1) -> 3 | P51: =IF(AND(D51="Receipt",G51="C01"),WORKDAY(N51+Assumptions!$C$14-1,1),N51) -> 46325 | Q51: =IF(INT((P51-Assumptions!$C$2)/7)+1>Assumptions!$C$3,"after W13",INT((P51-Assumptions!$C$2)/7)+1) -> 3 | R51: =IF(AND(D51="Receipt",OR(G51="C01",G51="C02",G51="C03",G51="C04",G51="C07")),WORKDAY(N51+IF(G51="C01",Assumptions!$C$14,Assumptions!$C$15)-1,1),N51) -> 46325 | S51: =IF(INT((R51-Assumptions!$C$2)/7)+1>Assumptions!$C$3,"after W13",INT((R51-Assumptions!$C$2)/7)+1) -> 3 | T51: Contractual / statutory | U51: Yes
A52: L0037 | B52: AR_Invoices | C52: INV-2026-1139 | D52: Receipt | E52: Customer – Furniture distributor | F52: Mobilier Pro Rhône | G52: C06 | H52: 4692 | I52: 1 | J52: =H52*I52 -> 4692 | K52: 46318 | L52: 0 | M52: 7 | N52: 46325 | O52: =IF(INT((N52-Assumptions!$C$2)/7)+1>Assumptions!$C$3,"after W13",INT((N52-Assumptions!$C$2)/7)+1) -> 3 | P52: =IF(AND(D52="Receipt",G52="C01"),WORKDAY(N52+Assumptions!$C$14-1,1),N52) -> 46325 | Q52: =IF(INT((P52-Assumptions!$C$2)/7)+1>Assumptions!$C$3,"after W13",INT((P52-Assumptions!$C$2)/7)+1) -> 3 | R52: =IF(AND(D52="Receipt",OR(G52="C01",G52="C02",G52="C03",G52="C04",G52="C07")),WORKDAY(N52+IF(G52="C01",Assumptions!$C$14,Assumptions!$C$15)-1,1),N52) -> 46325 | S52: =IF(INT((R52-Assumptions!$C$2)/7)+1>Assumptions!$C$3,"after W13",INT((R52-Assumptions!$C$2)/7)+1) -> 3 | T52: Open | U52: Yes | V52: Furniture order
A53: L0038 | B53: AR_Invoices | C53: INV-2026-1140 | D53: Receipt | E53: Customer – Furniture distributor | F53: Mobilier Pro Rhône | G53: C06 | H53: 9588 | I53: 1 | J53: =H53*I53 -> 9588 | K53: 46318 | L53: 0 | M53: 7 | N53: 46325 | O53: =IF(INT((N53-Assumptions!$C$2)/7)+1>Assumptions!$C$3,"after W13",INT((N53-Assumptions!$C$2)/7)+1) -> 3 | P53: =IF(AND(D53="Receipt",G53="C01"),WORKDAY(N53+Assumptions!$C$14-1,1),N53) -> 46325 | Q53: =IF(INT((P53-Assumptions!$C$2)/7)+1>Assumptions!$C$3,"after W13",INT((P53-Assumptions!$C$2)/7)+1) -> 3 | R53: =IF(AND(D53="Receipt",OR(G53="C01",G53="C02",G53="C03",G53="C04",G53="C07")),WORKDAY(N53+IF(G53="C01",Assumptions!$C$14,Assumptions!$C$15)-1,1),N53) -> 46325 | S53: =IF(INT((R53-Assumptions!$C$2)/7)+1>Assumptions!$C$3,"after W13",INT((R53-Assumptions!$C$2)/7)+1) -> 3 | T53: Open | U53: Yes | V53: Furniture order
A54: L0050 | B54: AR_Invoices | C54: INV-2026-1152 | D54: Receipt | E54: Customer – Furniture distributor | F54: Officea Distribution | G54: C05 | H54: 9324 | I54: 1 | J54: =H54*I54 -> 9324 | K54: 46325 | L54: 0 | M54: 0 | N54: 46325 | O54: =IF(INT((N54-Assumptions!$C$2)/7)+1>Assumptions!$C$3,"after W13",INT((N54-Assumptions!$C$2)/7)+1) -> 3 | P54: =IF(AND(D54="Receipt",G54="C01"),WORKDAY(N54+Assumptions!$C$14-1,1),N54) -> 46325 | Q54: =IF(INT((P54-Assumptions!$C$2)/7)+1>Assumptions!$C$3,"after W13",INT((P54-Assumptions!$C$2)/7)+1) -> 3 | R54: =IF(AND(D54="Receipt",OR(G54="C01",G54="C02",G54="C03",G54="C04",G54="C07")),WORKDAY(N54+IF(G54="C01",Assumptions!$C$14,Assumptions!$C$15)-1,1),N54) -> 46325 | S54: =IF(INT((R54-Assumptions!$C$2)/7)+1>Assumptions!$C$3,"after W13",INT((R54-Assumptions!$C$2)/7)+1) -> 3 | T54: Open | U54: Yes | V54: Furniture order
A55: L0013 | B55: AR_Invoices | C55: INV-2026-1110 | D55: Receipt | E55: Customer – Office fit-out contractor | F55: Bâtir Bureaux SAS | G55: C02 | H55: 45012 | I55: 1 | J55: =H55*I55 -> 45012 | K55: 46306 | L55: 0 | M55: 21 | N55: 46328 | O55: =IF(INT((N55-Assumptions!$C$2)/7)+1>Assumptions!$C$3,"after W13",INT((N55-Assumptions!$C$2)/7)+1) -> 4 | P55: =IF(AND(D55="Receipt",G55="C01"),WORKDAY(N55+Assumptions!$C$14-1,1),N55) -> 46328 | Q55: =IF(INT((P55-Assumptions!$C$2)/7)+1>Assumptions!$C$3,"after W13",INT((P55-Assumptions!$C$2)/7)+1) -> 4 | R55: =IF(AND(D55="Receipt",OR(G55="C01",G55="C02",G55="C03",G55="C04",G55="C07")),WORKDAY(N55+IF(G55="C01",Assumptions!$C$14,Assumptions!$C$15)-1,1),N55) -> 46343 | S55: =IF(INT((R55-Assumptions!$C$2)/7)+1>Assumptions!$C$3,"after W13",INT((R55-Assumptions!$C$2)/7)+1) -> 6 | T55: Open | U55: Yes | V55: Furniture order
A56: L0043 | B56: AR_Invoices | C56: INV-2026-1145 | D56: Receipt | E56: Customer – Furniture distributor | F56: Mobilier Pro Rhône | G56: C06 | H56: 4008 | I56: 1 | J56: =H56*I56 -> 4008 | K56: 46321 | L56: 0 | M56: 7 | N56: 46328 | O56: =IF(INT((N56-Assumptions!$C$2)/7)+1>Assumptions!$C$3,"after W13",INT((N56-Assumptions!$C$2)/7)+1) -> 4 | P56: =IF(AND(D56="Receipt",G56="C01"),WORKDAY(N56+Assumptions!$C$14-1,1),N56) -> 46328 | Q56: =IF(INT((P56-Assumptions!$C$2)/7)+1>Assumptions!$C$3,"after W13",INT((P56-Assumptions!$C$2)/7)+1) -> 4 | R56: =IF(AND(D56="Receipt",OR(G56="C01",G56="C02",G56="C03",G56="C04",G56="C07")),WORKDAY(N56+IF(G56="C01",Assumptions!$C$14,Assumptions!$C$15)-1,1),N56) -> 46328 | S56: =IF(INT((R56-Assumptions!$C$2)/7)+1>Assumptions!$C$3,"after W13",INT((R56-Assumptions!$C$2)/7)+1) -> 4 | T56: Open | U56: Yes | V56: Furniture order
A57: L0061 | B57: AR_Invoices | C57: INV-2026-1163 | D57: Receipt | E57: Customer – Furniture distributor | F57: Officea Distribution | G57: C05 | H57: 8784 | I57: 1 | J57: =H57*I57 -> 8784 | K57: 46328 | L57: 0 | M57: 0 | N57: 46328 | O57: =IF(INT((N57-Assumptions!$C$2)/7)+1>Assumptions!$C$3,"after W13",INT((N57-Assumptions!$C$2)/7)+1) -> 4 | P57: =IF(AND(D57="Receipt",G57="C01"),WORKDAY(N57+Assumptions!$C$14-1,1),N57) -> 46328 | Q57: =IF(INT((P57-Assumptions!$C$2)/7)+1>Assumptions!$C$3,"after W13",INT((P57-Assumptions!$C$2)/7)+1) -> 4 | R57: =IF(AND(D57="Receipt",OR(G57="C01",G57="C02",G57="C03",G57="C04",G57="C07")),WORKDAY(N57+IF(G57="C01",Assumptions!$C$14,Assumptions!$C$15)-1,1),N57) -> 46328 | S57: =IF(INT((R57-Assumptions!$C$2)/7)+1>Assumptions!$C$3,"after W13",INT((R57-Assumptions!$C$2)/7)+1) -> 4 | T57: Open | U57: Yes | V57: Furniture order
A58: L0063 | B58: AR_Invoices | C58: INV-2026-1165 | D58: Receipt | E58: Customer – Furniture distributor | F58: Officea Distribution | G58: C05 | H58: 11028 | I58: 1 | J58: =H58*I58 -> 11028 | K58: 46328 | L58: 0 | M58: 0 | N58: 46328 | O58: =IF(INT((N58-Assumptions!$C$2)/7)+1>Assumptions!$C$3,"after W13",INT((N58-Assumptions!$C$2)/7)+1) -> 4 | P58: =IF(AND(D58="Receipt",G58="C01"),WORKDAY(N58+Assumptions!$C$14-1,1),N58) -> 46328 | Q58: =IF(INT((P58-Assumptions!$C$2)/7)+1>Assumptions!$C$3,"after W13",INT((P58-Assumptions!$C$2)/7)+1) -> 4 | R58: =IF(AND(D58="Receipt",OR(G58="C01",G58="C02",G58="C03",G58="C04",G58="C07")),WORKDAY(N58+IF(G58="C01",Assumptions!$C$14,Assumptions!$C$15)-1,1),N58) -> 46328 | S58: =IF(INT((R58-Assumptions!$C$2)/7)+1>Assumptions!$C$3,"after W13",INT((R58-Assumptions!$C$2)/7)+1) -> 4 | T58: Open | U58: Yes | V58: Furniture order
A59: L0065 | B59: AR_Invoices | C59: INV-2026-1167 | D59: Receipt | E59: Customer – Furniture distributor | F59: Officea Distribution | G59: C05 | H59: 6300 | I59: 1 | J59: =H59*I59 -> 6300 | K59: 46328 | L59: 0 | M59: 0 | N59: 46328 | O59: =IF(INT((N59-Assumptions!$C$2)/7)+1>Assumptions!$C$3,"after W13",INT((N59-Assumptions!$C$2)/7)+1) -> 4 | P59: =IF(AND(D59="Receipt",G59="C01"),WORKDAY(N59+Assumptions!$C$14-1,1),N59) -> 46328 | Q59: =IF(INT((P59-Assumptions!$C$2)/7)+1>Assumptions!$C$3,"after W13",INT((P59-Assumptions!$C$2)/7)+1) -> 4 | R59: =IF(AND(D59="Receipt",OR(G59="C01",G59="C02",G59="C03",G59="C04",G59="C07")),WORKDAY(N59+IF(G59="C01",Assumptions!$C$14,Assumptions!$C$15)-1,1),N59) -> 46328 | S59: =IF(INT((R59-Assumptions!$C$2)/7)+1>Assumptions!$C$3,"after W13",INT((R59-Assumptions!$C$2)/7)+1) -> 4 | T59: Open | U59: Yes | V59: Furniture order
A60: L0074 | B60: AR_Invoices | C60: INV-2026-1176 | D60: Receipt | E60: Customer – Public sector | F60: Université Lyon-Est | G60: C08 | H60: 29448 | I60: 1 | J60: =H60*I60 -> 29448 | K60: 46320 | L60: 0 | M60: 8.5 | N60: 46328 | O60: =IF(INT((N60-Assumptions!$C$2)/7)+1>Assumptions!$C$3,"after W13",INT((N60-Assumptions!$C$2)/7)+1) -> 4 | P60: =IF(AND(D60="Receipt",G60="C01"),WORKDAY(N60+Assumptions!$C$14-1,1),N60) -> 46328 | Q60: =IF(INT((P60-Assumptions!$C$2)/7)+1>Assumptions!$C$3,"after W13",INT((P60-Assumptions!$C$2)/7)+1) -> 4 | R60: =IF(AND(D60="Receipt",OR(G60="C01",G60="C02",G60="C03",G60="C04",G60="C07")),WORKDAY(N60+IF(G60="C01",Assumptions!$C$14,Assumptions!$C$15)-1,1),N60) -> 46328 | S60: =IF(INT((R60-Assumptions!$C$2)/7)+1>Assumptions!$C$3,"after W13",INT((R60-Assumptions!$C$2)/7)+1) -> 4 | T60: Open | U60: Yes | V60: Furniture order
A61: L0078 | B61: AR_Invoices | C61: INV-2026-1180 | D61: Receipt | E61: Customer – Office fit-out contractor | F61: Studio Kaya Design | G61: C07 | H61: 3648 | I61: 1 | J61: =H61*I61 -> 3648 | K61: 46323 | L61: 0 | M61: 3 | N61: 46328 | O61: =IF(INT((N61-Assumptions!$C$2)/7)+1>Assumptions!$C$3,"after W13",INT((N61-Assumptions!$C$2)/7)+1) -> 4 | P61: =IF(AND(D61="Receipt",G61="C01"),WORKDAY(N61+Assumptions!$C$14-1,1),N61) -> 46328 | Q61: =IF(INT((P61-Assumptions!$C$2)/7)+1>Assumptions!$C$3,"after W13",INT((P61-Assumptions!$C$2)/7)+1) -> 4 | R61: =IF(AND(D61="Receipt",OR(G61="C01",G61="C02",G61="C03",G61="C04",G61="C07")),WORKDAY(N61+IF(G61="C01",Assumptions!$C$14,Assumptions!$C$15)-1,1),N61) -> 46343 | S61: =IF(INT((R61-Assumptions!$C$2)/7)+1>Assumptions!$C$3,"after W13",INT((R61-Assumptions!$C$2)/7)+1) -> 6 | T61: Open | U61: Yes | V61: Furniture order
A62: L0342 | B62: Scheduled_Payments | C62: PAY-008 | D62: Payment | E62: IT, telecom & software | F62: Various (direct debits) | H62: -2880 | I62: 1 | J62: =H62*I62 -> -2880 | K62: 46329 | N62: 46329 | O62: =IF(INT((N62-Assumptions!$C$2)/7)+1>Assumptions!$C$3,"after W13",INT((N62-Assumptions!$C$2)/7)+1) -> 4 | P62: =IF(AND(D62="Receipt",G62="C01"),WORKDAY(N62+Assumptions!$C$14-1,1),N62) -> 46329 | Q62: =IF(INT((P62-Assumptions!$C$2)/7)+1>Assumptions!$C$3,"after W13",INT((P62-Assumptions!$C$2)/7)+1) -> 4 | R62: =IF(AND(D62="Receipt",OR(G62="C01",G62="C02",G62="C03",G62="C04",G62="C07")),WORKDAY(N62+IF(G62="C01",Assumptions!$C$14,Assumptions!$C$15)-1,1),N62) -> 46329 | S62: =IF(INT((R62-Assumptions!$C$2)/7)+1>Assumptions!$C$3,"after W13",INT((R62-Assumptions!$C$2)/7)+1) -> 4 | T62: Contractual / statutory | U62: Yes
A63: L0016 | B63: AR_Invoices | C63: INV-2026-1116 | D63: Receipt | E63: Customer – Office fit-out contractor | F63: Espace & Co Aménagement | G63: C03 | H63: 5496 | I63: 1 | J63: =H63*I63 -> 5496 | K63: 46319 | L63: 0 | M63: 10 | N63: 46329 | O63: =IF(INT((N63-Assumptions!$C$2)/7)+1>Assumptions!$C$3,"after W13",INT((N63-Assumptions!$C$2)/7)+1) -> 4 | P63: =IF(AND(D63="Receipt",G63="C01"),WORKDAY(N63+Assumptions!$C$14-1,1),N63) -> 46329 | Q63: =IF(INT((P63-Assumptions!$C$2)/7)+1>Assumptions!$C$3,"after W13",INT((P63-Assumptions!$C$2)/7)+1) -> 4 | R63: =IF(AND(D63="Receipt",OR(G63="C01",G63="C02",G63="C03",G63="C04",G63="C07")),WORKDAY(N63+IF(G63="C01",Assumptions!$C$14,Assumptions!$C$15)-1,1),N63) -> 46344 | S63: =IF(INT((R63-Assumptions!$C$2)/7)+1>Assumptions!$C$3,"after W13",INT((R63-Assumptions!$C$2)/7)+1) -> 6 | T63: Open | U63: Yes | V63: Furniture order
A64: L0343 | B64: Scheduled_Payments | C64: PAY-009 | D64: Payment | E64: Card & sundry spending | F64: Fuel, travel, consumables | H64: -4700 | I64: 1 | J64: =H64*I64 -> -4700 | K64: 46330 | N64: 46330 | O64: =IF(INT((N64-Assumptions!$C$2)/7)+1>Assumptions!$C$3,"after W13",INT((N64-Assumptions!$C$2)/7)+1) -> 4 | P64: =IF(AND(D64="Receipt",G64="C01"),WORKDAY(N64+Assumptions!$C$14-1,1),N64) -> 46330 | Q64: =IF(INT((P64-Assumptions!$C$2)/7)+1>Assumptions!$C$3,"after W13",INT((P64-Assumptions!$C$2)/7)+1) -> 4 | R64: =IF(AND(D64="Receipt",OR(G64="C01",G64="C02",G64="C03",G64="C04",G64="C07")),WORKDAY(N64+IF(G64="C01",Assumptions!$C$14,Assumptions!$C$15)-1,1),N64) -> 46330 | S64: =IF(INT((R64-Assumptions!$C$2)/7)+1>Assumptions!$C$3,"after W13",INT((R64-Assumptions!$C$2)/7)+1) -> 4 | T64: Estimate (run-rate) | U64: Yes | V64: Run-rate estimate (avg of last 26 weeks, rounded)
A65: L0017 | B65: AR_Invoices | C65: INV-2026-1117 | D65: Receipt | E65: Customer – Office fit-out contractor | F65: Espace & Co Aménagement | G65: C03 | H65: 9852 | I65: 1 | J65: =H65*I65 -> 9852 | K65: 46320 | L65: 0 | M65: 10 | N65: 46330 | O65: =IF(INT((N65-Assumptions!$C$2)/7)+1>Assumptions!$C$3,"after W13",INT((N65-Assumptions!$C$2)/7)+1) -> 4 | P65: =IF(AND(D65="Receipt",G65="C01"),WORKDAY(N65+Assumptions!$C$14-1,1),N65) -> 46330 | Q65: =IF(INT((P65-Assumptions!$C$2)/7)+1>Assumptions!$C$3,"after W13",INT((P65-Assumptions!$C$2)/7)+1) -> 4 | R65: =IF(AND(D65="Receipt",OR(G65="C01",G65="C02",G65="C03",G65="C04",G65="C07")),WORKDAY(N65+IF(G65="C01",Assumptions!$C$14,Assumptions!$C$15)-1,1),N65) -> 46345 | S65: =IF(INT((R65-Assumptions!$C$2)/7)+1>Assumptions!$C$3,"after W13",INT((R65-Assumptions!$C$2)/7)+1) -> 6 | T65: Open | U65: Yes | V65: Furniture order
A66: L0304 | B66: AP_Bills | C66: BILL-2026-0221 | D66: Payment | E66: Supplier payment | F66: Feutre & Textiles Lyonnais | H66: -39090.92 | I66: 1 | J66: =H66*I66 -> -39090.92 | K66: 46335 | N66: 46331 | O66: =IF(INT((N66-Assumptions!$C$2)/7)+1>Assumptions!$C$3,"after W13",INT((N66-Assumptions!$C$2)/7)+1) -> 4 | P66: =IF(AND(D66="Receipt",G66="C01"),WORKDAY(N66+Assumptions!$C$14-1,1),N66) -> 46331 | Q66: =IF(INT((P66-Assumptions!$C$2)/7)+1>Assumptions!$C$3,"after W13",INT((P66-Assumptions!$C$2)/7)+1) -> 4 | R66: =IF(AND(D66="Receipt",OR(G66="C01",G66="C02",G66="C03",G66="C04",G66="C07")),WORKDAY(N66+IF(G66="C01",Assumptions!$C$14,Assumptions!$C$15)-1,1),N66) -> 46331 | S66: =IF(INT((R66-Assumptions!$C$2)/7)+1>Assumptions!$C$3,"after W13",INT((R66-Assumptions!$C$2)/7)+1) -> 4 | T66: Open bill | U66: Yes | V66: Acoustic felt & fabrics
A67: L0312 | B67: AP_Bills | C67: BILL-2026-0230 | D67: Payment | E67: Supplier payment | F67: Quincaillerie Pro Est | H67: -5965.56 | I67: 1 | J67: =H67*I67 -> -5965.56 | K67: 46334 | N67: 46331 | O67: =IF(INT((N67-Assumptions!$C$2)/7)+1>Assumptions!$C$3,"after W13",INT((N67-Assumptions!$C$2)/7)+1) -> 4 | P67: =IF(AND(D67="Receipt",G67="C01"),WORKDAY(N67+Assumptions!$C$14-1,1),N67) -> 46331 | Q67: =IF(INT((P67-Assumptions!$C$2)/7)+1>Assumptions!$C$3,"after W13",INT((P67-Assumptions!$C$2)/7)+1) -> 4 | R67: =IF(AND(D67="Receipt",OR(G67="C01",G67="C02",G67="C03",G67="C04",G67="C07")),WORKDAY(N67+IF(G67="C01",Assumptions!$C$14,Assumptions!$C$15)-1,1),N67) -> 46331 | S67: =IF(INT((R67-Assumptions!$C$2)/7)+1>Assumptions!$C$3,"after W13",INT((R67-Assumptions!$C$2)/7)+1) -> 4 | T67: Open bill | U67: Yes | V67: Hardware & fittings
A68: L0313 | B68: Committed_Purchases | C68: PO-2601 | D68: Payment | E68: Supplier payment | F68: Vernis Écolo SAS | H68: -15961.99 | I68: 1 | J68: =H68*I68 -> -15961.99 | K68: 46337 | N68: 46331 | O68: =IF(INT((N68-Assumptions!$C$2)/7)+1>Assumptions!$C$3,"after W13",INT((N68-Assumptions!$C$2)/7)+1) -> 4 | P68: =IF(AND(D68="Receipt",G68="C01"),WORKDAY(N68+Assumptions!$C$14-1,1),N68) -> 46331 | Q68: =IF(INT((P68-Assumptions!$C$2)/7)+1>Assumptions!$C$3,"after W13",INT((P68-Assumptions!$C$2)/7)+1) -> 4 | R68: =IF(AND(D68="Receipt",OR(G68="C01",G68="C02",G68="C03",G68="C04",G68="C07")),WORKDAY(N68+IF(G68="C01",Assumptions!$C$14,Assumptions!$C$15)-1,1),N68) -> 46331 | S68: =IF(INT((R68-Assumptions!$C$2)/7)+1>Assumptions!$C$3,"after W13",INT((R68-Assumptions!$C$2)/7)+1) -> 4 | T68: PO confirmed | U68: Yes | V68: Finishes
A69: L0344 | B69: Scheduled_Payments | C69: PAY-010 | D69: Payment | E69: Bank loan repayment | F69: Banque Régionale (CNC machine loan) | H69: -8900 | I69: 1 | J69: =H69*I69 -> -8900 | K69: 46331 | N69: 46331 | O69: =IF(INT((N69-Assumptions!$C$2)/7)+1>Assumptions!$C$3,"after W13",INT((N69-Assumptions!$C$2)/7)+1) -> 4 | P69: =IF(AND(D69="Receipt",G69="C01"),WORKDAY(N69+Assumptions!$C$14-1,1),N69) -> 46331 | Q69: =IF(INT((P69-Assumptions!$C$2)/7)+1>Assumptions!$C$3,"after W13",INT((P69-Assumptions!$C$2)/7)+1) -> 4 | R69: =IF(AND(D69="Receipt",OR(G69="C01",G69="C02",G69="C03",G69="C04",G69="C07")),WORKDAY(N69+IF(G69="C01",Assumptions!$C$14,Assumptions!$C$15)-1,1),N69) -> 46331 | S69: =IF(INT((R69-Assumptions!$C$2)/7)+1>Assumptions!$C$3,"after W13",INT((R69-Assumptions!$C$2)/7)+1) -> 4 | T69: Contractual / statutory | U69: Yes | V69: principal + interest
A70: L0018 | B70: AR_Invoices | C70: INV-2026-1118 | D70: Receipt | E70: Customer – Office fit-out contractor | F70: Nova Interiors SARL | G70: C04 | H70: 6360 | I70: 1 | J70: =H70*I70 -> 6360 | K70: 46306 | L70: 0 | M70: 25 | N70: 46331 | O70: =IF(INT((N70-Assumptions!$C$2)/7)+1>Assumptions!$C$3,"after W13",INT((N70-Assumptions!$C$2)/7)+1) -> 4 | P70: =IF(AND(D70="Receipt",G70="C01"),WORKDAY(N70+Assumptions!$C$14-1,1),N70) -> 46331 | Q70: =IF(INT((P70-Assumptions!$C$2)/7)+1>Assumptions!$C$3,"after W13",INT((P70-Assumptions!$C$2)/7)+1) -> 4 | R70: =IF(AND(D70="Receipt",OR(G70="C01",G70="C02",G70="C03",G70="C04",G70="C07")),WORKDAY(N70+IF(G70="C01",Assumptions!$C$14,Assumptions!$C$15)-1,1),N70) -> 46346 | S70: =IF(INT((R70-Assumptions!$C$2)/7)+1>Assumptions!$C$3,"after W13",INT((R70-Assumptions!$C$2)/7)+1) -> 6 | T70: Open | U70: Yes | V70: Furniture order
A71: L0048 | B71: AR_Invoices | C71: INV-2026-1150 | D71: Receipt | E71: Customer – Furniture distributor | F71: Mobilier Pro Rhône | G71: C06 | H71: 9564 | I71: 1 | J71: =H71*I71 -> 9564 | K71: 46324 | L71: 0 | M71: 7 | N71: 46331 | O71: =IF(INT((N71-Assumptions!$C$2)/7)+1>Assumptions!$C$3,"after W13",INT((N71-Assumptions!$C$2)/7)+1) -> 4 | P71: =IF(AND(D71="Receipt",G71="C01"),WORKDAY(N71+Assumptions!$C$14-1,1),N71) -> 46331 | Q71: =IF(INT((P71-Assumptions!$C$2)/7)+1>Assumptions!$C$3,"after W13",INT((P71-Assumptions!$C$2)/7)+1) -> 4 | R71: =IF(AND(D71="Receipt",OR(G71="C01",G71="C02",G71="C03",G71="C04",G71="C07")),WORKDAY(N71+IF(G71="C01",Assumptions!$C$14,Assumptions!$C$15)-1,1),N71) -> 46331 | S71: =IF(INT((R71-Assumptions!$C$2)/7)+1>Assumptions!$C$3,"after W13",INT((R71-Assumptions!$C$2)/7)+1) -> 4 | T71: Open | U71: Yes | V71: Furniture order
A72: L0069 | B72: AR_Invoices | C72: INV-2026-1171 | D72: Receipt | E72: Customer – Furniture distributor | F72: Officea Distribution | G72: C05 | H72: 7932 | I72: 1 | J72: =H72*I72 -> 7932 | K72: 46332 | L72: 0 | M72: 0 | N72: 46332 | O72: =IF(INT((N72-Assumptions!$C$2)/7)+1>Assumptions!$C$3,"after W13",INT((N72-Assumptions!$C$2)/7)+1) -> 4 | P72: =IF(AND(D72="Receipt",G72="C01"),WORKDAY(N72+Assumptions!$C$14-1,1),N72) -> 46332 | Q72: =IF(INT((P72-Assumptions!$C$2)/7)+1>Assumptions!$C$3,"after W13",INT((P72-Assumptions!$C$2)/7)+1) -> 4 | R72: =IF(AND(D72="Receipt",OR(G72="C01",G72="C02",G72="C03",G72="C04",G72="C07")),WORKDAY(N72+IF(G72="C01",Assumptions!$C$14,Assumptions!$C$15)-1,1),N72) -> 46332 | S72: =IF(INT((R72-Assumptions!$C$2)/7)+1>Assumptions!$C$3,"after W13",INT((R72-Assumptions!$C$2)/7)+1) -> 4 | T72: Open | U72: Yes | V72: Furniture order
A73: L0345 | B73: Scheduled_Payments | C73: PAY-011 | D73: Payment | E73: Energy | F73: Electricity & gas supplier (direct debit) | H73: -14160 | I73: 1 | J73: =H73*I73 -> -14160 | K73: 46335 | N73: 46335 | O73: =IF(INT((N73-Assumptions!$C$2)/7)+1>Assumptions!$C$3,"after W13",INT((N73-Assumptions!$C$2)/7)+1) -> 5 | P73: =IF(AND(D73="Receipt",G73="C01"),WORKDAY(N73+Assumptions!$C$14-1,1),N73) -> 46335 | Q73: =IF(INT((P73-Assumptions!$C$2)/7)+1>Assumptions!$C$3,"after W13",INT((P73-Assumptions!$C$2)/7)+1) -> 5 | R73: =IF(AND(D73="Receipt",OR(G73="C01",G73="C02",G73="C03",G73="C04",G73="C07")),WORKDAY(N73+IF(G73="C01",Assumptions!$C$14,Assumptions!$C$15)-1,1),N73) -> 46335 | S73: =IF(INT((R73-Assumptions!$C$2)/7)+1>Assumptions!$C$3,"after W13",INT((R73-Assumptions!$C$2)/7)+1) -> 5 | T73: Contractual / statutory | U73: Yes
A74: L0032 | B74: AR_Invoices | C74: INV-2026-1133 | D74: Receipt | E74: Customer – Export distributor | F74: Arkade Interiors SRL | G74: C12 | H74: 13160 | I74: 1 | J74: =H74*I74 -> 13160 | K74: 46329 | L74: 0 | M74: 6 | N74: 46335 | O74: =IF(INT((N74-Assumptions!$C$2)/7)+1>Assumptions!$C$3,"after W13",INT((N74-Assumptions!$C$2)/7)+1) -> 5 | P74: =IF(AND(D74="Receipt",G74="C01"),WORKDAY(N74+Assumptions!$C$14-1,1),N74) -> 46335 | Q74: =IF(INT((P74-Assumptions!$C$2)/7)+1>Assumptions!$C$3,"after W13",INT((P74-Assumptions!$C$2)/7)+1) -> 5 | R74: =IF(AND(D74="Receipt",OR(G74="C01",G74="C02",G74="C03",G74="C04",G74="C07")),WORKDAY(N74+IF(G74="C01",Assumptions!$C$14,Assumptions!$C$15)-1,1),N74) -> 46335 | S74: =IF(INT((R74-Assumptions!$C$2)/7)+1>Assumptions!$C$3,"after W13",INT((R74-Assumptions!$C$2)/7)+1) -> 5 | T74: Open | U74: Yes | V74: Furniture order
A75: L0053 | B75: AR_Invoices | C75: INV-2026-1155 | D75: Receipt | E75: Customer – Furniture distributor | F75: Mobilier Pro Rhône | G75: C06 | H75: 7908 | I75: 1 | J75: =H75*I75 -> 7908 | K75: 46327 | L75: 0 | M75: 7 | N75: 46335 | O75: =IF(INT((N75-Assumptions!$C$2)/7)+1>Assumptions!$C$3,"after W13",INT((N75-Assumptions!$C$2)/7)+1) -> 5 | P75: =IF(AND(D75="Receipt",G75="C01"),WORKDAY(N75+Assumptions!$C$14-1,1),N75) -> 46335 | Q75: =IF(INT((P75-Assumptions!$C$2)/7)+1>Assumptions!$C$3,"after W13",INT((P75-Assumptions!$C$2)/7)+1) -> 5 | R75: =IF(AND(D75="Receipt",OR(G75="C01",G75="C02",G75="C03",G75="C04",G75="C07")),WORKDAY(N75+IF(G75="C01",Assumptions!$C$14,Assumptions!$C$15)-1,1),N75) -> 46335 | S75: =IF(INT((R75-Assumptions!$C$2)/7)+1>Assumptions!$C$3,"after W13",INT((R75-Assumptions!$C$2)/7)+1) -> 5 | T75: Open | U75: Yes | V75: Furniture order
A76: L0055 | B76: AR_Invoices | C76: INV-2026-1157 | D76: Receipt | E76: Customer – Furniture distributor | F76: Mobilier Pro Rhône | G76: C06 | H76: 8244 | I76: 1 | J76: =H76*I76 -> 8244 | K76: 46327 | L76: 0 | M76: 7 | N76: 46335 | O76: =IF(INT((N76-Assumptions!$C$2)/7)+1>Assumptions!$C$3,"after W13",INT((N76-Assumptions!$C$2)/7)+1) -> 5 | P76: =IF(AND(D76="Receipt",G76="C01"),WORKDAY(N76+Assumptions!$C$14-1,1),N76) -> 46335 | Q76: =IF(INT((P76-Assumptions!$C$2)/7)+1>Assumptions!$C$3,"after W13",INT((P76-Assumptions!$C$2)/7)+1) -> 5 | R76: =IF(AND(D76="Receipt",OR(G76="C01",G76="C02",G76="C03",G76="C04",G76="C07")),WORKDAY(N76+IF(G76="C01",Assumptions!$C$14,Assumptions!$C$15)-1,1),N76) -> 46335 | S76: =IF(INT((R76-Assumptions!$C$2)/7)+1>Assumptions!$C$3,"after W13",INT((R76-Assumptions!$C$2)/7)+1) -> 5 | T76: Open | U76: Yes | V76: Furniture order
A77: L0062 | B77: AR_Invoices | C77: INV-2026-1164 | D77: Receipt | E77: Customer – Furniture distributor | F77: Mobilier Pro Rhône | G77: C06 | H77: 5472 | I77: 1 | J77: =H77*I77 -> 5472 | K77: 46328 | L77: 0 | M77: 7 | N77: 46335 | O77: =IF(INT((N77-Assumptions!$C$2)/7)+1>Assumptions!$C$3,"after W13",INT((N77-Assumptions!$C$2)/7)+1) -> 5 | P77: =IF(AND(D77="Receipt",G77="C01"),WORKDAY(N77+Assumptions!$C$14-1,1),N77) -> 46335 | Q77: =IF(INT((P77-Assumptions!$C$2)/7)+1>Assumptions!$C$3,"after W13",INT((P77-Assumptions!$C$2)/7)+1) -> 5 | R77: =IF(AND(D77="Receipt",OR(G77="C01",G77="C02",G77="C03",G77="C04",G77="C07")),WORKDAY(N77+IF(G77="C01",Assumptions!$C$14,Assumptions!$C$15)-1,1),N77) -> 46335 | S77: =IF(INT((R77-Assumptions!$C$2)/7)+1>Assumptions!$C$3,"after W13",INT((R77-Assumptions!$C$2)/7)+1) -> 5 | T77: Open | U77: Yes | V77: Furniture order
A78: L0093 | B78: AR_Invoices | C78: INV-2026-1195 | D78: Receipt | E78: Customer – Office fit-out contractor | F78: Studio Kaya Design | G78: C07 | H78: 5448 | I78: 1 | J78: =H78*I78 -> 5448 | K78: 46330 | L78: 0 | M78: 3 | N78: 46335 | O78: =IF(INT((N78-Assumptions!$C$2)/7)+1>Assumptions!$C$3,"after W13",INT((N78-Assumptions!$C$2)/7)+1) -> 5 | P78: =IF(AND(D78="Receipt",G78="C01"),WORKDAY(N78+Assumptions!$C$14-1,1),N78) -> 46335 | Q78: =IF(INT((P78-Assumptions!$C$2)/7)+1>Assumptions!$C$3,"after W13",INT((P78-Assumptions!$C$2)/7)+1) -> 5 | R78: =IF(AND(D78="Receipt",OR(G78="C01",G78="C02",G78="C03",G78="C04",G78="C07")),WORKDAY(N78+IF(G78="C01",Assumptions!$C$14,Assumptions!$C$15)-1,1),N78) -> 46350 | S78: =IF(INT((R78-Assumptions!$C$2)/7)+1>Assumptions!$C$3,"after W13",INT((R78-Assumptions!$C$2)/7)+1) -> 7 | T78: Open | U78: Yes | V78: Furniture order
A79: L0346 | B79: Scheduled_Payments | C79: PAY-012 | D79: Payment | E79: Equipment lease | F79: LeasEquip France | H79: -3840 | I79: 1 | J79: =H79*I79 -> -3840 | K79: 46336 | N79: 46336 | O79: =IF(INT((N79-Assumptions!$C$2)/7)+1>Assumptions!$C$3,"after W13",INT((N79-Assumptions!$C$2)/7)+1) -> 5 | P79: =IF(AND(D79="Receipt",G79="C01"),WORKDAY(N79+Assumptions!$C$14-1,1),N79) -> 46336 | Q79: =IF(INT((P79-Assumptions!$C$2)/7)+1>Assumptions!$C$3,"after W13",INT((P79-Assumptions!$C$2)/7)+1) -> 5 | R79: =IF(AND(D79="Receipt",OR(G79="C01",G79="C02",G79="C03",G79="C04",G79="C07")),WORKDAY(N79+IF(G79="C01",Assumptions!$C$14,Assumptions!$C$15)-1,1),N79) -> 46336 | S79: =IF(INT((R79-Assumptions!$C$2)/7)+1>Assumptions!$C$3,"after W13",INT((R79-Assumptions!$C$2)/7)+1) -> 5 | T79: Contractual / statutory | U79: Yes
A80: L0021 | B80: AR_Invoices | C80: INV-2026-1121 | D80: Receipt | E80: Customer – Office fit-out contractor | F80: Espace & Co Aménagement | G80: C03 | H80: 11676 | I80: 1 | J80: =H80*I80 -> 11676 | K80: 46326 | L80: 0 | M80: 10 | N80: 46336 | O80: =IF(INT((N80-Assumptions!$C$2)/7)+1>Assumptions!$C$3,"after W13",INT((N80-Assumptions!$C$2)/7)+1) -> 5 | P80: =IF(AND(D80="Receipt",G80="C01"),WORKDAY(N80+Assumptions!$C$14-1,1),N80) -> 46336 | Q80: =IF(INT((P80-Assumptions!$C$2)/7)+1>Assumptions!$C$3,"after W13",INT((P80-Assumptions!$C$2)/7)+1) -> 5 | R80: =IF(AND(D80="Receipt",OR(G80="C01",G80="C02",G80="C03",G80="C04",G80="C07")),WORKDAY(N80+IF(G80="C01",Assumptions!$C$14,Assumptions!$C$15)-1,1),N80) -> 46351 | S80: =IF(INT((R80-Assumptions!$C$2)/7)+1>Assumptions!$C$3,"after W13",INT((R80-Assumptions!$C$2)/7)+1) -> 7 | T80: Open | U80: Yes | V80: Furniture order
A81: L0101 | B81: AR_Invoices | C81: INV-2026-1203 | D81: Receipt | E81: Customer – Office fit-out contractor | F81: Studio Kaya Design | G81: C07 | H81: 2916 | I81: 1 | J81: =H81*I81 -> 2916 | K81: 46333 | L81: 0 | M81: 3 | N81: 46336 | O81: =IF(INT((N81-Assumptions!$C$2)/7)+1>Assumptions!$C$3,"after W13",INT((N81-Assumptions!$C$2)/7)+1) -> 5 | P81: =IF(AND(D81="Receipt",G81="C01"),WORKDAY(N81+Assumptions!$C$14-1,1),N81) -> 46336 | Q81: =IF(INT((P81-Assumptions!$C$2)/7)+1>Assumptions!$C$3,"after W13",INT((P81-Assumptions!$C$2)/7)+1) -> 5 | R81: =IF(AND(D81="Receipt",OR(G81="C01",G81="C02",G81="C03",G81="C04",G81="C07")),WORKDAY(N81+IF(G81="C01",Assumptions!$C$14,Assumptions!$C$15)-1,1),N81) -> 46351 | S81: =IF(INT((R81-Assumptions!$C$2)/7)+1>Assumptions!$C$3,"after W13",INT((R81-Assumptions!$C$2)/7)+1) -> 7 | T81: Open | U81: Yes | V81: Furniture order
A82: L0102 | B82: AR_Invoices | C82: INV-2026-1204 | D82: Receipt | E82: Customer – Office fit-out contractor | F82: Studio Kaya Design | G82: C07 | H82: 5808 | I82: 1 | J82: =H82*I82 -> 5808 | K82: 46333 | L82: 0 | M82: 3 | N82: 46336 | O82: =IF(INT((N82-Assumptions!$C$2)/7)+1>Assumptions!$C$3,"after W13",INT((N82-Assumptions!$C$2)/7)+1) -> 5 | P82: =IF(AND(D82="Receipt",G82="C01"),WORKDAY(N82+Assumptions!$C$14-1,1),N82) -> 46336 | Q82: =IF(INT((P82-Assumptions!$C$2)/7)+1>Assumptions!$C$3,"after W13",INT((P82-Assumptions!$C$2)/7)+1) -> 5 | R82: =IF(AND(D82="Receipt",OR(G82="C01",G82="C02",G82="C03",G82="C04",G82="C07")),WORKDAY(N82+IF(G82="C01",Assumptions!$C$14,Assumptions!$C$15)-1,1),N82) -> 46351 | S82: =IF(INT((R82-Assumptions!$C$2)/7)+1>Assumptions!$C$3,"after W13",INT((R82-Assumptions!$C$2)/7)+1) -> 7 | T82: Open | U82: Yes | V82: Furniture order
A83: L0347 | B83: Scheduled_Payments | C83: PAY-013 | D83: Payment | E83: Card & sundry spending | F83: Fuel, travel, consumables | H83: -4700 | I83: 1 | J83: =H83*I83 -> -4700 | K83: 46337 | N83: 46337 | O83: =IF(INT((N83-Assumptions!$C$2)/7)+1>Assumptions!$C$3,"after W13",INT((N83-Assumptions!$C$2)/7)+1) -> 5 | P83: =IF(AND(D83="Receipt",G83="C01"),WORKDAY(N83+Assumptions!$C$14-1,1),N83) -> 46337 | Q83: =IF(INT((P83-Assumptions!$C$2)/7)+1>Assumptions!$C$3,"after W13",INT((P83-Assumptions!$C$2)/7)+1) -> 5 | R83: =IF(AND(D83="Receipt",OR(G83="C01",G83="C02",G83="C03",G83="C04",G83="C07")),WORKDAY(N83+IF(G83="C01",Assumptions!$C$14,Assumptions!$C$15)-1,1),N83) -> 46337 | S83: =IF(INT((R83-Assumptions!$C$2)/7)+1>Assumptions!$C$3,"after W13",INT((R83-Assumptions!$C$2)/7)+1) -> 5 | T83: Estimate (run-rate) | U83: Yes | V83: Run-rate estimate (avg of last 26 weeks, rounded)
A84: L0025 | B84: AR_Invoices | C84: INV-2026-1125 | D84: Receipt | E84: Customer – Office fit-out contractor | F84: Nova Interiors SARL | G84: C04 | H84: 5820 | I84: 1 | J84: =H84*I84 -> 5820 | K84: 46312 | L84: 0 | M84: 25 | N84: 46337 | O84: =IF(INT((N84-Assumptions!$C$2)/7)+1>Assumptions!$C$3,"after W13",INT((N84-Assumptions!$C$2)/7)+1) -> 5 | P84: =IF(AND(D84="Receipt",G84="C01"),WORKDAY(N84+Assumptions!$C$14-1,1),N84) -> 46337 | Q84: =IF(INT((P84-Assumptions!$C$2)/7)+1>Assumptions!$C$3,"after W13",INT((P84-Assumptions!$C$2)/7)+1) -> 5 | R84: =IF(AND(D84="Receipt",OR(G84="C01",G84="C02",G84="C03",G84="C04",G84="C07")),WORKDAY(N84+IF(G84="C01",Assumptions!$C$14,Assumptions!$C$15)-1,1),N84) -> 46352 | S84: =IF(INT((R84-Assumptions!$C$2)/7)+1>Assumptions!$C$3,"after W13",INT((R84-Assumptions!$C$2)/7)+1) -> 7 | T84: Open | U84: Yes | V84: Furniture order
A85: L0026 | B85: AR_Invoices | C85: INV-2026-1126 | D85: Receipt | E85: Customer – Office fit-out contractor | F85: Nova Interiors SARL | G85: C04 | H85: 9564 | I85: 1 | J85: =H85*I85 -> 9564 | K85: 46312 | L85: 0 | M85: 25 | N85: 46337 | O85: =IF(INT((N85-Assumptions!$C$2)/7)+1>Assumptions!$C$3,"after W13",INT((N85-Assumptions!$C$2)/7)+1) -> 5 | P85: =IF(AND(D85="Receipt",G85="C01"),WORKDAY(N85+Assumptions!$C$14-1,1),N85) -> 46337 | Q85: =IF(INT((P85-Assumptions!$C$2)/7)+1>Assumptions!$C$3,"after W13",INT((P85-Assumptions!$C$2)/7)+1) -> 5 | R85: =IF(AND(D85="Receipt",OR(G85="C01",G85="C02",G85="C03",G85="C04",G85="C07")),WORKDAY(N85+IF(G85="C01",Assumptions!$C$14,Assumptions!$C$15)-1,1),N85) -> 46352 | S85: =IF(INT((R85-Assumptions!$C$2)/7)+1>Assumptions!$C$3,"after W13",INT((R85-Assumptions!$C$2)/7)+1) -> 7 | T85: Open | U85: Yes | V85: Furniture order
A86: L0105 | B86: AR_Invoices | C86: INV-2026-1207 | D86: Receipt | E86: Customer – Office fit-out contractor | F86: Studio Kaya Design | G86: C07 | H86: 2604 | I86: 1 | J86: =H86*I86 -> 2604 | K86: 46334 | L86: 0 | M86: 3 | N86: 46337 | O86: =IF(INT((N86-Assumptions!$C$2)/7)+1>Assumptions!$C$3,"after W13",INT((N86-Assumptions!$C$2)/7)+1) -> 5 | P86: =IF(AND(D86="Receipt",G86="C01"),WORKDAY(N86+Assumptions!$C$14-1,1),N86) -> 46337 | Q86: =IF(INT((P86-Assumptions!$C$2)/7)+1>Assumptions!$C$3,"after W13",INT((P86-Assumptions!$C$2)/7)+1) -> 5 | R86: =IF(AND(D86="Receipt",OR(G86="C01",G86="C02",G86="C03",G86="C04",G86="C07")),WORKDAY(N86+IF(G86="C01",Assumptions!$C$14,Assumptions!$C$15)-1,1),N86) -> 46352 | S86: =IF(INT((R86-Assumptions!$C$2)/7)+1>Assumptions!$C$3,"after W13",INT((R86-Assumptions!$C$2)/7)+1) -> 7 | T86: Open | U86: Yes | V86: Furniture order
A87: L0315 | B87: Committed_Purchases | C87: PO-2603 | D87: Payment | E87: Supplier payment | F87: Quincaillerie Pro Est | H87: -6312.02 | I87: 1 | J87: =H87*I87 -> -6312.02 | K87: 46341 | N87: 46338 | O87: =IF(INT((N87-Assumptions!$C$2)/7)+1>Assumptions!$C$3,"after W13",INT((N87-Assumptions!$C$2)/7)+1) -> 5 | P87: =IF(AND(D87="Receipt",G87="C01"),WORKDAY(N87+Assumptions!$C$14-1,1),N87) -> 46338 | Q87: =IF(INT((P87-Assumptions!$C$2)/7)+1>Assumptions!$C$3,"after W13",INT((P87-Assumptions!$C$2)/7)+1) -> 5 | R87: =IF(AND(D87="Receipt",OR(G87="C01",G87="C02",G87="C03",G87="C04",G87="C07")),WORKDAY(N87+IF(G87="C01",Assumptions!$C$14,Assumptions!$C$15)-1,1),N87) -> 46338 | S87: =IF(INT((R87-Assumptions!$C$2)/7)+1>Assumptions!$C$3,"after W13",INT((R87-Assumptions!$C$2)/7)+1) -> 5 | T87: PO confirmed | U87: Yes | V87: Hardware & fittings
A88: L0081 | B88: AR_Invoices | C88: INV-2026-1183 | D88: Receipt | E88: Customer – Furniture distributor | F88: Officea Distribution | G88: C05 | H88: 18120 | I88: 1 | J88: =H88*I88 -> 18120 | K88: 46339 | L88: 0 | M88: 0 | N88: 46339 | O88: =IF(INT((N88-Assumptions!$C$2)/7)+1>Assumptions!$C$3,"after W13",INT((N88-Assumptions!$C$2)/7)+1) -> 5 | P88: =IF(AND(D88="Receipt",G88="C01"),WORKDAY(N88+Assumptions!$C$14-1,1),N88) -> 46339 | Q88: =IF(INT((P88-Assumptions!$C$2)/7)+1>Assumptions!$C$3,"after W13",INT((P88-Assumptions!$C$2)/7)+1) -> 5 | R88: =IF(AND(D88="Receipt",OR(G88="C01",G88="C02",G88="C03",G88="C04",G88="C07")),WORKDAY(N88+IF(G88="C01",Assumptions!$C$14,Assumptions!$C$15)-1,1),N88) -> 46339 | S88: =IF(INT((R88-Assumptions!$C$2)/7)+1>Assumptions!$C$3,"after W13",INT((R88-Assumptions!$C$2)/7)+1) -> 5 | T88: Open | U88: Yes | V88: Furniture order
A89: L0082 | B89: AR_Invoices | C89: INV-2026-1184 | D89: Receipt | E89: Customer – Furniture distributor | F89: Officea Distribution | G89: C05 | H89: 7452 | I89: 1 | J89: =H89*I89 -> 7452 | K89: 46339 | L89: 0 | M89: 0 | N89: 46339 | O89: =IF(INT((N89-Assumptions!$C$2)/7)+1>Assumptions!$C$3,"after W13",INT((N89-Assumptions!$C$2)/7)+1) -> 5 | P89: =IF(AND(D89="Receipt",G89="C01"),WORKDAY(N89+Assumptions!$C$14-1,1),N89) -> 46339 | Q89: =IF(INT((P89-Assumptions!$C$2)/7)+1>Assumptions!$C$3,"after W13",INT((P89-Assumptions!$C$2)/7)+1) -> 5 | R89: =IF(AND(D89="Receipt",OR(G89="C01",G89="C02",G89="C03",G89="C04",G89="C07")),WORKDAY(N89+IF(G89="C01",Assumptions!$C$14,Assumptions!$C$15)-1,1),N89) -> 46339 | S89: =IF(INT((R89-Assumptions!$C$2)/7)+1>Assumptions!$C$3,"after W13",INT((R89-Assumptions!$C$2)/7)+1) -> 5 | T89: Open | U89: Yes | V89: Furniture order
A90: L0085 | B90: AR_Invoices | C90: INV-2026-1187 | D90: Receipt | E90: Customer – Direct corporate client | F90: Hub & Desk Coworking SAS | G90: C11 | H90: 8004 | I90: 1 | J90: =H90*I90 -> 8004 | K90: 46327 | L90: 0 | M90: 12 | N90: 46339 | O90: =IF(INT((N90-Assumptions!$C$2)/7)+1>Assumptions!$C$3,"after W13",INT((N90-Assumptions!$C$2)/7)+1) -> 5 | P90: =IF(AND(D90="Receipt",G90="C01"),WORKDAY(N90+Assumptions!$C$14-1,1),N90) -> 46339 | Q90: =IF(INT((P90-Assumptions!$C$2)/7)+1>Assumptions!$C$3,"after W13",INT((P90-Assumptions!$C$2)/7)+1) -> 5 | R90: =IF(AND(D90="Receipt",OR(G90="C01",G90="C02",G90="C03",G90="C04",G90="C07")),WORKDAY(N90+IF(G90="C01",Assumptions!$C$14,Assumptions!$C$15)-1,1),N90) -> 46339 | S90: =IF(INT((R90-Assumptions!$C$2)/7)+1>Assumptions!$C$3,"after W13",INT((R90-Assumptions!$C$2)/7)+1) -> 5 | T90: Open | U90: Yes | V90: Furniture order
A91: L0348 | B91: Scheduled_Payments | C91: PAY-014 | D91: Payment | E91: Social charges & income tax withheld | F91: URSSAF / AGIRC-ARRCO / DGFiP (PAS) | H91: -86000 | I91: 1 | J91: =H91*I91 -> -86000 | K91: 46342 | N91: 46342 | O91: =IF(INT((N91-Assumptions!$C$2)/7)+1>Assumptions!$C$3,"after W13",INT((N91-Assumptions!$C$2)/7)+1) -> 6 | P91: =IF(AND(D91="Receipt",G91="C01"),WORKDAY(N91+Assumptions!$C$14-1,1),N91) -> 46342 | Q91: =IF(INT((P91-Assumptions!$C$2)/7)+1>Assumptions!$C$3,"after W13",INT((P91-Assumptions!$C$2)/7)+1) -> 6 | R91: =IF(AND(D91="Receipt",OR(G91="C01",G91="C02",G91="C03",G91="C04",G91="C07")),WORKDAY(N91+IF(G91="C01",Assumptions!$C$14,Assumptions!$C$15)-1,1),N91) -> 46342 | S91: =IF(INT((R91-Assumptions!$C$2)/7)+1>Assumptions!$C$3,"after W13",INT((R91-Assumptions!$C$2)/7)+1) -> 6 | T91: Contractual / statutory | U91: Yes | V91: for previous month's payroll
A92: L0034 | B92: AR_Invoices | C92: INV-2026-1135 | D92: Receipt | E92: Customer – Office fit-out contractor | F92: Espace & Co Aménagement | G92: C03 | H92: 40488 | I92: 1 | J92: =H92*I92 -> 40488 | K92: 46332 | L92: 0 | M92: 10 | N92: 46342 | O92: =IF(INT((N92-Assumptions!$C$2)/7)+1>Assumptions!$C$3,"after W13",INT((N92-Assumptions!$C$2)/7)+1) -> 6 | P92: =IF(AND(D92="Receipt",G92="C01"),WORKDAY(N92+Assumptions!$C$14-1,1),N92) -> 46342 | Q92: =IF(INT((P92-Assumptions!$C$2)/7)+1>Assumptions!$C$3,"after W13",INT((P92-Assumptions!$C$2)/7)+1) -> 6 | R92: =IF(AND(D92="Receipt",OR(G92="C01",G92="C02",G92="C03",G92="C04",G92="C07")),WORKDAY(N92+IF(G92="C01",Assumptions!$C$14,Assumptions!$C$15)-1,1),N92) -> 46357 | S92: =IF(INT((R92-Assumptions!$C$2)/7)+1>Assumptions!$C$3,"after W13",INT((R92-Assumptions!$C$2)/7)+1) -> 8 | T92: Open | U92: Yes | V92: Furniture order
A93: L0041 | B93: AR_Invoices | C93: INV-2026-1143 | D93: Receipt | E93: Customer – Export distributor | F93: Arkade Interiors SRL | G93: C12 | H93: 13020 | I93: 1 | J93: =H93*I93 -> 13020 | K93: 46335 | L93: 0 | M93: 6 | N93: 46342 | O93: =IF(INT((N93-Assumptions!$C$2)/7)+1>Assumptions!$C$3,"after W13",INT((N93-Assumptions!$C$2)/7)+1) -> 6 | P93: =IF(AND(D93="Receipt",G93="C01"),WORKDAY(N93+Assumptions!$C$14-1,1),N93) -> 46342 | Q93: =IF(INT((P93-Assumptions!$C$2)/7)+1>Assumptions!$C$3,"after W13",INT((P93-Assumptions!$C$2)/7)+1) -> 6 | R93: =IF(AND(D93="Receipt",OR(G93="C01",G93="C02",G93="C03",G93="C04",G93="C07")),WORKDAY(N93+IF(G93="C01",Assumptions!$C$14,Assumptions!$C$15)-1,1),N93) -> 46342 | S93: =IF(INT((R93-Assumptions!$C$2)/7)+1>Assumptions!$C$3,"after W13",INT((R93-Assumptions!$C$2)/7)+1) -> 6 | T93: Open | U93: Yes | V93: Furniture order
A94: L0072 | B94: AR_Invoices | C94: INV-2026-1174 | D94: Receipt | E94: Customer – Furniture distributor | F94: Mobilier Pro Rhône | G94: C06 | H94: 8100 | I94: 1 | J94: =H94*I94 -> 8100 | K94: 46335 | L94: 0 | M94: 7 | N94: 46342 | O94: =IF(INT((N94-Assumptions!$C$2)/7)+1>Assumptions!$C$3,"after W13",INT((N94-Assumptions!$C$2)/7)+1) -> 6 | P94: =IF(AND(D94="Receipt",G94="C01"),WORKDAY(N94+Assumptions!$C$14-1,1),N94) -> 46342 | Q94: =IF(INT((P94-Assumptions!$C$2)/7)+1>Assumptions!$C$3,"after W13",INT((P94-Assumptions!$C$2)/7)+1) -> 6 | R94: =IF(AND(D94="Receipt",OR(G94="C01",G94="C02",G94="C03",G94="C04",G94="C07")),WORKDAY(N94+IF(G94="C01",Assumptions!$C$14,Assumptions!$C$15)-1,1),N94) -> 46342 | S94: =IF(INT((R94-Assumptions!$C$2)/7)+1>Assumptions!$C$3,"after W13",INT((R94-Assumptions!$C$2)/7)+1) -> 6 | T94: Open | U94: Yes | V94: Furniture order
A95: L0087 | B95: AR_Invoices | C95: INV-2026-1189 | D95: Receipt | E95: Customer – Furniture distributor | F95: Officea Distribution | G95: C05 | H95: 9444 | I95: 1 | J95: =H95*I95 -> 9444 | K95: 46342 | L95: 0 | M95: 0 | N95: 46342 | O95: =IF(INT((N95-Assumptions!$C$2)/7)+1>Assumptions!$C$3,"after W13",INT((N95-Assumptions!$C$2)/7)+1) -> 6 | P95: =IF(AND(D95="Receipt",G95="C01"),WORKDAY(N95+Assumptions!$C$14-1,1),N95) -> 46342 | Q95: =IF(INT((P95-Assumptions!$C$2)/7)+1>Assumptions!$C$3,"after W13",INT((P95-Assumptions!$C$2)/7)+1) -> 6 | R95: =IF(AND(D95="Receipt",OR(G95="C01",G95="C02",G95="C03",G95="C04",G95="C07")),WORKDAY(N95+IF(G95="C01",Assumptions!$C$14,Assumptions!$C$15)-1,1),N95) -> 46342 | S95: =IF(INT((R95-Assumptions!$C$2)/7)+1>Assumptions!$C$3,"after W13",INT((R95-Assumptions!$C$2)/7)+1) -> 6 | T95: Open | U95: Yes | V95: Furniture order
A96: L0088 | B96: AR_Invoices | C96: INV-2026-1190 | D96: Receipt | E96: Customer – Furniture distributor | F96: Officea Distribution | G96: C05 | H96: 6360 | I96: 1 | J96: =H96*I96 -> 6360 | K96: 46342 | L96: 0 | M96: 0 | N96: 46342 | O96: =IF(INT((N96-Assumptions!$C$2)/7)+1>Assumptions!$C$3,"after W13",INT((N96-Assumptions!$C$2)/7)+1) -> 6 | P96: =IF(AND(D96="Receipt",G96="C01"),WORKDAY(N96+Assumptions!$C$14-1,1),N96) -> 46342 | Q96: =IF(INT((P96-Assumptions!$C$2)/7)+1>Assumptions!$C$3,"after W13",INT((P96-Assumptions!$C$2)/7)+1) -> 6 | R96: =IF(AND(D96="Receipt",OR(G96="C01",G96="C02",G96="C03",G96="C04",G96="C07")),WORKDAY(N96+IF(G96="C01",Assumptions!$C$14,Assumptions!$C$15)-1,1),N96) -> 46342 | S96: =IF(INT((R96-Assumptions!$C$2)/7)+1>Assumptions!$C$3,"after W13",INT((R96-Assumptions!$C$2)/7)+1) -> 6 | T96: Open | U96: Yes | V96: Furniture order
A97: L0104 | B97: AR_Invoices | C97: INV-2026-1206 | D97: Receipt | E97: Customer – Public sector | F97: Université Lyon-Est | G97: C08 | H97: 18588 | I97: 1 | J97: =H97*I97 -> 18588 | K97: 46334 | L97: 0 | M97: 8.5 | N97: 46342 | O97: =IF(INT((N97-Assumptions!$C$2)/7)+1>Assumptions!$C$3,"after W13",INT((N97-Assumptions!$C$2)/7)+1) -> 6 | P97: =IF(AND(D97="Receipt",G97="C01"),WORKDAY(N97+Assumptions!$C$14-1,1),N97) -> 46342 | Q97: =IF(INT((P97-Assumptions!$C$2)/7)+1>Assumptions!$C$3,"after W13",INT((P97-Assumptions!$C$2)/7)+1) -> 6 | R97: =IF(AND(D97="Receipt",OR(G97="C01",G97="C02",G97="C03",G97="C04",G97="C07")),WORKDAY(N97+IF(G97="C01",Assumptions!$C$14,Assumptions!$C$15)-1,1),N97) -> 46342 | S97: =IF(INT((R97-Assumptions!$C$2)/7)+1>Assumptions!$C$3,"after W13",INT((R97-Assumptions!$C$2)/7)+1) -> 6 | T97: Open | U97: Yes | V97: Furniture order
A98: L0095 | B98: AR_Invoices | C98: INV-2026-1197 | D98: Receipt | E98: Customer – Direct corporate client | F98: Hub & Desk Coworking SAS | G98: C11 | H98: 7680 | I98: 1 | J98: =H98*I98 -> 7680 | K98: 46331 | L98: 0 | M98: 12 | N98: 46343 | O98: =IF(INT((N98-Assumptions!$C$2)/7)+1>Assumptions!$C$3,"after W13",INT((N98-Assumptions!$C$2)/7)+1) -> 6 | P98: =IF(AND(D98="Receipt",G98="C01"),WORKDAY(N98+Assumptions!$C$14-1,1),N98) -> 46343 | Q98: =IF(INT((P98-Assumptions!$C$2)/7)+1>Assumptions!$C$3,"after W13",INT((P98-Assumptions!$C$2)/7)+1) -> 6 | R98: =IF(AND(D98="Receipt",OR(G98="C01",G98="C02",G98="C03",G98="C04",G98="C07")),WORKDAY(N98+IF(G98="C01",Assumptions!$C$14,Assumptions!$C$15)-1,1),N98) -> 46343 | S98: =IF(INT((R98-Assumptions!$C$2)/7)+1>Assumptions!$C$3,"after W13",INT((R98-Assumptions!$C$2)/7)+1) -> 6 | T98: Open | U98: Yes | V98: Furniture order
A99: L0349 | B99: Scheduled_Payments | C99: PAY-015 | D99: Payment | E99: Card & sundry spending | F99: Fuel, travel, consumables | H99: -4700 | I99: 1 | J99: =H99*I99 -> -4700 | K99: 46344 | N99: 46344 | O99: =IF(INT((N99-Assumptions!$C$2)/7)+1>Assumptions!$C$3,"after W13",INT((N99-Assumptions!$C$2)/7)+1) -> 6 | P99: =IF(AND(D99="Receipt",G99="C01"),WORKDAY(N99+Assumptions!$C$14-1,1),N99) -> 46344 | Q99: =IF(INT((P99-Assumptions!$C$2)/7)+1>Assumptions!$C$3,"after W13",INT((P99-Assumptions!$C$2)/7)+1) -> 6 | R99: =IF(AND(D99="Receipt",OR(G99="C01",G99="C02",G99="C03",G99="C04",G99="C07")),WORKDAY(N99+IF(G99="C01",Assumptions!$C$14,Assumptions!$C$15)-1,1),N99) -> 46344 | S99: =IF(INT((R99-Assumptions!$C$2)/7)+1>Assumptions!$C$3,"after W13",INT((R99-Assumptions!$C$2)/7)+1) -> 6 | T99: Estimate (run-rate) | U99: Yes | V99: Run-rate estimate (avg of last 26 weeks, rounded)
A100: L0039 | B100: AR_Invoices | C100: INV-2026-1141 | D100: Receipt | E100: Customer – Office fit-out contractor | F100: Espace & Co Aménagement | G100: C03 | H100: 4440 | I100: 1 | J100: =H100*I100 -> 4440 | K100: 46334 | L100: 0 | M100: 10 | N100: 46344 | O100: =IF(INT((N100-Assumptions!$C$2)/7)+1>Assumptions!$C$3,"after W13",INT((N100-Assumptions!$C$2)/7)+1) -> 6 | P100: =IF(AND(D100="Receipt",G100="C01"),WORKDAY(N100+Assumptions!$C$14-1,1),N100) -> 46344 | Q100: =IF(INT((P100-Assumptions!$C$2)/7)+1>Assumptions!$C$3,"after W13",INT((P100-Assumptions!$C$2)/7)+1) -> 6 | R100: =IF(AND(D100="Receipt",OR(G100="C01",G100="C02",G100="C03",G100="C04",G100="C07")),WORKDAY(N100+IF(G100="C01",Assumptions!$C$14,Assumptions!$C$15)-1,1),N100) -> 46359 | S100: =IF(INT((R100-Assumptions!$C$2)/7)+1>Assumptions!$C$3,"after W13",INT((R100-Assumptions!$C$2)/7)+1) -> 8 | T100: Open | U100: Yes | V100: Furniture order
A101: L0123 | B101: Order_Book | C101: ORD-2615 | D101: Receipt | E101: Customer – Office fit-out contractor | F101: Studio Kaya Design | G101: C07 | H101: 3000 | I101: 1 | J101: =H101*I101 -> 3000 | K101: 46341 | L101: 0 | M101: 3 | N101: 46344 | O101: =IF(INT((N101-Assumptions!$C$2)/7)+1>Assumptions!$C$3,"after W13",INT((N101-Assumptions!$C$2)/7)+1) -> 6 | P101: =IF(AND(D101="Receipt",G101="C01"),WORKDAY(N101+Assumptions!$C$14-1,1),N101) -> 46344 | Q101: =IF(INT((P101-Assumptions!$C$2)/7)+1>Assumptions!$C$3,"after W13",INT((P101-Assumptions!$C$2)/7)+1) -> 6 | R101: =IF(AND(D101="Receipt",OR(G101="C01",G101="C02",G101="C03",G101="C04",G101="C07")),WORKDAY(N101+IF(G101="C01",Assumptions!$C$14,Assumptions!$C$15)-1,1),N101) -> 46359 | S101: =IF(INT((R101-Assumptions!$C$2)/7)+1>Assumptions!$C$3,"after W13",INT((R101-Assumptions!$C$2)/7)+1) -> 8 | T101: Confirmed order | U101: Yes | V101: Furniture order
...

Sheet Backtest
A1: Backtest — how accurate would this method have been?
A2: 66 weekly forecasts made every Friday from 04 Apr 2025 to 03 Jul 2026, each looking 13 weeks ahead, compared with the actual bank balance. Only information available on each forecast date is used for customer behaviour. Simplifications: payments and future invoices are taken as known (the test isolates the hard part — when customers pay).
A4: Headline accuracy
A5: metric | B5: this method (customer delays) | C5: naive (pay on due date) | D5: improvement
A6: Mean absolute error of weekly closing balance | B6: =SUMPRODUCT(ABS($G$40:$G$897))/COUNT($G$40:$G$897) -> 77019.249 | C6: =SUMPRODUCT(ABS($H$40:$H$897))/COUNT($H$40:$H$897) -> 304466.41 | D6: =1-B6/C6 -> 0.74703532
A7: Bias (average error; + = too optimistic) | B7: =AVERAGE($G$40:$G$897) -> 53591.646 | C7: =AVERAGE($H$40:$H$897) -> 304466.41
A8: MAE at week 4 | B8: =SUMPRODUCT(($B$40:$B$897=4)*ABS($G$40:$G$897))/COUNTIF($B$40:$B$897,4) -> 79938.606 | C8: =SUMPRODUCT(($B$40:$B$897=4)*ABS($H$40:$H$897))/COUNTIF($B$40:$B$897,4) -> 301609.03 | D8: =1-B8/C8 -> 0.73495951
A9: MAE at week 13 | B9: =SUMPRODUCT(($B$40:$B$897=13)*ABS($G$40:$G$897))/COUNTIF($B$40:$B$897,13) -> 87055.848 | C9: =SUMPRODUCT(($B$40:$B$897=13)*ABS($H$40:$H$897))/COUNTIF($B$40:$B$897,13) -> 308698.45 | D9: =1-B9/C9 -> 0.71799066
A11: Method comparison (tested before choosing)
A12: timing rule | B12: MAE | C12: bias | D12: comment
A13: Median delay per customer (chosen) | B13: 77019 | C13: 53592 | D13: Simple to explain: 'Bâtir Bureaux usually pays 21 days late'.
A14: Mean delay per customer | B14: 71970 | C14: 34781 | D14: Slightly better on average, but pulled by rare very late payments.
A15: Probability-weighted (spread each invoice over weeks) | B15: 66584 | C15: 42065 | D15: Best accuracy (−14% MAE); planned for version 2 — harder to show line by line.
A16: Naive: everyone pays on the due date | B16: 304466 | C16: 304466 | D16: What a basic spreadsheet does; always too optimistic.
A18: Warning lead time (actual weeks below the €100k buffer)
A19: episode starts (week of) | B19: lowest actual balance | C19: weeks below buffer | D19: lead time — this method (weeks) | E19: lead time — naive (weeks) | F19: comment
A20: 45838 | B20: -38211 | C20: 5 | D20: 0 | E20: 0 | F20: Missed: only ~4 months of payment history existed when these forecasts were made, and a dividend plus summer slowdown were under-estimated. Shows why a learning period is needed.
A21: 45957 | B21: 1503 | C21: 2 | D21: 12 | E21: 0 | F21: Flagged by the very first forecast that covered this week (maximum possible lead time); the naive forecast never flagged it.
A23: False alarms: 31% of this method's 'below buffer' weeks did not actually go below the buffer (naive forecast: never warns at all). A cautious warning is acceptable because the CFO reviews each one; the optimistic bias is covered by the buffer and the P10 band.
A25: Error by forecast horizon
A26: horizon (weeks ahead) | B26: 1 | C26: 2 | D26: 3 | E26: 4 | F26: 5 | G26: 6 | H26: 7 | I26: 8 | J26: 9 | K26: 10 | L26: 11 | M26: 12 | N26: 13
A27: MAE — this method | B27: =SUMPRODUCT(($B$40:$B$897=1)*ABS($G$40:$G$897))/COUNTIF($B$40:$B$897,1) -> 48232 | C27: =SUMPRODUCT(($B$40:$B$897=2)*ABS($G$40:$G$897))/COUNTIF($B$40:$B$897,2) -> 62026.212 | D27: =SUMPRODUCT(($B$40:$B$897=3)*ABS($G$40:$G$897))/COUNTIF($B$40:$B$897,3) -> 75663.303 | E27: =SUMPRODUCT(($B$40:$B$897=4)*ABS($G$40:$G$897))/COUNTIF($B$40:$B$897,4) -> 79938.606 | F27: =SUMPRODUCT(($B$40:$B$897=5)*ABS($G$40:$G$897))/COUNTIF($B$40:$B$897,5) -> 80411.727 | G27: =SUMPRODUCT(($B$40:$B$897=6)*ABS($G$40:$G$897))/COUNTIF($B$40:$B$897,6) -> 80814.303 | H27: =SUMPRODUCT(($B$40:$B$897=7)*ABS($G$40:$G$897))/COUNTIF($B$40:$B$897,7) -> 79718.515 | I27: =SUMPRODUCT(($B$40:$B$897=8)*ABS($G$40:$G$897))/COUNTIF($B$40:$B$897,8) -> 78502.424 | J27: =SUMPRODUCT(($B$40:$B$897=9)*ABS($G$40:$G$897))/COUNTIF($B$40:$B$897,9) -> 79747 | K27: =SUMPRODUCT(($B$40:$B$897=10)*ABS($G$40:$G$897))/COUNTIF($B$40:$B$897,10) -> 82924.545 | L27: =SUMPRODUCT(($B$40:$B$897=11)*ABS($G$40:$G$897))/COUNTIF($B$40:$B$897,11) -> 82316.303 | M27: =SUMPRODUCT(($B$40:$B$897=12)*ABS($G$40:$G$897))/COUNTIF($B$40:$B$897,12) -> 83899.455 | N27: =SUMPRODUCT(($B$40:$B$897=13)*ABS($G$40:$G$897))/COUNTIF($B$40:$B$897,13) -> 87055.848
A28: MAE — naive | B28: =SUMPRODUCT(($B$40:$B$897=1)*ABS($H$40:$H$897))/COUNTIF($B$40:$B$897,1) -> 293722.64 | C28: =SUMPRODUCT(($B$40:$B$897=2)*ABS($H$40:$H$897))/COUNTIF($B$40:$B$897,2) -> 295128.94 | D28: =SUMPRODUCT(($B$40:$B$897=3)*ABS($H$40:$H$897))/COUNTIF($B$40:$B$897,3) -> 296700.27 | E28: =SUMPRODUCT(($B$40:$B$897=4)*ABS($H$40:$H$897))/COUNTIF($B$40:$B$897,4) -> 301609.03 | F28: =SUMPRODUCT(($B$40:$B$897=5)*ABS($H$40:$H$897))/COUNTIF($B$40:$B$897,5) -> 304364.3 | G28: =SUMPRODUCT(($B$40:$B$897=6)*ABS($H$40:$H$897))/COUNTIF($B$40:$B$897,6) -> 304744.36 | H28: =SUMPRODUCT(($B$40:$B$897=7)*ABS($H$40:$H$897))/COUNTIF($B$40:$B$897,7) -> 305608.09 | I28: =SUMPRODUCT(($B$40:$B$897=8)*ABS($H$40:$H$897))/COUNTIF($B$40:$B$897,8) -> 306721.27 | J28: =SUMPRODUCT(($B$40:$B$897=9)*ABS($H$40:$H$897))/COUNTIF($B$40:$B$897,9) -> 309350.97 | K28: =SUMPRODUCT(($B$40:$B$897=10)*ABS($H$40:$H$897))/COUNTIF($B$40:$B$897,10) -> 310380.88 | L28: =SUMPRODUCT(($B$40:$B$897=11)*ABS($H$40:$H$897))/COUNTIF($B$40:$B$897,11) -> 310820.24 | M28: =SUMPRODUCT(($B$40:$B$897=12)*ABS($H$40:$H$897))/COUNTIF($B$40:$B$897,12) -> 310213.88 | N28: =SUMPRODUCT(($B$40:$B$897=13)*ABS($H$40:$H$897))/COUNTIF($B$40:$B$897,13) -> 308698.45
A38: Raw backtest data (one row per forecast date × week ahead)
A39: forecast_date | B39: weeks_ahead | C39: week_start | D39: actual_closing | E39: forecast_this_method | F39: forecast_naive | G39: error_this_method | H39: error_naive
A40: 45751 | B40: 1 | C40: 45754 | D40: 302474.28 | E40: 308368.28 | F40: 540564.28 | G40: =E40-D40 -> 5894 | H40: =F40-D40 -> 238090
A41: 45751 | B41: 2 | C41: 45761 | D41: 294118.24 | E41: 316458.24 | F41: 530190.24 | G41: =E41-D41 -> 22340 | H41: =F41-D41 -> 236072
A42: 45751 | B42: 3 | C42: 45768 | D42: 357614.31 | E42: 371268.31 | F42: 529632.31 | G42: =E42-D42 -> 13654 | H42: =F42-D42 -> 172018
A43: 45751 | B43: 4 | C43: 45775 | D43: 238614.09 | E43: 259672.09 | F43: 477114.09 | G43: =E43-D43 -> 21058 | H43: =F43-D43 -> 238500
A44: 45751 | B44: 5 | C44: 45782 | D44: 247095.82 | E44: 322779.82 | F44: 513399.82 | G44: =E44-D44 -> 75684 | H44: =F44-D44 -> 266304
A45: 45751 | B45: 6 | C45: 45789 | D45: 199788.7 | E45: 285288.7 | F45: 515732.7 | G45: =E45-D45 -> 85500 | H45: =F45-D45 -> 315944
A46: 45751 | B46: 7 | C46: 45796 | D46: 295509.67 | E46: 433107.67 | F46: 608979.67 | G46: =E46-D46 -> 137598 | H46: =F46-D46 -> 313470
A47: 45751 | B47: 8 | C47: 45803 | D47: 151538.04 | E47: 254348.04 | F47: 382978.04 | G47: =E47-D47 -> 102810 | H47: =F47-D47 -> 231440
A48: 45751 | B48: 9 | C48: 45810 | D48: 238869.46 | E48: 241767.46 | F48: 427239.46 | G48: =E48-D48 -> 2898 | H48: =F48-D48 -> 188370
A49: 45751 | B49: 10 | C49: 45817 | D49: 294525.89 | E49: 373033.89 | F49: 540927.89 | G49: =E49-D49 -> 78508 | H49: =F49-D49 -> 246402
A50: 45751 | B50: 11 | C50: 45824 | D50: 289454.93 | E50: 309164.93 | F50: 534974.93 | G50: =E50-D50 -> 19710 | H50: =F50-D50 -> 245520
A51: 45751 | B51: 12 | C51: 45831 | D51: 240598.9 | E51: 263948.9 | F51: 492488.9 | G51: =E51-D51 -> 23350 | H51: =F51-D51 -> 251890
... A897: 46206 | B897: 13 | C897: 46293 | D897: 434308.31 | E897: 442828.31 | F897: 586180.31 | G897: =E897-D897 -> 8520 | H897: =F897-D897 -> 151872

Sheet Assumptions
A1: id | B1: assumption | C1: value | D1: unit | E1: source / evidence | F1: owner | G1: last_updated | H1: confidence | I1: used_for
A2: A01 | B2: Forecast start (Monday of week 1) | C2: 46307 | D2: date | E2: Data cut-off Fri 9 Oct 2026 | F2: CFO | G2: 46304 | H2: High | I2: Week numbering
A3: A02 | B3: Forecast horizon | C3: 13 | D3: weeks | E3: Treasury standard (one quarter) | F3: CFO | G3: 46304 | H3: High | I3: Window
A4: A03 | B4: Opening cash balance | C4: =Bank_Accounts!F4 -> 381240.65 | D4: EUR | E4: Bank feeds (EBICS + PSD2), 9 Oct 2026 18:00 | F4: System | G4: 46304 | H4: High | I4: Starting point
A5: A04 | B5: Minimum cash buffer | C5: 100000 | D5: EUR | E5: CFO policy ≈ 2 weeks of payroll + charges | F5: CFO | G5: 46037 | H5: High | I5: Warning threshold
A6: A05 | B6: Overdraft facility | C6: =Bank_Accounts!H4 -> 150000 | D6: EUR | E6: Facility letter, Banque Régionale | F6: CFO | G6: 46082 | H6: High | I6: Hard limit
A7: A06 | B7: Customer payment date = due date + customer's typical days late | C7: median, last 12 months | D7: rule | E7: AR_Invoices history (paid invoices) | F7: Model (reviewed by accountant) | G7: 46304 | H7: Medium | I7: Receipts timing
A8: A07 | B8: Look-back window for payment behaviour | C8: 12 | D8: months | E8: Balances recency vs. sample size | F8: Analyst | G8: 46304 | H8: Medium | I8: A06
A9: A08 | B9: Pipeline orders (not yet confirmed) probability | C9: 0.8 | D9: % | E9: Historical order conversion (sales team estimate) | F9: Sales director | G9: 46300 | H9: Low | I9: Order_Book
A10: A09 | B10: Weekly card & sundry spending | C10: 4700 | D10: EUR/week | E10: Average of last 26 weeks, rounded | F10: Accountant | G10: 46304 | H10: Medium | I10: Scheduled_Payments
A11: A10 | B11: Suppliers paid on the Thursday on or before due date | C11: Thursday run | D11: rule | E11: Company payment policy | F11: Accountant | G11: 46037 | H11: High | I11: Payments timing
A12: A11 | B12: VAT for Oct & Nov 2026 | C12: estimated | D12: rule | E12: Output VAT on invoices − deductible VAT on bills | F12: Accountant | G12: 46304 | H12: Medium | I12: VAT payments
A13: A12 | B13: Disputed invoices excluded from base receipts until resolved | C13: excluded | D13: rule | E13: Prudence | F13: CFO | G13: 46304 | H13: High | I13: Receipts
A14: S01 | B14: Scenario: extra delay on Lumen Hospitality payments | C14: 45 | D14: days | E14: Lumen's project manager flagged snags at Annecy installation (scenario) | F14: CFO | G14: 46304 | H14: Scenario | I14: Delayed-payment scenario
A15: S02 | B15: Scenario: extra delay for office fit-out contractors | C15: 15 | D15: days | E15: Sector slowdown; Nova Interiors already slowing | F15: CFO | G15: 46304 | H15: Scenario | I15: Stress scenario
A17: Legend: blue = editable input · green = linked to another sheet · yellow = key assumption the CFO reviews weekly. Each change should update 'last_updated' and be noted in the change log of the proposal.

Sheet Data_Sources
A1: Basis of each data attribute — regulation, published statistic, or stated assumption
A2: All entities and amounts are fictional. Real rules and statistics were used to make the simulated behaviour realistic. 'Assumption' = chosen by the author, not taken from a source.
A4: attribute in dataset | B4: value used | C4: basis | D4: type | E4: source
A5: Customer payment terms (Customers.payment_terms_days) | B5: 30 / 45 / 60 days | C5: French B2B maximum: 60 days from invoice or 45 days end of month; 30 days if nothing agreed (Commercial Code, LME law). | D5: Regulation | E5: https://rubypayeur.com/blog/loi-lme/
A6: Late-payment penalties & €40 fee (CFO_Actions A1) | B6: used as leverage | C6: Penalty rate and €40 fixed recovery indemnity must appear in terms of sale. | D6: Regulation | E6: https://rubypayeur.com/blog/loi-lme/
A7: Public customers' terms (C08 university, C09 hospital) | B7: 30 days / 50 days | C7: Public buyers must pay within 30 days; public health establishments within 50 days. | D7: Regulation | E7: https://www.code-commande-publique.com/delais-de-paiement-l2192-10-s
A8: Hospital actual behaviour (C09 ≈ 50 + 20 days) | B8: ≈ 70 days total | C8: Public health establishments averaged 71.3 days in mainland France vs a 50-day limit. | D8: Statistic (Banque de France, ODP report 2025) | E8: https://www.banque-france.fr/system/files/2026-09/CP_RA-ODP_20260924.pdf
A9: Average days late across all customers (AR_Invoices.days_late) | B9: 10.2 days (simulated) | C9: Calibrated to French averages: 13.4 days late overall, 11.2 in industry, 12.1 for firms with 10–49 employees (Q4 2025, Altares data cited by the Observatoire). | D9: Statistic (calibration target) | E9: https://www.banque-france.fr/system/files/2026-07/ODP2025_WEB.pdf
A10: Share of payments > 30 days late | B10: 6.2% (simulated) | C10: France 2025: 8.6% of payments more than 30 days late. Our 6% 'long delay' shock (15–40 extra days) reproduces this order of magnitude. | D10: Statistic (calibration target) | E10: https://www.banque-france.fr/system/files/2026-07/ODP2025_WEB.pdf
A11: DSO ≈ 67 days | B11: ≈ 67 days | C11: Deliberately higher than the national average client delay (28 days, all companies incl. cash sales) because Atelier Verde sells B2B on 45–60 day terms to contractors who wait for their own clients. Assumption. | D11: Assumption (contrast with statistic) | E11: https://www.banque-france.fr/system/files/2026-07/ODP2025_WEB.pdf
A12: Social charges date (Scheduled_Payments) | B12: 15th of following month | C12: Companies with fewer than 50 employees file the DSN and pay contributions on the 15th of M+1 (5th for 50+). | D12: Regulation | E12: https://www.swim.legal/blog/urssaf-societe-role-obligations-declarations-entreprises-2026
A13: VAT payment date (VAT_Returns) | B13: 24th of following month | C13: Monthly CA3 return due between the 15th and 24th of M+1 depending on legal form and tax office; latest date assumed. | D13: Regulation + assumption | E13: https://www.swim.legal/blog/tva-ca3-declaration-echeances-lignes
A14: VAT rate | B14: 20% | C14: Standard French VAT rate. | D14: Regulation (general knowledge)
A15: No VAT on German supplier and Belgian customer | B15: reverse charge | C15: Intra-EU transactions: VAT is self-assessed by the buyer (autoliquidation) and reported on the CA3, so no VAT cash flow. | D15: Regulation | E15: https://www.swim.legal/blog/tva-ca3-declaration-echeances-lignes
A16: Corporate tax instalments | B16: 15 Mar / Jun / Sep / Dec | C16: Four fixed instalment dates for corporate income tax (acomptes d'IS). | D16: Regulation | E16: https://bpifrance-creation.fr/entrepreneur/actualites/acompte-dimpot-societes
A17: Business property tax (CFE) on 15 Dec, 13th-month bonus | B17: 15 Dec / December payroll | C17: Common French practice; not verified against a specific source. | D17: Assumption
A18: 13-week, weekly, rolling horizon | B18: 13 weeks | C18: Treasury standard for near-term liquidity; required by lenders in stressed situations. | D18: Industry practice | E18: https://www.kognitos.com/blog/13-week-cash-flow-forecasting-treasury-standard-how-ai-changes-it-2026/
A19: Bank connectivity (Bank_Accounts.source_channel) | B19: EBICS, PSD2 | C19: Financial Navigator connects to ~4,900 banks via Host-to-Host, EBICS or PSD2. | D19: Company information | E19: https://app.dealroom.co/companies/a352
A20: Milestone billing 30/40/30 for hotel projects | B20: 30% / 40% / 30% | C20: Typical structure for project-based fit-out contracts. | D20: Assumption
A21: Cost structure (materials ≈ 44%, staff ≈ 36%, EBITDA ≈ 8%) | B21: see PnL_Monthly | C21: Chosen to represent a thin-margin make-to-order manufacturer; not benchmarked against sector data. | D21: Assumption
A22: Seasonality (August slump, Sep–Nov peak, Christmas closure) | B22: monthly factors 0.55–1.20 | C22: Typical for office furniture (year-end budgets, summer closure). | D22: Assumption
A23: Overdraft €150k at EURIBOR + 2.5%, buffer €100k | B23: see Assumptions | C23: Plausible SME facility; buffer ≈ two weeks of payroll and social charges. | D23: Assumption
A24: Customer payment behaviour per customer | B24: normal distribution per customer + 6% long-delay shock | C24: Simulated with a fixed random seed; Nova Interiors given a deteriorating trend to test anomaly detection. | D24: Simulation design
A25: Company, customers, suppliers, banks, people | B25: all fictional | C25: Invented names; any resemblance is coincidental. | D25: Fictional

Sheet Data_Dictionary
A1: sheet | B1: column | C1: meaning
A2: Bank_Accounts | B2: balance_eur | C2: Cleared balance at the cut-off time
A3: Bank_Accounts | B3: overdraft_limit_eur | C3: Authorised overdraft (negative balance allowed up to this amount)
A4: Bank_Weekly | B4: receipts_eur / payments_eur | C4: Total money in / out during the Monday–Sunday week
A5: Bank_Transactions | B5: category | C5: Cash-flow category assigned by the bank-feed rules
A6: Customers | B6: payment_terms_days | C6: Contractual days between invoice date and due date
A7: Customers | B7: avg_days_late_12m | C7: Calculated: average (payment date − due date) over invoices paid since 10 Oct 2025
A8: AR_Invoices | B8: amount_incl_vat | C8: What the customer actually pays (cash); ex_vat is the revenue in the P&L
A9: AR_Invoices | B9: days_late | C9: Payment date − due date (negative = paid early)
A10: AR_Invoices | B10: status | C10: Paid / Open / Open – disputed
A11: AR_Invoices | B11: project | C11: Hotel project code for milestone invoices (blank = regular order)
A12: Order_Book | B12: order_status | C12: Contract signed – milestone / Confirmed order / Pipeline (not yet ordered)
... A18: PnL_Monthly | B18: basis | C18: Actual (closed months) or Forecast (Oct–Dec 2026)

Sheet Bank_Accounts
A1: account_id | B1: bank | C1: account_type | D1: iban_masked | E1: currency | F1: balance_eur | G1: as_at | H1: overdraft_limit_eur | I1: overdraft_rate | J1: source_channel
A2: BA01 | B2: Banque Régionale (fictional) | C2: Main current account | D2: FR76 •••• •••• •••• 4821 | E2: EUR | F2: 343829.4 | G2: 2026-10-09 18:00 | H2: 150000 | I2: EURIBOR 3M + 2.5% (≈4.6% p.a.) | J2: EBICS
A3: BA02 | B3: Banque Mutuelle (fictional) | C3: Secondary current account (card spending) | D3: FR76 •••• •••• •••• 0937 | E3: EUR | F3: 37411.25 | G3: 2026-10-09 18:00 | H3: 0 | I3: n/a | J3: PSD2 API
E4: Total cash | F4: =SUM(F2:F3) -> 381240.65 | H4: =SUM(H2:H3) -> 150000

Sheet Bank_Weekly
A1: Weekly bank position, all accounts combined. Opening = previous week's closing; closing = opening + receipts − payments (formulas).
A3: iso_week | B3: week_start | C3: week_end | D3: opening_balance_eur | E3: receipts_eur | F3: payments_eur | G3: closing_balance_eur
A4: 2025-W14 | B4: 45747 | C4: 45753 | D4: 376033.78 | E4: 55236 | F4: 190241.81 | G4: =D4+E4-F4 -> 241027.97
A5: 2025-W15 | B5: 45754 | C5: 45760 | D5: =G4 -> 241027.97 | E5: 136812 | F5: 75365.69 | G5: =D5+E5-F5 -> 302474.28
A6: 2025-W16 | B6: 45761 | C6: 45767 | D6: =G5 -> 302474.28 | E6: 115670 | F6: 124026.04 | G6: =D6+E6-F6 -> 294118.24
A7: 2025-W17 | B7: 45768 | C7: 45774 | D7: =G6 -> 294118.24 | E7: 143074 | F7: 79577.93 | G7: =D7+E7-F7 -> 357614.31
A8: 2025-W18 | B8: 45775 | C8: 45781 | D8: =G7 -> 357614.31 | E8: 129204 | F8: 248204.22 | G8: =D8+E8-F8 -> 238614.09
A9: 2025-W19 | B9: 45782 | C9: 45788 | D9: =G8 -> 238614.09 | E9: 85020 | F9: 76538.27 | G9: =D9+E9-F9 -> 247095.82
A10: 2025-W20 | B10: 45789 | C10: 45795 | D10: =G9 -> 247095.82 | E10: 90888 | F10: 138195.12 | G10: =D10+E10-F10 -> 199788.7
A11: 2025-W21 | B11: 45796 | C11: 45802 | D11: =G10 -> 199788.7 | E11: 105122 | F11: 9401.03 | G11: =D11+E11-F11 -> 295509.67
A12: 2025-W22 | B12: 45803 | C12: 45809 | D12: =G11 -> 295509.67 | E12: 170474 | F12: 314445.63 | G12: =D12+E12-F12 -> 151538.04
A13: 2025-W23 | B13: 45810 | C13: 45816 | D13: =G12 -> 151538.04 | E13: 150422 | F13: 63090.58 | G13: =D13+E13-F13 -> 238869.46
A14: 2025-W24 | B14: 45817 | C14: 45823 | D14: =G13 -> 238869.46 | E14: 78998 | F14: 23341.57 | G14: =D14+E14-F14 -> 294525.89
A15: 2025-W25 | B15: 45824 | C15: 45830 | D15: =G14 -> 294525.89 | E15: 142764 | F15: 147834.96 | G15: =D15+E15-F15 -> 289454.93
A16: 2025-W26 | B16: 45831 | C16: 45837 | D16: =G15 -> 289454.93 | E16: 146670 | F16: 195526.03 | G16: =D16+E16-F16 -> 240598.9
... A83: 2026-W41 | B83: 46300 | C83: 46306 | D83: =G82 -> 434308.31 | E83: 31740 | F83: 84807.66 | G83: =D83+E83-F83 -> 381240.65

Sheet Bank_Transactions
A1: transaction_id | B1: date | C1: direction | D1: category | E1: counterparty_name | F1: reference | G1: amount_eur | H1: balance_after_eur
A2: TX00001 | B2: 45748 | C2: Inflow | D2: Customer receipt | E2: Mobilier Pro Rhône | F2: INV-2025-0109 | G2: 9324 | H2: 385357.78
A3: TX00002 | B3: 45748 | C3: Outflow | D3: Insurance (quarterly) | E3: Insurer | G3: -7800 | H3: 377557.78
A4: TX00003 | B4: 45748 | C4: Outflow | D4: Rent (quarterly in advance) | E4: SCI Les Ateliers du Rhône (landlord) | G4: -23400 | H4: 354157.78
A5: TX00004 | B5: 45749 | C5: Inflow | D5: Customer receipt | E5: Bâtir Bureaux SAS | F5: INV-2025-0058 | G5: 12852 | H5: 367009.78
A6: TX00005 | B6: 45749 | C6: Inflow | D6: Customer receipt | E6: Studio Kaya Design | F6: INV-2025-0156 | G6: 3576 | H6: 370585.78
A7: TX00006 | B7: 45749 | C7: Outflow | D7: Card & sundry spending | E7: Fuel, travel, consumables | G7: -5509.47 | H7: 365076.31
A8: TX00007 | B8: 45750 | C8: Outflow | D8: IT, telecom & software | E8: Various (direct debits) | G8: -2880 | H8: 362196.31
A9: TX00008 | B9: 45750 | C9: Outflow | D9: Supplier payment | E9: Quincaillerie Pro Est | F9: BILL-2025-0035 | G9: -5210.2 | H9: 356986.11
A10: TX00009 | B10: 45750 | C10: Outflow | D10: Supplier payment | E10: Aciers Rhône-Métal | F10: BILL-2025-0027 | G10: -31264.46 | H10: 325721.65
A11: TX00010 | B11: 45750 | C11: Inflow | D11: Customer receipt | E11: Officea Distribution | F11: INV-2025-0134 | G11: 4968 | H11: 330689.65
A12: TX00011 | B12: 45750 | C12: Outflow | D12: Supplier payment | E12: Holzwerk Bayern GmbH | F12: BILL-2025-0033 | G12: -114177.68 | H12: 216511.97
A13: TX00012 | B13: 45751 | C13: Inflow | D13: Customer receipt | E13: Espace & Co Aménagement | F13: INV-2025-0084 | G13: 7812 | H13: 224323.97
A14: TX00013 | B14: 45751 | C14: Inflow | D14: Customer receipt | E14: Espace & Co Aménagement | F14: INV-2025-0083 | G14: 16704 | H14: 241027.97
A15: TX00014 | B15: 45754 | C15: Inflow | D15: Customer receipt | E15: Officea Distribution | F15: INV-2025-0139 | G15: 4272 | H15: 245299.97
A16: TX00015 | B16: 45754 | C16: Inflow | D16: Customer receipt | E16: Officea Distribution | F16: INV-2025-0141 | G16: 3540 | H16: 248839.97
A17: TX00016 | B17: 45754 | C17: Inflow | D17: Customer receipt | E17: Bâtir Bureaux SAS | F17: INV-2025-0114 | G17: 22464 | H17: 271303.97
A18: TX00017 | B18: 45754 | C18: Inflow | D18: Customer receipt | E18: Studio Kaya Design | F18: INV-2025-0155 | G18: 9744 | H18: 281047.97
A19: TX00018 | B19: 45754 | C19: Inflow | D19: Customer receipt | E19: CHU Vallée du Rhône | F19: INV-2025-0092 | G19: 14136 | H19: 295183.97
A20: TX00019 | B20: 45754 | C20: Outflow | D20: Bank loan repayment | E20: Banque Régionale (CNC machine loan) | G20: -8900 | H20: 286283.97
A21: TX00020 | B21: 45754 | C21: Inflow | D21: Customer receipt | E21: Officea Distribution | F21: INV-2025-0136 | G21: 15048 | H21: 301331.97
A22: TX00021 | B22: 45755 | C22: Outflow | D22: Energy | E22: Electricity & gas supplier (direct debit) | G22: -9840 | H22: 291491.97
A23: TX00022 | B23: 45756 | C23: Outflow | D23: Card & sundry spending | E23: Fuel, travel, consumables | G23: -5261.42 | H23: 286230.55
A24: TX00023 | B24: 45756 | C24: Inflow | D24: Customer receipt | E24: Mobilier Pro Rhône | F24: INV-2025-0131 | G24: 5376 | H24: 291606.55
A25: TX00024 | B25: 45756 | C25: Inflow | D25: Customer receipt | E25: Studio Kaya Design | F25: INV-2025-0166 | G25: 4548 | H25: 296154.55
A26: TX00025 | B26: 45757 | C26: Outflow | D26: Supplier payment | E26: Feutre & Textiles Lyonnais | F26: BILL-2025-0024 | G26: -31749.82 | H26: 264404.73
A27: TX00026 | B27: 45757 | C27: Outflow | D27: Equipment lease | E27: LeasEquip France | G27: -3840 | H27: 260564.73
A28: TX00027 | B28: 45757 | C28: Outflow | D28: Supplier payment | E28: Quincaillerie Pro Est | F28: BILL-2025-0038 | G28: -4442.65 | H28: 256122.08
A29: TX00028 | B29: 45757 | C29: Outflow | D29: Supplier payment | E29: Vernis Écolo SAS | F29: BILL-2025-0036 | G29: -11331.8 | H29: 244790.28
A30: TX00029 | B30: 45758 | C30: Inflow | D30: Customer receipt | E30: Officea Distribution | F30: INV-2025-0145 | G30: 8712 | H30: 253502.28
A31: TX00030 | B31: 45758 | C31: Inflow | D31: Customer receipt | E31: Bâtir Bureaux SAS | F31: INV-2025-0088 | G31: 36996 | H31: 290498.28
A32: TX00031 | B32: 45758 | C32: Inflow | D32: Customer receipt | E32: Mobilier Pro Rhône | F32: INV-2025-0130 | G32: 11976 | H32: 302474.28
A33: TX00032 | B33: 45761 | C33: Inflow | D33: Customer receipt | E33: Arkade Interiors SRL | F33: INV-2025-0110 | G33: 7610 | H33: 310084.28
A34: TX00033 | B34: 45761 | C34: Inflow | D34: Customer receipt | E34: Mobilier Pro Rhône | F34: INV-2025-0103 | G34: 7752 | H34: 317836.28
A35: TX00034 | B35: 45761 | C35: Inflow | D35: Customer receipt | E35: Officea Distribution | F35: INV-2025-0148 | G35: 14808 | H35: 332644.28
A36: TX00035 | B36: 45761 | C36: Inflow | D36: Customer receipt | E36: Espace & Co Aménagement | F36: INV-2025-0118 | G36: 7368 | H36: 340012.28
A37: TX00036 | B37: 45761 | C37: Inflow | D37: Customer receipt | E37: Studio Kaya Design | F37: INV-2025-0168 | G37: 1800 | H37: 341812.28
A38: TX00037 | B38: 45761 | C38: Inflow | D38: Customer receipt | E38: Espace & Co Aménagement | F38: INV-2025-0093 | G38: 18000 | H38: 359812.28
A39: TX00038 | B39: 45762 | C39: Outflow | D39: Social charges & income tax withheld | E39: URSSAF / AGIRC-ARRCO / DGFiP (PAS) | G39: -82000 | H39: 277812.28
A40: TX00039 | B40: 45762 | C40: Inflow | D40: Customer receipt | E40: Espace & Co Aménagement | F40: INV-2025-0128 | G40: 23652 | H40: 301464.28
A41: TX00040 | B41: 45762 | C41: Inflow | D41: Customer receipt | E41: Mobilier Pro Rhône | F41: INV-2025-0153 | G41: 7464 | H41: 308928.28
A42: TX00041 | B42: 45763 | C42: Outflow | D42: Card & sundry spending | E42: Fuel, travel, consumables | G42: -5491.49 | H42: 303436.79
A43: TX00042 | B43: 45764 | C43: Outflow | D43: Supplier payment | E43: Aciers Rhône-Métal | F43: BILL-2025-0031 | G43: -31467.43 | H43: 271969.36
A44: TX00043 | B44: 45764 | C44: Inflow | D44: Customer receipt | E44: Officea Distribution | F44: INV-2025-0158 | G44: 9096 | H44: 281065.36
A45: TX00044 | B45: 45764 | C45: Inflow | D45: Customer receipt | E45: Nova Interiors SARL | F45: INV-2025-0120 | G45: 4440 | H45: 285505.36
A46: TX00045 | B46: 45764 | C46: Outflow | D46: Supplier payment | E46: Quincaillerie Pro Est | F46: BILL-2025-0039 | G46: -5067.12 | H46: 280438.24
A47: TX00046 | B47: 45764 | C47: Inflow | D47: Customer receipt | E47: Officea Distribution | F47: INV-2025-0152 | G47: 5904 | H47: 286342.24
A48: TX00047 | B48: 45765 | C48: Inflow | D48: Customer receipt | E48: Nova Interiors SARL | F48: INV-2025-0138 | G48: 7776 | H48: 294118.24
A49: TX00048 | B49: 45769 | C49: Inflow | D49: Customer receipt | E49: Studio Kaya Design | F49: INV-2025-0183 | G49: 2808 | H49: 296926.24
A50: TX00049 | B50: 45769 | C50: Inflow | D50: Customer receipt | E50: Officea Distribution | F50: INV-2025-0167 | G50: 10092 | H50: 307018.24
A51: TX00050 | B51: 45769 | C51: Inflow | D51: Customer receipt | E51: Nova Interiors SARL | F51: INV-2025-0127 | G51: 12696 | H51: 319714.24
A52: TX00051 | B52: 45769 | C52: Inflow | D52: Customer receipt | E52: Bâtir Bureaux SAS | F52: INV-2025-0085 | G52: 6996 | H52: 326710.24
A53: TX00052 | B53: 45769 | C53: Inflow | D53: Customer receipt | E53: Officea Distribution | F53: INV-2025-0163 | G53: 5004 | H53: 331714.24
A54: TX00053 | B54: 45769 | C54: Inflow | D54: Customer receipt | E54: Arkade Interiors SRL | F54: INV-2025-0151 | G54: 15710 | H54: 347424.24
... A57: TX00056 | B57: 45770 | C57: Inflow | D57: Customer receipt | E57: Bâtir Bureaux SAS | F57: INV-2025-0126 | G57: 24492 | H57: 386648.24
A58: TX00057 | B58: 45770 | C58: Outflow | D58: Card & sundry spending | E58: Fuel, travel, consumables | G58: -4193.76 | H58: 382454.48
A59: TX00058 | B59: 45770 | C59: Inflow | D59: Customer receipt | E59: Espace & Co Aménagement | F59: INV-2025-0122 | G59: 15216 | H59: 397670.48
A60: TX00059 | B60: 45771 | C60: Outflow | D60: Supplier payment | E60: TransAlp Logistique | F60: BILL-2025-0040 | G60: -18500.05 | H60: 379170.43
A61: TX00060 | B61: 45771 | C61: Outflow | D61: VAT payment | E61: DGFiP | F61: 2025-03 | G61: -56884.12 | H61: 322286.31
A62: TX00061 | B62: 45771 | C62: Inflow | D62: Customer receipt | E62: Hub & Desk Coworking SAS | F62: INV-2025-0177 | G62: 8784 | H62: 331070.31
A63: TX00062 | B63: 45772 | C63: Inflow | D63: Customer receipt | E63: Mobilier Pro Rhône | F63: INV-2025-0154 | G63: 2688 | H63: 333758.31
A64: TX00063 | B64: 45772 | C64: Inflow | D64: Customer receipt | E64: Nova Interiors SARL | F64: INV-2025-0171 | G64: 18000 | H64: 351758.31
A65: TX00064 | B65: 45772 | C65: Inflow | D65: Customer receipt | E65: Studio Kaya Design | F65: INV-2025-0200 | G65: 5856 | H65: 357614.31
A66: TX00065 | B66: 45775 | C66: Inflow | D66: Customer receipt | E66: Officea Distribution | F66: INV-2025-0178 | G66: 9684 | H66: 367298.31
A67: TX00066 | B67: 45775 | C67: Inflow | D67: Customer receipt | E67: Officea Distribution | F67: INV-2025-0173 | G67: 6120 | H67: 373418.31
A68: TX00067 | B68: 45775 | C68: Inflow | D68: Customer receipt | E68: Mobilier Pro Rhône | F68: INV-2025-0169 | G68: 3864 | H68: 377282.31
A69: TX00068 | B69: 45775 | C69: Inflow | D69: Customer receipt | E69: Mobilier Pro Rhône | F69: INV-2025-0143 | G69: 9036 | H69: 386318.31
A70: TX00069 | B70: 45775 | C70: Inflow | D70: Customer receipt | E70: Hub & Desk Coworking SAS | F70: INV-2025-0175 | G70: 7128 | H70: 393446.31
... A73: TX00072 | B73: 45776 | C73: Inflow | D73: Customer receipt | E73: Université Lyon-Est | F73: INV-2025-0194 | G73: 19860 | H73: 421730.31
A74: TX00073 | B74: 45777 | C74: Outflow | D74: Payroll (net salaries) | E74: Employees (38 FTE) | G74: -101500 | H74: 320230.31
A75: TX00074 | B75: 45777 | C75: Outflow | D75: Card & sundry spending | E75: Fuel, travel, consumables | G75: -4506.59 | H75: 315723.72
A76: TX00075 | B76: 45777 | C76: Outflow | D76: Supplier payment | E76: Quincaillerie Pro Est | F76: BILL-2025-0041 | G76: -5012.76 | H76: 310710.96
A77: TX00076 | B77: 45777 | C77: Outflow | D77: Supplier payment | E77: Aciers Rhône-Métal | F77: BILL-2025-0037 | G77: -32832.16 | H77: 277878.8
A78: TX00077 | B78: 45777 | C78: Outflow | D78: Supplier payment | E78: Holzwerk Bayern GmbH | F78: BILL-2025-0043 | G78: -104352.71 | H78: 173526.09
A79: TX00078 | B79: 45779 | C79: Inflow | D79: Customer receipt | E79: Université Lyon-Est | F79: INV-2025-0222 | G79: 17544 | H79: 191070.09
A80: TX00079 | B80: 45779 | C80: Inflow | D80: Customer receipt | E80: CHU Vallée du Rhône | F80: INV-2025-0135 | G80: 19260 | H80: 210330.09
A81: TX00080 | B81: 45779 | C81: Inflow | D81: Customer receipt | E81: Mobilier Pro Rhône | F81: INV-2025-0189 | G81: 10212 | H81: 220542.09
A82: TX00081 | B82: 45779 | C82: Inflow | D82: Customer receipt | E82: Officea Distribution | F82: INV-2025-0182 | G82: 5220 | H82: 225762.09
A83: TX00082 | B83: 45779 | C83: Inflow | D83: Customer receipt | E83: Nova Interiors SARL | F83: INV-2025-0162 | G83: 12852 | H83: 238614.09
A84: TX00083 | B84: 45782 | C84: Inflow | D84: Customer receipt | E84: Officea Distribution | F84: INV-2025-0195 | G84: 18036 | H84: 256650.09
A85: TX00084 | B85: 45782 | C85: Outflow | D85: IT, telecom & software | E85: Various (direct debits) | G85: -2880 | H85: 253770.09
A86: TX00085 | B86: 45782 | C86: Inflow | D86: Customer receipt | E86: Espace & Co Aménagement | F86: INV-2025-0142 | G86: 10788 | H86: 264558.09
A87: TX00086 | B87: 45782 | C87: Inflow | D87: Customer receipt | E87: Studio Kaya Design | F87: INV-2025-0209 | G87: 4344 | H87: 268902.09
A88: TX00087 | B88: 45782 | C88: Outflow | D88: Bank loan repayment | E88: Banque Régionale (CNC machine loan) | G88: -8900 | H88: 260002.09
A89: TX00088 | B89: 45782 | C89: Inflow | D89: Customer receipt | E89: Studio Kaya Design | F89: INV-2025-0210 | G89: 2604 | H89: 262606.09
A90: TX00089 | B90: 45782 | C90: Inflow | D90: Customer receipt | E90: Studio Kaya Design | F90: INV-2025-0208 | G90: 4740 | H90: 267346.09
A91: TX00090 | B91: 45783 | C91: Inflow | D91: Customer receipt | E91: Studio Kaya Design | F91: INV-2025-0216 | G91: 4164 | H91: 271510.09
A92: TX00091 | B92: 45784 | C92: Outflow | D92: Card & sundry spending | E92: Fuel, travel, consumables | G92: -5193.23 | H92: 266316.86
A93: TX00092 | B93: 45784 | C93: Outflow | D93: Supplier payment | E93: Feutre & Textiles Lyonnais | F93: BILL-2025-0034 | G93: -33226.62 | H93: 233090.24
A94: TX00093 | B94: 45784 | C94: Outflow | D94: Supplier payment | E94: Vernis Écolo SAS | F94: BILL-2025-0046 | G94: -11943.78 | H94: 221146.46
A95: TX00094 | B95: 45784 | C95: Outflow | D95: Supplier payment | E95: Quincaillerie Pro Est | F95: BILL-2025-0044 | G95: -4554.64 | H95: 216591.82
A96: TX00095 | B96: 45786 | C96: Inflow | D96: Customer receipt | E96: CHU Vallée du Rhône | F96: INV-2025-0144 | G96: 6228 | H96: 222819.82
A97: TX00096 | B97: 45786 | C97: Inflow | D97: Customer receipt | E97: Mobilier Pro Rhône | F97: INV-2025-0174 | G97: 4740 | H97: 227559.82
A98: TX00097 | B98: 45786 | C98: Outflow | D98: Energy | E98: Electricity & gas supplier (direct debit) | G98: -9840 | H98: 217719.82
A99: TX00098 | B99: 45786 | C99: Inflow | D99: Customer receipt | E99: Officea Distribution | F99: INV-2025-0199 | G99: 6444 | H99: 224163.82
A100: TX00099 | B100: 45786 | C100: Inflow | D100: Customer receipt | E100: Université Lyon-Est | F100: INV-2025-0159 | G100: 15540 | H100: 239703.82
A101: TX00100 | B101: 45786 | C101: Inflow | D101: Customer receipt | E101: Hub & Desk Coworking SAS | F101: INV-2025-0202 | G101: 7392 | H101: 247095.82
A102: TX00101 | B102: 45789 | C102: Inflow | D102: Customer receipt | E102: CHU Vallée du Rhône | F102: INV-2025-0172 | G102: 11412 | H102: 258507.82
A103: TX00102 | B103: 45789 | C103: Inflow | D103: Customer receipt | E103: Officea Distribution | F103: INV-2025-0204 | G103: 9348 | H103: 267855.82
A104: TX00103 | B104: 45789 | C104: Outflow | D104: Equipment lease | E104: LeasEquip France | G104: -3840 | H104: 264015.82
...

Sheet Customers
A1: customer_id | B1: customer_name | C1: segment | D1: country | E1: payment_terms_days | F1: payment_method | G1: credit_limit_eur | H1: avg_days_late_12m | I1: invoices_paid_12m | J1: open_balance_incl_vat | K1: of_which_overdue
A2: C01 | B2: Lumen Hospitality Group | C2: Hospitality (projects) | D2: FR | E2: 60 | F2: Bank transfer | G2: 300000 | H2: =IFERROR(AVERAGEIFS(AR_Invoices!$M:$M,AR_Invoices!$B:$B,$A2,AR_Invoices!$K:$K,"Paid",AR_Invoices!$L:$L,">="&DATE(2025,10,10)),"-") -> 12.666667 | I2: =COUNTIFS(AR_Invoices!$B:$B,$A2,AR_Invoices!$K:$K,"Paid",AR_Invoices!$L:$L,">="&DATE(2025,10,10)) -> 3 | J2: =SUMIFS(AR_Invoices!$H:$H,AR_Invoices!$B:$B,$A2,AR_Invoices!$K:$K,"<>Paid") -> 230400 | K2: =SUMIFS(AR_Invoices!$H:$H,AR_Invoices!$B:$B,$A2,AR_Invoices!$K:$K,"<>Paid",AR_Invoices!$N:$N,">0") -> 0
A3: C02 | B3: Bâtir Bureaux SAS | C3: Office fit-out contractor | D3: FR | E3: 60 | F3: Bank transfer | G3: 120000 | H3: =IFERROR(AVERAGEIFS(AR_Invoices!$M:$M,AR_Invoices!$B:$B,$A3,AR_Invoices!$K:$K,"Paid",AR_Invoices!$L:$L,">="&DATE(2025,10,10)),"-") -> 22.157143 | I3: =COUNTIFS(AR_Invoices!$B:$B,$A3,AR_Invoices!$K:$K,"Paid",AR_Invoices!$L:$L,">="&DATE(2025,10,10)) -> 70 | J3: =SUMIFS(AR_Invoices!$H:$H,AR_Invoices!$B:$B,$A3,AR_Invoices!$K:$K,"<>Paid") -> 325116 | K3: =SUMIFS(AR_Invoices!$H:$H,AR_Invoices!$B:$B,$A3,AR_Invoices!$K:$K,"<>Paid",AR_Invoices!$N:$N,">0") -> 57072
A4: C03 | B4: Espace & Co Aménagement | C4: Office fit-out contractor | D4: FR | E4: 60 | F4: Bank transfer | G4: 80000 | H4: =IFERROR(AVERAGEIFS(AR_Invoices!$M:$M,AR_Invoices!$B:$B,$A4,AR_Invoices!$K:$K,"Paid",AR_Invoices!$L:$L,">="&DATE(2025,10,10)),"-") -> 11.064516 | I4: =COUNTIFS(AR_Invoices!$B:$B,$A4,AR_Invoices!$K:$K,"Paid",AR_Invoices!$L:$L,">="&DATE(2025,10,10)) -> 62 | J4: =SUMIFS(AR_Invoices!$H:$H,AR_Invoices!$B:$B,$A4,AR_Invoices!$K:$K,"<>Paid") -> 171504 | K4: =SUMIFS(AR_Invoices!$H:$H,AR_Invoices!$B:$B,$A4,AR_Invoices!$K:$K,"<>Paid",AR_Invoices!$N:$N,">0") -> 0
A5: C04 | B5: Nova Interiors SARL | C5: Office fit-out contractor | D5: FR | E5: 45 | F5: Bank transfer | G5: 50000 | H5: =IFERROR(AVERAGEIFS(AR_Invoices!$M:$M,AR_Invoices!$B:$B,$A5,AR_Invoices!$K:$K,"Paid",AR_Invoices!$L:$L,">="&DATE(2025,10,10)),"-") -> 25.938462 | I5: =COUNTIFS(AR_Invoices!$B:$B,$A5,AR_Invoices!$K:$K,"Paid",AR_Invoices!$L:$L,">="&DATE(2025,10,10)) -> 65 | J5: =SUMIFS(AR_Invoices!$H:$H,AR_Invoices!$B:$B,$A5,AR_Invoices!$K:$K,"<>Paid") -> 152076 | K5: =SUMIFS(AR_Invoices!$H:$H,AR_Invoices!$B:$B,$A5,AR_Invoices!$K:$K,"<>Paid",AR_Invoices!$N:$N,">0") -> 42708
A6: C05 | B6: Officea Distribution | C6: Furniture distributor | D6: FR | E6: 45 | F6: LCR (bill of exchange) | G6: 90000 | H6: =IFERROR(AVERAGEIFS(AR_Invoices!$M:$M,AR_Invoices!$B:$B,$A6,AR_Invoices!$K:$K,"Paid",AR_Invoices!$L:$L,">="&DATE(2025,10,10)),"-") -> 0.57258065 | I6: =COUNTIFS(AR_Invoices!$B:$B,$A6,AR_Invoices!$K:$K,"Paid",AR_Invoices!$L:$L,">="&DATE(2025,10,10)) -> 124 | J6: =SUMIFS(AR_Invoices!$H:$H,AR_Invoices!$B:$B,$A6,AR_Invoices!$K:$K,"<>Paid") -> 140712 | K6: =SUMIFS(AR_Invoices!$H:$H,AR_Invoices!$B:$B,$A6,AR_Invoices!$K:$K,"<>Paid",AR_Invoices!$N:$N,">0") -> 0
A7: C06 | B7: Mobilier Pro Rhône | C7: Furniture distributor | D7: FR | E7: 45 | F7: Bank transfer | G7: 60000 | H7: =IFERROR(AVERAGEIFS(AR_Invoices!$M:$M,AR_Invoices!$B:$B,$A7,AR_Invoices!$K:$K,"Paid",AR_Invoices!$L:$L,">="&DATE(2025,10,10)),"-") -> 7.622807 | I7: =COUNTIFS(AR_Invoices!$B:$B,$A7,AR_Invoices!$K:$K,"Paid",AR_Invoices!$L:$L,">="&DATE(2025,10,10)) -> 114 | J7: =SUMIFS(AR_Invoices!$H:$H,AR_Invoices!$B:$B,$A7,AR_Invoices!$K:$K,"<>Paid") -> 100704 | K7: =SUMIFS(AR_Invoices!$H:$H,AR_Invoices!$B:$B,$A7,AR_Invoices!$K:$K,"<>Paid",AR_Invoices!$N:$N,">0") -> 4656
A8: C07 | B8: Studio Kaya Design | C8: Office fit-out contractor | D8: FR | E8: 30 | F8: Bank transfer | G8: 20000 | H8: =IFERROR(AVERAGEIFS(AR_Invoices!$M:$M,AR_Invoices!$B:$B,$A8,AR_Invoices!$K:$K,"Paid",AR_Invoices!$L:$L,">="&DATE(2025,10,10)),"-") -> 4.345679 | I8: =COUNTIFS(AR_Invoices!$B:$B,$A8,AR_Invoices!$K:$K,"Paid",AR_Invoices!$L:$L,">="&DATE(2025,10,10)) -> 81 | J8: =SUMIFS(AR_Invoices!$H:$H,AR_Invoices!$B:$B,$A8,AR_Invoices!$K:$K,"<>Paid") -> 50424 | K8: =SUMIFS(AR_Invoices!$H:$H,AR_Invoices!$B:$B,$A8,AR_Invoices!$K:$K,"<>Paid",AR_Invoices!$N:$N,">0") -> 0
A9: C08 | B9: Université Lyon-Est | C9: Public sector | D9: FR | E9: 30 | F9: Bank transfer (Chorus Pro) | G9: 80000 | H9: =IFERROR(AVERAGEIFS(AR_Invoices!$M:$M,AR_Invoices!$B:$B,$A9,AR_Invoices!$K:$K,"Paid",AR_Invoices!$L:$L,">="&DATE(2025,10,10)),"-") -> 9.2083333 | I9: =COUNTIFS(AR_Invoices!$B:$B,$A9,AR_Invoices!$K:$K,"Paid",AR_Invoices!$L:$L,">="&DATE(2025,10,10)) -> 24 | J9: =SUMIFS(AR_Invoices!$H:$H,AR_Invoices!$B:$B,$A9,AR_Invoices!$K:$K,"<>Paid") -> 62556 | K9: =SUMIFS(AR_Invoices!$H:$H,AR_Invoices!$B:$B,$A9,AR_Invoices!$K:$K,"<>Paid",AR_Invoices!$N:$N,">0") -> 0
A10: C09 | B10: CHU Vallée du Rhône | C10: Public sector (hospital) | D10: FR | E10: 50 | F10: Bank transfer (Chorus Pro) | G10: 60000 | H10: =IFERROR(AVERAGEIFS(AR_Invoices!$M:$M,AR_Invoices!$B:$B,$A10,AR_Invoices!$K:$K,"Paid",AR_Invoices!$L:$L,">="&DATE(2025,10,10)),"-") -> 24.653846 | I10: =COUNTIFS(AR_Invoices!$B:$B,$A10,AR_Invoices!$K:$K,"Paid",AR_Invoices!$L:$L,">="&DATE(2025,10,10)) -> 26 | J10: =SUMIFS(AR_Invoices!$H:$H,AR_Invoices!$B:$B,$A10,AR_Invoices!$K:$K,"<>Paid") -> 51996 | K10: =SUMIFS(AR_Invoices!$H:$H,AR_Invoices!$B:$B,$A10,AR_Invoices!$K:$K,"<>Paid",AR_Invoices!$N:$N,">0") -> 16824
A11: C10 | B11: Azur Collection Hôtels | C11: Hospitality (projects) | D11: FR | E11: 45 | F11: Bank transfer | G11: 250000 | H11: =IFERROR(AVERAGEIFS(AR_Invoices!$M:$M,AR_Invoices!$B:$B,$A11,AR_Invoices!$K:$K,"Paid",AR_Invoices!$L:$L,">="&DATE(2025,10,10)),"-") -> 18 | I11: =COUNTIFS(AR_Invoices!$B:$B,$A11,AR_Invoices!$K:$K,"Paid",AR_Invoices!$L:$L,">="&DATE(2025,10,10)) -> 3 | J11: =SUMIFS(AR_Invoices!$H:$H,AR_Invoices!$B:$B,$A11,AR_Invoices!$K:$K,"<>Paid") -> 0 | K11: =SUMIFS(AR_Invoices!$H:$H,AR_Invoices!$B:$B,$A11,AR_Invoices!$K:$K,"<>Paid",AR_Invoices!$N:$N,">0") -> 0
A12: C11 | B12: Hub & Desk Coworking SAS | C12: Direct corporate client | D12: FR | E12: 30 | F12: Bank transfer | G12: 30000 | H12: =IFERROR(AVERAGEIFS(AR_Invoices!$M:$M,AR_Invoices!$B:$B,$A12,AR_Invoices!$K:$K,"Paid",AR_Invoices!$L:$L,">="&DATE(2025,10,10)),"-") -> 11.367347 | I12: =COUNTIFS(AR_Invoices!$B:$B,$A12,AR_Invoices!$K:$K,"Paid",AR_Invoices!$L:$L,">="&DATE(2025,10,10)) -> 49 | J12: =SUMIFS(AR_Invoices!$H:$H,AR_Invoices!$B:$B,$A12,AR_Invoices!$K:$K,"<>Paid") -> 52092 | K12: =SUMIFS(AR_Invoices!$H:$H,AR_Invoices!$B:$B,$A12,AR_Invoices!$K:$K,"<>Paid",AR_Invoices!$N:$N,">0") -> 24900
A13: C12 | B13: Arkade Interiors SRL | C13: Export distributor | D13: BE | E13: 60 | F13: SEPA transfer | G13: 60000 | H13: =IFERROR(AVERAGEIFS(AR_Invoices!$M:$M,AR_Invoices!$B:$B,$A13,AR_Invoices!$K:$K,"Paid",AR_Invoices!$L:$L,">="&DATE(2025,10,10)),"-") -> 5.4390244 | I13: =COUNTIFS(AR_Invoices!$B:$B,$A13,AR_Invoices!$K:$K,"Paid",AR_Invoices!$L:$L,">="&DATE(2025,10,10)) -> 41 | J13: =SUMIFS(AR_Invoices!$H:$H,AR_Invoices!$B:$B,$A13,AR_Invoices!$K:$K,"<>Paid") -> 76890 | K13: =SUMIFS(AR_Invoices!$H:$H,AR_Invoices!$B:$B,$A13,AR_Invoices!$K:$K,"<>Paid",AR_Invoices!$N:$N,">0") -> 21030
I14: Total | J14: =SUM(J2:J13) -> 1414470 | K14: =SUM(K2:K13) -> 167190

Sheet AR_Invoices
A1: invoice_id | B1: customer_id | C1: customer_name | D1: issue_date | E1: due_date | F1: amount_ex_vat | G1: vat | H1: amount_incl_vat | I1: description | J1: project | K1: status | L1: paid_date | M1: days_late | N1: days_overdue_at_cutoff | O1: dispute_note
A2: INV-2025-0054 | B2: C05 | C2: Officea Distribution | D2: 45659 | E2: 45704 | F2: 4040 | G2: 808 | H2: 4848 | I2: Furniture order | K2: Paid | L2: 45705 | M2: 1
A3: INV-2025-0055 | B3: C07 | C3: Studio Kaya Design | D3: 45659 | E3: 45689 | F3: 2250 | G3: 450 | H3: 2700 | I3: Furniture order | K3: Paid | L3: 45691 | M3: 2
A4: INV-2025-0056 | B4: C04 | C4: Nova Interiors SARL | D4: 45659 | E4: 45704 | F4: 14260 | G4: 2852 | H4: 17112 | I4: Furniture order | K4: Paid | L4: 45716 | M4: 12
A5: INV-2025-0057 | B5: C05 | C5: Officea Distribution | D5: 45659 | E5: 45704 | F5: 2550 | G5: 510 | H5: 3060 | I5: Furniture order | K5: Paid | L5: 45705 | M5: 1
A6: INV-2025-0058 | B6: C02 | C6: Bâtir Bureaux SAS | D6: 45659 | E6: 45719 | F6: 10710 | G6: 2142 | H6: 12852 | I6: Furniture order | K6: Paid | L6: 45749 | M6: 30
A7: INV-2025-0059 | B7: C06 | C7: Mobilier Pro Rhône | D7: 45659 | E7: 45704 | F7: 2850 | G7: 570 | H7: 3420 | I7: Furniture order | K7: Paid | L7: 45721 | M7: 17
A8: INV-2025-0060 | B8: C05 | C8: Officea Distribution | D8: 45660 | E8: 45705 | F8: 2650 | G8: 530 | H8: 3180 | I8: Furniture order | K8: Paid | L8: 45705 | M8: 0
A9: INV-2025-0061 | B9: C06 | C9: Mobilier Pro Rhône | D9: 45660 | E9: 45705 | F9: 4550 | G9: 910 | H9: 5460 | I9: Furniture order | K9: Paid | L9: 45702 | M9: -3
A10: INV-2025-0062 | B10: C02 | C10: Bâtir Bureaux SAS | D10: 45660 | E10: 45720 | F10: 24650 | G10: 4930 | H10: 29580 | I10: Furniture order | K10: Paid | L10: 45735 | M10: 15
A11: INV-2025-0063 | B11: C03 | C11: Espace & Co Aménagement | D11: 45663 | E11: 45723 | F11: 13140 | G11: 2628 | H11: 15768 | I11: Furniture order | K11: Paid | L11: 45736 | M11: 13
A12: INV-2025-0064 | B12: C05 | C12: Officea Distribution | D12: 45664 | E12: 45709 | F12: 9160 | G12: 1832 | H12: 10992 | I12: Furniture order | K12: Paid | L12: 45709 | M12: 0
A13: INV-2025-0065 | B13: C04 | C13: Nova Interiors SARL | D13: 45664 | E13: 45709 | F13: 5960 | G13: 1192 | H13: 7152 | I13: Furniture order | K13: Paid | L13: 45716 | M13: 7
... A231: INV-2025-0283 | B231: C06 | C231: Mobilier Pro Rhône | D231: 45789 | E231: 45834 | F231: 4480 | G231: 896 | H231: 5376 | I231: Furniture order | K231: Paid | L231: 45838 | M231: 4
A232: INV-2025-0284 | B232: C01 | C232: Lumen Hospitality Group | D232: 45789 | E232: 45849 | F232: 117000 | G232: 23400 | H232: 140400 | I232: Hôtel Lumen Chambéry – 30% order deposit | J232: LUM-CHB | K232: Paid | L232: 45887 | M232: 38
A233: INV-2025-0285 | B233: C03 | C233: Espace & Co Aménagement | D233: 45790 | E233: 45850 | F233: 13150 | G233: 2630 | H233: 15780 | I233: Furniture order | K233: Paid | L233: 45867 | M233: 17
A234: INV-2025-0286 | B234: C06 | C234: Mobilier Pro Rhône | D234: 45791 | E234: 45836 | F234: 8500 | G234: 1700 | H234: 10200 | I234: Furniture order | K234: Paid | L234: 45846 | M234: 10
A235: INV-2025-0287 | B235: C03 | C235: Espace & Co Aménagement | D235: 45791 | E235: 45851 | F235: 15150 | G235: 3030 | H235: 18180 | I235: Furniture order | K235: Paid | L235: 45859 | M235: 8
A236: INV-2025-0288 | B236: C06 | C236: Mobilier Pro Rhône | D236: 45792 | E236: 45837 | F236: 6200 | G236: 1240 | H236: 7440 | I236: Furniture order | K236: Paid | L236: 45846 | M236: 9
A237: INV-2025-0289 | B237: C06 | C237: Mobilier Pro Rhône | D237: 45792 | E237: 45837 | F237: 9000 | G237: 1800 | H237: 10800 | I237: Furniture order | K237: Paid | L237: 45853 | M237: 16
A238: INV-2025-0290 | B238: C06 | C238: Mobilier Pro Rhône | D238: 45793 | E238: 45838 | F238: 5990 | G238: 1198 | H238: 7188 | I238: Furniture order | K238: Paid | L238: 45841 | M238: 3
A239: INV-2025-0291 | B239: C11 | C239: Hub & Desk Coworking SAS | D239: 45793 | E239: 45823 | F239: 13820 | G239: 2764 | H239: 16584 | I239: Furniture order | K239: Paid | L239: 45824 | M239: 1
A240: INV-2025-0292 | B240: C04 | C240: Nova Interiors SARL | D240: 45793 | E240: 45838 | F240: 14550 | G240: 2910 | H240: 17460 | I240: Furniture order | K240: Paid | L240: 45835 | M240: -3
A241: INV-2025-0293 | B241: C08 | C241: Université Lyon-Est | D241: 45796 | E241: 45826 | F241: 16310 | G241: 3262 | H241: 19572 | I241: Furniture order | K241: Paid | L241: 45838 | M241: 12
A242: INV-2025-0294 | B242: C04 | C242: Nova Interiors SARL | D242: 45796 | E242: 45841 | F242: 7760 | G242: 1552 | H242: 9312 | I242: Furniture order | K242: Paid | L242: 45856 | M242: 15
A243: INV-2025-0295 | B243: C05 | C243: Officea Distribution | D243: 45797 | E243: 45842 | F243: 3430 | G243: 686 | H243: 4116 | I243: Furniture order | K243: Paid | L243: 45842 | M243: 0
A244: INV-2025-0296 | B244: C07 | C244: Studio Kaya Design | D244: 45797 | E244: 45827 | F244: 4260 | G244: 852 | H244: 5112 | I244: Furniture order | K244: Paid | L244: 45832 | M244: 5
... A418: INV-2025-0470 | B418: C07 | C418: Studio Kaya Design | D418: 45908 | E418: 45938 | F418: 1850 | G418: 370 | H418: 2220 | I418: Furniture order | K418: Paid | L418: 45937 | M418: -1
A419: INV-2025-0471 | B419: C01 | C419: Lumen Hospitality Group | D419: 45908 | E419: 45968 | F419: 156000 | G419: 31200 | H419: 187200 | I419: Hôtel Lumen Chambéry – 40% on delivery | J419: LUM-CHB | K419: Paid | L419: 45981 | M419: 13
